Workbook

Sheet 00_README
A1: Nucleus HRMS — Demo Dataset v1.0
A3: Version | B3: v1.1, 15 September 2026. Extends v1.0 with 33 sheets and corrects four data defects. Read 70_Change_Log_v1_1 first, then 69_Coverage_Matrix. Load order for the added sheets is in the change log note. Every formula from v1.0 is unchanged and recalculates identically.
A4: Purpose | B4: Reference data for populating a Nucleus demo tenant. Every record is engineered so that one or more of the 26 client demo points can be shown live, end to end.
A5: Demo client | B5: Vindhya Precision Industries Pvt Ltd — a fictional multi-state manufacturer. Two legal entities, five sites, four states, 68 workers across nine worker classes.
A6: Demo period | B6: Attendance and transactions are dated 01–15 September 2026. Payroll cycle is September 2026. Set the demo tenant clock to 15 September 2026 so open items sit in the right state.
A8: HOW TO USE THIS FILE
A9: 1 | B9: Load sheets in the numbered order. 02–19 are master and configuration data and must exist before any transaction sheet will import.
A10: 2 | B10: Enter the data exactly as given. The values are not arbitrary — thresholds, times, dates and amounts are chosen so the expected results in sheet 21 are reproduced by the product.
A11: 3 | B11: After loading, run the attendance computation for 01–15 September and reconcile against sheet 21 (21_Expected_Attendance). Any row where the product disagrees with the expected status is a defect to fix before the demo, not a data error.
A12: 4 | B12: Sheet 01_Scenario_Map is the demo script. It names, for each of the 26 client points, the exact records to open on screen and what the client should see.
A14: LEGEND — how to read the sheets
A15: Codes ending in a number | B15: Primary keys. Use these exact values; every other sheet references them.
A16: Demo_Point column | B16: Names the client requirement that the row exists to prove. Blank means the row is background data providing realistic volume.
A17: Grey banded rows | B17: Alternate-row shading only. No meaning.
A18: Amber cells | B18: A value that must be entered exactly as given, because a computed result depends on it.
A19: Blank cells | B19: Deliberately empty — either not applicable to that worker class, or a field the product is expected to derive.
A20: Formulas | B20: Sheets 13, 21 and 24 carry formulas that derive values from the configuration sheets. They are there so the dataset checks itself — if you change a threshold in 08, the expected status in 21 updates.
A22: WHAT IS DELIBERATELY NOT HERE
A23: Bank account numbers | B23: Only last four digits are given. Use the product's own test account generator.
A24: Aadhaar, PAN, UAN | B24: Format-valid dummy values only, flagged as such. Never demo with real identifiers.
A25: Photographs and documents | B25: Attach any placeholder; none are supplied.
A27: COVERAGE | B27: All 26 demo points are covered. See 01_Scenario_Map for the record-level mapping.

Sheet 01_Scenario_Map
A1: Demo point | B1: Requirement | C1: Client status | D1: Sheets to load | E1: Records to open | F1: What the client should see | G1: Also load (added in v1.1)
A2: 1 | B2: Multi-punch day, 19h20m across midnight, separate dinner-break report, OT 7h20m | C2: WIP | D2: 20_Punch_Events, 21_Expected_Attendance | E2: E1018 Ravi Kulkarni, 08 Sep 2026 | F2: Two segments (08:00–20:30, 21:15–03:20). Gross 19h20m, dinner break 45m listed separately, OT 7h20m against the 12h shift. Attendance date stays 08 Sep, not split across two days. | G2: 49_Break_Register, 43_Roles_and_Data_Scope, 44_Demo_Users, 52_Shift_Roster
A3: 1 | B3: Team history for a date range, from the team calendar | C3: WIP | D3: 21_Expected_Attendance | E3: Manager E1017 Nikhil Iyer, 01–15 Sep | F3: Filter by manager and date range; export the per-day attendance, OT, late and gate-pass columns. | G3: 49_Break_Register, 43_Roles_and_Data_Scope, 44_Demo_Users, 52_Shift_Roster
A4: 2 | B4: Contractual employees have no rest days and are paid daily wages | C4: WIP | D4: 06_Worker_Classes, 12_Employees, 21_Expected_Attendance | E4: WC-CONT; E1032 Shivanna Muniyappa, 06 and 13 Sep | F4: Sundays appear as Working, not Weekly Off. Wage type Daily on the employee record. | G4: 38_Employment_Categories, 47_Pay_Components, 55_Payroll_Register
A5: 3 | B5: Third-party group: employees have rest days, helpers do not | C5: WIP | D5: 06_Worker_Classes, 12_Employees, 21_Expected_Attendance | E5: E1034 Imran Shaikh (WC-3PE) vs E1036 Lakshmi Rao (WC-3PH), 06 Sep | F5: Same vendor VN-01, same site, same shift. Sunday is Weekly Off for one and Working for the other. | G5: 38_Employment_Categories, 45_Vendors_Contractors, 46_Contractor_Invoices
A6: 4 | B6: Overtime only on rest days or holidays for some employees | C6: WIP | D6: 06_Worker_Classes, 21_Expected_Attendance | E6: E1034 Imran Shaikh, 04 Sep vs 06 Sep | F6: Weekday OT computes to zero despite a 12h+ span. Rest-day working pays the whole span as OT. | G6: 38_Employment_Categories, 55_Payroll_Register
A7: 5 | B7: Early return from leave — mark present, re-credit balance, three-level approval | C7: Done | D7: 18_Leave_Requests, 17_Leave_Ledger | E7: LV-2026-0774, E1043 Neha Mishra | F7: Applied 10 days, returned after 6. Ledger shows the original debit and a reversal credit of the unused days. Approval trail shows Supervisor, then HOD, then HR Head, with an HR edit logged. | G7: 50_Attendance_Regularisation, 53_Leave_Balance_AsOn, 64_Approval_Workflows
A8: 6 | B8: Comp-off lapses 60 days from the credit date | C8: WIP | D8: 19_CompOff_Ledger | E8: CO-2026-0231 (E1028) and CO-2026-0288 (E1028) | F8: Two credits on separate clocks. The July credit lapses 10 Sep; the 06 Sep credit runs to 05 Nov. Show that a single balance-level expiry cannot express this. | G8: 53_Leave_Balance_AsOn — the ledger now reconciles to the comp-off register
A9: 7 | B9: Auto leave credit — bands, accrual, joiner proration, caps, encashment, trainees | C9: WIP | D9: 14_Leave_Types, 15_Leave_Accrual_Policy, 16_Leave_Proration, 17_Leave_Ledger | E9: E1004 (AGM band, 18 EL), E1019 (standard, 1.5 EL/month), E1067 Ankita Bhargava (6 months on 16 Sep, 9 EL), E1060 (April joiner, 4 CL/SL), E1030/E1031 (GET/DET) | F9: Walk the ladder from policy to individual balance. Then attempt a CL+EL combined application and show it blocked by the exclusion rule, and an 11th EL day in one month blocked by the monthly cap. | G9: 39_Leave_Schemes, 40_Leave_Rules_Matrix, 53_Leave_Balance_AsOn, 54_Year_End_Leave_Preview
A10: 8 | B10: HO-generated salary, plant attendance, plant users cannot see rate | C10: Done | D10: 12_Employees, 13_Salary_Structure | E10: E1056 Anand Krishnan — location LOC-CHN, payroll group HO | F10: Sign in as the Chennai plant HR user: attendance visible and editable, every compensation field blank. Sign in as E1007 Deepak Sarangi (payroll): the same record shows full salary. | G10: 43_Roles_and_Data_Scope, 44_Demo_Users, 55_Payroll_Register
A11: 9 | B11: Loan policy — one at a time, guarantors, 4x and 6x basic, guarantor lock, override | C11: Done | D11: 24_Loans, 25_Loan_Guarantors | E11: LN-2026-0041, LN-2026-0009, LN-APP-2026-0014, LN-2026-0012 | F11: E1044 has an active loan at 4x basic. His guarantors E1040 and E1041 are now blocked — show E1041's application rejected with the reason. E1056 qualifies at 6x on 8 years' service. E1050's closed loan released his guarantors. E1022 carries a director-approved special-terms sanction. | G11: 64_Approval_Workflows
A12: 10 | B12: Overtime generated and paid after salary, not with it | C12: Done | D12: 23_Overtime_Register, 26_Payroll_Runs | E12: PR-2026-09-01 and PR-2026-09-02 | F12: Two runs against September. The regular run releases on 30 Sep; the off-cycle OT run on 07 Oct, with its own bank file and its own GL journal line. | G12: 55_Payroll_Register, 56_GL_Journal, 57_Bank_File
A13: 11 | B13: Gate pass — 4 hours a month, maximum two, added to work hours | C13: Done | D13: 22_Gate_Pass, 21_Expected_Attendance | E13: GP-2026-0141, GP-2026-0155, GP-2026-0163 (E1023) | F13: Two approved passes of 2h each. Both dates show the gap as a break and the same minutes credited back, so net hours are unaffected. The third request is rejected on the monthly ceiling. | G13: 49_Break_Register, 67_Reports_Register
... A15: 13 | B15: Auto shift capture from the in-punch | C15: Done | D15: 07_Shifts, 21_Expected_Attendance | E15: E1020 Arjun Bhat, 04 and 11 Sep | F15: Assigned SH-A, punched inside the SH-B window. Shift_Applied differs from Shift_Assigned and the 12h threshold is applied against the inferred shift. | G15: 52_Shift_Roster, 51_Attendance_Exceptions
A16: 14 | B16: Link the ERP employee master by API | C16: Done | D16: 36_ERP_Inbound_Master | E16: Batch ERP-SYNC-2026-09-14, six rows | F16: Three clean upserts, one field-ownership conflict held for review, one unmatched employee code, one duplicate payload rejected on hash. Show the ownership map deciding who wins.
A17: 15 | B17: Account posting to ERP | C17: Done | D17: 35_GL_Mapping, 26_Payroll_Runs | E17: September journal, both runs | F17: Every component mapped to an account and cost centre. Show the run blocked when a mapping is missing, then the balanced journal and the reconciliation to the bank file total. | G17: 56_GL_Journal, 57_Bank_File, 35_GL_Mapping — four accounts added so the journal balances
A18: 16 | B18: Full and final on the last working day, with no-dues clearance | C18: WIP | D18: 27_Exit_Clearance | E18: E1068 Dinesh Vaidya (LWD 30 Sep), E1042 Swapnil Kadam (LWD 18 Sep) | F18: Nine checklist items with named owners, four blocking. E1042 has two open blocking items so F&F is held; E1068 is fully cleared and settles on the last working day. | G18: 58_FnF_Settlement, 33_Assets recovery value, 57_Bank_File
A19: 17 | B19: Statutory compliance, Factory Act forms and returns | C19: Done | D19: 28_Statutory_Calendar, 29_Statutory_Forms | E19: Sep–Nov obligations across four states | F19: PT differs by state on the same run. Show the register set for a Karnataka factory against Tamil Nadu. | G19: 48_PT_Slabs, 62_Documents, 45_Vendors_Contractors
A20: 18 | B20: Star employees | C20: Done | D20: 30_Recognition_Referral | E20: RC-2026-Q2-004, RC-2026-Q2-007 | F20: Programme, citation, period and the award component flowing to payroll as an earning.
A21: 19 | B21: Referral process and awards | C21: Done | D21: 30_Recognition_Referral | E21: RF-2026-0021 (part paid), RF-2026-0026 (balance due on confirmation) | F21: Referral tracked from candidate through to a payroll payout in a named run. | G21: 59_Candidates_and_Offers, 60_Confirmations
A22: 20 | B22: Announcements — birthday, star employee, new joiner, referral, management message | C22: Done | D22: 31_Announcements | E22: AN-2026-0088 through AN-2026-0094 | F22: Auto-generated from events, with audience rules and channel selection including WhatsApp.
A23: 21 | B23: Appointment and other HR letters | C23: Done | D23: 32_Letter_Templates | E23: TPL-APPT-02 issued to E1066, TPL-CONF-01 issued to E1058 | F23: Template version retained against the issued letter, so a reprint two years later is provable.
A24: 22 | B24: Organisation chart, department-wise hierarchy | C24: Done | D24: 04_Org_Units, 12_Employees | E24: OU-100 down to OU-180, three levels | F24: Drill the chart, then filter headcount by org unit and location.
A25: 23 | B25: Induction training at joining, and asset | C25: Done | D25: 33_Assets, 34_Induction_Learning | E25: E1066 Abhinav Rastogi, joined 01 Sep | F25: Induction path assigned on joining, three assets allocated, and the same assets appearing as blocking clearance items at exit. | G25: 60_Confirmations, 61_Preboarding_Chain, 62_Documents
A26: 24 | B26: Recruitment — position code for replacement | C26: Done | D26: 11_Positions, 37_Requisitions | E26: REQ-2026-0037 against vacated POS-2214; REQ-2026-0041 as an addition | F26: The replacement consumes no fresh sanction. The addition is blocked because Machining is at sanctioned strength. | G26: 59_Candidates_and_Offers, 61_Preboarding_Chain
A27: 25 | B27: Approved manpower, department wise | C27: Done | D27: 10_Sanctioned_Manpower | E27: OU-111 Machining at Peenya — 24 sanctioned, 24 filled | F27: Sanctioned against actual against open requisitions, by department, designation and location. | G27: 59_Candidates_and_Offers
A28: 26 | B28: Joining form under the Factory Act, Form F | C28: WIP | D28: 29_Statutory_Forms, 34_Induction_Learning | E28: FRM-F-2026-0112 for E1066 | F28: Generated inside the joining chain, not chased afterwards. Owner for this item is to be assigned. | G28: 61_Preboarding_Chain
A30: This sheet is the demo script. Run the points in the order your client raised them, not in numeric order.

Sheet 02_Legal_Entities
A1: Entity code | B1: Registered name | C1: CIN / LLPIN | D1: Registered office | E1: PAN | F1: PF / Labour code | G1: GSTIN | H1: Financial year | I1: Status
A2: LE-01 | B2: Vindhya Precision Industries Pvt Ltd | C2: U29253KA2011PTC058411 | D2: Bengaluru, Karnataka | E2: AAACV4471K | F2: KA/BLR/0045512 | G2: 29AAACV4471K1ZP | H2: Apr-Mar | I2: Active
A3: LE-02 | B3: Vindhya Components Pvt Ltd | C3: U29309TG2016PTC112904 | D3: Hyderabad, Telangana | E3: AAECV8820M | F3: TS/HYD/0021877 | G3: 36AAECV8820M1ZR | H3: Apr-Mar | I3: Active

Sheet 03_Locations
A1: Location code | B1: Location name | C1: Entity | D1: City | E1: State | F1: State code | G1: Establishment type | H1: PIN | I1: Factory licence | J1: PT slab set | K1: LWF set | L1: Payroll group | M1: Factory Act applies
A2: LOC-BLR | B2: Bengaluru Corporate Office | C2: LE-01 | D2: Bengaluru | E2: Karnataka | F2: KA | G2: Office | H2: 560001 | I2: Not applicable | J2: KA-PT-Slab-2026 | K2: KA-LWF | L2: HO | M2: N
A3: LOC-PLA | B3: Peenya Works | C3: LE-01 | D3: Bengaluru | E3: Karnataka | F3: KA | G3: Factory | H3: 560058 | I3: KA/FAC/2013/00891 | J3: KA-PT-Slab-2026 | K3: KA-LWF | L3: PLANT-BLR | M3: Y
A4: LOC-PUN | B4: Chakan Works | C4: LE-01 | D4: Pune | E4: Maharashtra | F4: MH | G4: Factory | H4: 410501 | I4: MH/FAC/2015/03327 | J4: MH-PT-Slab-2026 | K4: MH-LWF | L4: PLANT-PUN | M4: Y
A5: LOC-HYD | B5: Medchal Works | C5: LE-02 | D5: Hyderabad | E5: Telangana | F5: TS | G5: Factory | H5: 501401 | I5: TS/FAC/2016/01142 | J5: TS-PT-Slab-2026 | K5: TS-LWF | L5: PLANT-HYD | M5: Y
A6: LOC-CHN | B6: Oragadam Works | C6: LE-02 | D6: Chennai | E6: Tamil Nadu | F6: TN | G6: Factory | H6: 602105 | I6: TN/FAC/2015/02218 | J6: TN-PT-Slab-2026 | K6: TN-LWF | L6: PLANT-CHN | M6: Y

Sheet 04_Org_Units
A1: Org unit code | B1: Org unit name | C1: Parent | D1: Level | E1: Type | F1: Primary location | G1: Cost centre
A2: OU-100 | B2: Executive Office | D2: 1 | E2: Function | F2: LOC-BLR | G2: CC-1000
A3: OU-110 | B3: Manufacturing | C3: OU-100 | D3: 2 | E3: Function | G3: CC-2000
A4: OU-111 | B4: Machining | C4: OU-110 | D4: 3 | E4: Sub-function | G4: CC-2100
A5: OU-112 | B5: Assembly | C5: OU-110 | D5: 3 | E5: Sub-function | G5: CC-2200
A6: OU-113 | B6: Quality Assurance | C6: OU-110 | D6: 3 | E6: Sub-function | G6: CC-2300
A7: OU-114 | B7: Maintenance | C7: OU-110 | D7: 3 | E7: Sub-function | G7: CC-2400
A8: OU-120 | B8: Supply Chain | C8: OU-100 | D8: 2 | E8: Function | G8: CC-3000
A9: OU-121 | B9: Stores | C9: OU-120 | D9: 3 | E9: Sub-function | G9: CC-3100
A10: OU-122 | B10: Logistics | C10: OU-120 | D10: 3 | E10: Sub-function | G10: CC-3200
A11: OU-130 | B11: Engineering | C11: OU-100 | D11: 2 | E11: Function | G11: CC-4000
A12: OU-140 | B12: Sales & Marketing | C12: OU-100 | D12: 2 | E12: Function | F12: LOC-BLR | G12: CC-5000
A13: OU-150 | B13: Finance & Accounts | C13: OU-100 | D13: 2 | E13: Function | F13: LOC-BLR | G13: CC-6000
A14: OU-160 | B14: Human Resources | C14: OU-100 | D14: 2 | E14: Function | G14: CC-6500
A15: OU-170 | B15: Information Technology | C15: OU-100 | D15: 2 | E15: Function | F15: LOC-BLR | G15: CC-7000
A16: OU-180 | B16: Environment, Health & Safety | C16: OU-110 | D16: 3 | E16: Sub-function | G16: CC-2500

Sheet 05_Designations
A1: Designation code | B1: Title | C1: Band | D1: Exempt from grace deduction | E1: Leave band | F1: Overtime default | G1: Notice period (days) | H1: Grade rank | I1: Default leave scheme | J1: Rule the rank serves
A2: DES-01 | B2: Managing Director | C2: E | D2: Y | E2: AGM_AND_ABOVE | F2: None | G2: 90 | H2: 100 | I2: LS-AGM | J2: AGM and above — 18 EL / 6 CL / 6 SL on 1 Jan (LP-01 to LP-03); also grace-exempt
A3: DES-02 | B3: Vice President | C3: E | D3: Y | E3: AGM_AND_ABOVE | F3: None | G3: 90 | H3: 90 | I3: LS-AGM | J3: AGM and above — 18 EL / 6 CL / 6 SL on 1 Jan (LP-01 to LP-03); also grace-exempt
A4: DES-03 | B4: General Manager | C4: D | D4: Y | E4: AGM_AND_ABOVE | F4: None | G4: 90 | H4: 80 | I4: LS-AGM | J4: AGM and above — 18 EL / 6 CL / 6 SL on 1 Jan (LP-01 to LP-03); also grace-exempt
A5: DES-04 | B5: Assistant General Manager | C5: D | D5: Y | E5: AGM_AND_ABOVE | F5: None | G5: 60 | H5: 70 | I5: LS-AGM | J5: AGM and above — 18 EL / 6 CL / 6 SL on 1 Jan (LP-01 to LP-03); also grace-exempt
A6: DES-05 | B6: Senior Manager | C6: C | D6: Y | E6: STANDARD | F6: None | G6: 60 | H6: 60 | I6: LS-STD | J6: Assistant Manager and above — exempt from the late-mark deduction
A7: DES-06 | B7: Manager | C7: C | D7: Y | E7: STANDARD | F7: None | G7: 60 | H7: 55 | I7: LS-STD | J7: Assistant Manager and above — exempt from the late-mark deduction
A8: DES-07 | B8: Assistant Manager | C8: C | D8: Y | E8: STANDARD | F8: None | G8: 30 | H8: 50 | I8: LS-STD | J8: Assistant Manager and above — exempt from the late-mark deduction
A9: DES-08 | B9: Senior Engineer | C9: B | D9: N | E9: STANDARD | F9: All | G9: 30 | H9: 40 | I9: LS-STD
A10: DES-09 | B10: Engineer | C10: B | D10: N | E10: STANDARD | F10: All | G10: 30 | H10: 35 | I10: LS-STD
A11: DES-10 | B11: Senior Officer | C11: B | D11: N | E11: STANDARD | F11: All | G11: 30 | H11: 34 | I11: LS-STD
A12: DES-11 | B12: Officer | C12: A | D12: N | E12: STANDARD | F12: All | G12: 30 | H12: 30 | I12: LS-STD
A13: DES-12 | B13: Senior Operator | C13: A | D13: N | E13: STANDARD | F13: All | G13: 30 | H13: 25 | I13: LS-STD
A14: DES-13 | B14: Operator | C14: A | D14: N | E14: STANDARD | F14: All | G14: 30 | H14: 20 | I14: LS-STD
A15: DES-14 | B15: Technician | C15: A | D15: N | E15: STANDARD | F15: All | G15: 30 | H15: 20 | I15: LS-STD
A16: DES-15 | B16: Graduate Engineer Trainee | C16: T | D16: N | E16: TRAINEE_GET | F16: None | G16: 15 | H16: 15 | I16: LS-TRN
A17: DES-16 | B17: Diploma Engineer Trainee | C17: T | D17: N | E17: TRAINEE_DET | F17: None | G17: 15 | H17: 14 | I17: LS-TRN
A18: DES-17 | B18: Helper | C18: H | D18: N | E18: NOT_ELIGIBLE | F18: RestDayHolidayOnly | G18: 7 | H18: 5 | I18: LS-NONE
A19: DES-18 | B19: Contract Operator | C19: H | D19: N | E19: NOT_ELIGIBLE | F19: All | G19: 7 | H19: 5 | I19: LS-NONE
A20: DES-19 | B20: Apprentice | C20: T | D20: N | E20: NOT_ELIGIBLE | F20: None | G20: 7 | H20: 10 | I20: LS-NONE
A21: DES-20 | B21: Retainer Consultant | C21: C | D21: Y | E21: NOT_ELIGIBLE | F21: None | G21: 30 | H21: 50 | I21: LS-NONE | J21: Assistant Manager and above — exempt from the late-mark deduction
A23: Exempt from grace deduction is Y for Assistant Manager and above, per client rule. Leave band drives the accrual policy in sheet 15. ADDED v1.1: Grade rank is the single numeric ladder every "and above" rule must compare. AGM and above is rank >= 70; Assistant Manager and above is rank >= 50. No rule may match a designation name.

Sheet 06_Worker_Classes
A1: Class code | B1: Label | C1: Has rest days | D1: Rest day pattern | E1: Wage type | F1: Overtime eligibility | G1: Leave eligible | H1: Statutory set | I1: Obligation | J1: Demo point
A2: WC-PERM | B2: Permanent | C2: Y | D2: Sunday weekly off | E2: Monthly | F2: All | G2: Y | H2: PF+ESI+PT+LWF+Gratuity | I2: Direct
A3: WC-FTC | B3: Fixed Term Contract | C3: Y | D3: Sunday weekly off | E3: Monthly | F3: All | G3: Y | H3: PF+ESI+PT+LWF+Gratuity (FTC treatment) | I3: Direct
A4: WC-TRN | B4: Trainee | C4: Y | D4: Sunday weekly off | E4: Monthly | F4: None | G4: Y (CL only, per band) | H4: PF+ESI+PT | I4: Direct | J4: Point 7
A5: WC-APP | B5: Apprentice | C5: Y | D5: Sunday weekly off | E5: Stipend | F5: None | G5: N | H5: Apprentices Act — no PF/ESI | I5: Direct
A6: WC-CONT | B6: Contractual — daily wage | C6: N | D6: No rest day | E6: Daily | F6: All | G6: N | H6: PF+ESI+PT | I6: Direct | J6: Point 2
A7: WC-3PE | B7: Third-Party Employee | C7: Y | D7: Sunday weekly off | E7: Monthly | F7: RestDayHolidayOnly | G7: N | H7: Contractor's PF/ESI — verification held | I7: Principal Employer | J7: Points 3, 4
A8: WC-3PH | B8: Third-Party Helper | C8: N | D8: No rest day | E8: Daily | F8: RestDayHolidayOnly | G8: N | H8: Contractor's PF/ESI — verification held | I8: Principal Employer | J8: Point 3
A9: WC-CONS | B9: Retainer Consultant | C9: N | D9: Not applicable | E9: Retainer | F9: None | G9: N | H9: TDS 194J only | I9: Not applicable
A10: WC-GIG | B10: Gig / Platform Worker | C10: N | D10: Not applicable | E10: Per engagement | F10: None | G10: N | H10: Social Security Code — aggregator contribution | I10: Aggregator
A12: Worker class carries time and pay policy, not just statutory applicability. Every attribute here is overridable on the individual assignment with a reason.

Sheet 07_Shifts
A1: Shift code | B1: Shift name | C1: Shift group | D1: Start | E1: End | F1: Duration (min) | G1: Break — recorded, paid (min) | H1: Break — deducted (min) | I1: Inference window — earliest in | J1: Inference window — latest in | K1: Crosses midnight | L1: Half day if net below (min) | M1: Absent if net below (min) | N1: OT starts after (min) | O1: Auto detect enabled | P1: Thresholds source
A2: SH-A | B2: A Shift — Day 12h | C2: PLANT12 | D2: 08:00 | E2: 20:00 | F2: 720 | G2: 60 | H2: 0 | I2: 06:30 | J2: 09:29 | K2: N | L2: 690 | M2: 390 | N2: 720 | O2: Y | P2: Mirrors 08_Attendance_Rules for this shift length. F-SHF-01 requires the thresholds to live on the shift, not in code.
A3: SH-B | B3: B Shift — Night 12h | C3: PLANT12 | D3: 20:00 | E3: 08:00 | F3: 720 | G3: 60 | H3: 0 | I3: 19:00 | J3: 22:29 | K3: Y | L3: 690 | M3: 390 | N3: 720 | O3: Y | P3: Mirrors 08_Attendance_Rules for this shift length. F-SHF-01 requires the thresholds to live on the shift, not in code.
A4: SH-C | B4: C Shift — Early 10h | C4: PLANT10 | D4: 07:00 | E4: 17:00 | F4: 600 | G4: 45 | H4: 0 | I4: 05:30 | J4: 07:59 | K4: N | L4: 570 | M4: 360 | N4: 600 | O4: Y | P4: Mirrors 08_Attendance_Rules for this shift length. F-SHF-01 requires the thresholds to live on the shift, not in code.
A5: SH-D | B5: D Shift — Late 10h | C5: PLANT10 | D5: 17:00 | E5: 03:00 | F5: 600 | G5: 45 | H5: 0 | I5: 16:00 | J5: 18:29 | K5: Y | L5: 570 | M5: 360 | N5: 600 | O5: Y | P5: Mirrors 08_Attendance_Rules for this shift length. F-SHF-01 requires the thresholds to live on the shift, not in code.
A6: SH-E | B6: General Shift 9h | C6: STAFF9 | D6: 09:00 | E6: 18:00 | F6: 540 | G6: 45 | H6: 0 | I6: 07:30 | J6: 11:00 | K6: N | L6: 510 | M6: 300 | N6: 540 | O6: Y | P6: Mirrors 08_Attendance_Rules for this shift length. F-SHF-01 requires the thresholds to live on the shift, not in code.
A7: SH-F | B7: Office Shift 8h | C7: OFFICE8 | D7: 09:30 | E7: 17:30 | F7: 480 | G7: 30 | H7: 0 | I7: 08:00 | J7: 11:30 | K7: N | L7: 450 | M7: 270 | N7: 480 | O7: N | P7: Mirrors 08_Attendance_Rules for this shift length. F-SHF-01 requires the thresholds to live on the shift, not in code.
A9: Breaks are recorded and reported but NOT deducted for this client — see sheet 21. Inference windows do not overlap inside a shift group. An in-punch inside another shift's window within the same group causes that shift to be adopted for the day (demo point 13). ADDED v1.1: half-day, absent and OT thresholds now sit on the shift itself, as F-SHF-01 requires. They are the same numbers as 08_Attendance_Rules — if the two ever disagree, the shift master wins and 08 is the audit copy. SH-F is office staff and auto-detection is off for it.

Sheet 08_Attendance_Rules
A1: Shift hours | B1: Half day if net below (min) | C1: Absent if net below (min) | D1: Grace in (min) | E1: Grace out (min) | F1: Late instances allowed per month | G1: Long night finishes after | H1: Next-day relief until | I1: Stated as
A2: 12 | B2: 690 | C2: 390 | D2: 15 | E2: 15 | F2: 3 | G2: 03:00 | H2: 09:30 | I2: 11:30 net for half day, 6:30 for absent
A3: 10 | B3: 570 | C3: 360 | D3: 15 | E3: 15 | F3: 3 | G3: 03:00 | H3: 09:30 | I3: 9:30 net for half day, 6:00 for absent
A4: 9 | B4: 510 | C4: 300 | D4: 15 | E4: 15 | F4: 3 | G4: 03:00 | H4: 09:30 | I4: 8:30 net for half day, 5:00 for absent
A5: 8 | B5: 450 | C5: 270 | D5: 15 | E5: 15 | F5: 3 | G5: 03:00 | H5: 09:30 | I5: 7:30 net for half day, 4:30 for absent
A7: These four rows are the client's stated rule. Sheet 21 reads them by INDEX/MATCH, so changing a threshold here updates every expected status. Overtime basis for this client is the GROSS span, not net hours — see 21_Expected_Attendance.

Sheet 09_Holiday_Calendar
A1: Date | B1: Holiday | C1: Applicable locations | D1: Type
A2: 2026-01-01 | B2: New Year's Day | C2: LOC-BLR,LOC-PUN,LOC-HYD,LOC-CHN | D2: Festival
A3: 2026-01-14 | B3: Makara Sankranti / Pongal | C3: LOC-BLR,LOC-HYD,LOC-CHN | D3: Festival
A4: 2026-01-26 | B4: Republic Day | C4: ALL | D4: National
A5: 2026-03-04 | B5: Holi | C5: LOC-PUN | D5: Festival
A6: 2026-04-14 | B6: Dr Ambedkar Jayanti / Tamil New Year | C6: LOC-BLR,LOC-PUN,LOC-CHN | D6: Festival
A7: 2026-05-01 | B7: May Day | C7: ALL | D7: Statutory
A8: 2026-08-15 | B8: Independence Day | C8: ALL | D8: National
A9: 2026-08-26 | B9: Ganesh Chaturthi | C9: LOC-BLR,LOC-PUN | D9: Festival
A10: 2026-09-15 | B10: Vinayaka Chaturthi | C10: LOC-HYD,LOC-CHN | D10: Festival
A11: 2026-10-02 | B11: Gandhi Jayanti | C11: ALL | D11: National
A12: 2026-10-20 | B12: Ayudha Puja / Dussehra | C12: LOC-BLR,LOC-CHN,LOC-HYD | D12: Festival
... A14: 2026-12-25 | B14: Christmas | C14: LOC-CHN | D14: Festival
A16: Holidays differ by location. 15 Sep 2026 is a holiday at Hyderabad and Chennai only, which is visible in the September attendance for E1056.

Sheet 10_Sanctioned_Manpower
A1: Record | B1: Org unit | C1: Designation | D1: Location | E1: Sanctioned | F1: Filled | G1: Open requisitions | H1: Effective from | I1: Approved by | J1: Demo point
A2: SM-001 | B2: OU-111 | C2: DES-13 | D2: LOC-PLA | E2: 24 | F2: 24 | G2: 1 | H2: 2026-04-01 | I2: E1002 | J2: Point 25
A3: SM-002 | B3: OU-111 | C3: DES-08 | D3: LOC-PLA | E3: 4 | F3: 3 | G3: 1 | H3: 2026-04-01 | I3: E1002 | J3: Point 24
A4: SM-003 | B4: OU-112 | C4: DES-12 | D4: LOC-PLA | E4: 12 | F4: 11 | G4: 0 | H4: 2026-04-01 | I4: E1002
A5: SM-004 | B5: OU-113 | C5: DES-11 | D5: LOC-PLA | E5: 6 | F5: 6 | G5: 0 | H5: 2026-04-01 | I5: E1002 | J5: Updated v1.1 — E1069 joined against this line, so Quality Officers at Peenya are now at sanction
A6: SM-005 | B6: OU-114 | C6: DES-14 | D6: LOC-PLA | E6: 8 | F6: 8 | G6: 0 | H6: 2026-04-01 | I6: E1002
A7: SM-006 | B7: OU-112 | C7: DES-13 | D7: LOC-PUN | E7: 18 | F7: 16 | G7: 2 | H7: 2026-04-01 | I7: E1002
A8: SM-007 | B8: OU-111 | C8: DES-08 | D8: LOC-PUN | E8: 3 | F8: 3 | G8: 0 | H8: 2026-04-01 | I8: E1002
A9: SM-008 | B9: OU-113 | C9: DES-09 | D9: LOC-HYD | E9: 5 | F9: 4 | G9: 0 | H9: 2026-04-01 | I9: E1002
A10: SM-009 | B10: OU-111 | C10: DES-13 | D10: LOC-CHN | E10: 20 | F10: 18 | G10: 1 | H10: 2026-04-01 | I10: E1002
A11: SM-010 | B11: OU-122 | C11: DES-11 | D11: LOC-PUN | E11: 3 | F11: 3 | G11: 0 | H11: 2026-04-01 | I11: E1002
A13: Machining operators at Peenya are at full sanctioned strength — this is what blocks the addition requisition REQ-2026-0041 in sheet 26. UPDATED v1.1: SM-004 shows 6 of 6 filled after E1069 joined; the open requisition against it is closed.

Sheet 11_Positions
A1: Position code | B1: Title | C1: Org unit | D1: Location | E1: Grade | F1: Cost centre | G1: Status | H1: Current incumbent | I1: Last incumbent | J1: Vacated on | K1: Demo point
A2: POS-2214 | B2: Senior Engineer — Machining | C2: OU-111 | D2: LOC-PLA | E2: B | F2: CC-2100 | G2: Vacant | I2: E1071 | J2: 2026-08-22 | K2: Point 24
A3: POS-2216 | B3: Senior Engineer — Machining | C3: OU-111 | D3: LOC-PLA | E3: B | F3: CC-2100 | G3: Filled | H3: E1018
A4: POS-2301 | B4: Officer — Quality | C4: OU-113 | D4: LOC-PLA | E4: A | F4: CC-2300 | G4: Filled | H4: E1023
A5: POS-2410 | B5: Technician — Maintenance | C5: OU-114 | D5: LOC-PLA | E5: A | F5: CC-2400 | G5: Filled | H5: E1026
A6: POS-3121 | B6: Officer — Stores | C6: OU-121 | D6: LOC-PLA | E6: A | F6: CC-3100 | G6: Filled | H6: E1037
A7: POS-2225 | B7: Operator — Assembly | C7: OU-112 | D7: LOC-PUN | E7: A | F7: CC-2200 | G7: Vacant | I7: E1072 | J7: 2026-09-02
A8: POS-2226 | B8: Operator — Assembly | C8: OU-112 | D8: LOC-PUN | E8: A | F8: CC-2200 | G8: Vacant | I8: E1073 | J8: 2026-08-11
A9: POS-4011 | B9: Engineer — Engineering | C9: OU-130 | D9: LOC-BLR | E9: B | F9: CC-4000 | G9: Filled | H9: E1065
A10: POS-3210 | B10: Officer — Logistics | C10: OU-122 | D10: LOC-PUN | E10: A | F10: CC-3200 | G10: Filled | H10: E1066
A11: POS-2115 | B11: Operator — Machining | C11: OU-111 | D11: LOC-CHN | E11: A | F11: CC-2100 | G11: Vacant | I11: E1074 | J11: 2026-07-30
A13: A position exists with or without a person in it. E1071 to E1074 are prior incumbents who have left and are not in the employee sheet — they exist only as vacancy history.

Sheet 12_Employees
A1: Employee code | B1: Full name | C1: Gender | D1: Date of birth | E1: Date of joining | F1: Entity | G1: Location | H1: Org unit | I1: Designation | J1: Band | K1: Worker class | L1: Shift group | M1: Default shift | N1: Manager code | O1: Manager name | P1: Payroll group | Q1: Vendor | R1: Status | S1: UAN (dummy) | T1: Bank a/c last 4 | U1: Demo point / note | V1: Employment category | W1: Employment sub-category | X1: Rest day applicable | Y1: Rest day pattern | Z1: Wage basis | AA1: OT eligible | AB1: OT eligibility basis | AC1: OT rate multiplier | AD1: Leave scheme | AE1: Leave band | AF1: Trainee type | AG1: COFF lapse days | AH1: EL eligibility from | AI1: Payroll processing location | AJ1: Attendance location | AK1: Continuous service years | AL1: Grade rank | AM1: Exempt from grace deduction | AN1: Gate pass hours per month | AO1: Gate pass count per month | AP1: ERP employee key | AQ1: Resolution note
A2: E1001 | B2: Arvind Raghunathan | C2: M | D2: 1968-03-12 | E2: 2012-04-02 | F2: LE-01 | G2: LOC-BLR | H2: OU-100 | I2: DES-01 | J2: E | K2: WC-PERM | L2: OFFICE8 | M2: SH-F | P2: HO | R2: Active | S2: UAN000100037037 | T2: XXXX7017 | V2: CAT-PERM — Permanent | X2: Y | Y2: Sunday weekly off | Z2: Monthly | AA2: Y | AB2: All days | AC2: 2 | AD2: LS-AGM | AE2: AGM_AND_ABOVE | AG2: 60 | AH2: Not applicable — annual credit on 1 January | AI2: LOC-BLR | AJ2: LOC-BLR | AK2: 14.45 | AL2: 100 | AM2: Y | AN2: 4 | AO2: 2 | AP2: VPI-1001
A3: E1002 | B3: Meenakshi Sundaram | C3: F | D3: 1972-09-04 | E3: 2014-07-01 | F3: LE-01 | G3: LOC-BLR | H3: OU-110 | I3: DES-02 | J3: E | K3: WC-PERM | L3: OFFICE8 | M3: SH-F | N3: E1001 | O3: Arvind Raghunathan | P3: HO | R3: Active | S3: UAN000100037074 | T3: XXXX7034 | V3: CAT-PERM — Permanent | X3: Y | Y3: Sunday weekly off | Z3: Monthly | AA3: Y | AB3: All days | AC3: 2 | AD3: LS-AGM | AE3: AGM_AND_ABOVE | AG3: 60 | AH3: Not applicable — annual credit on 1 January | AI3: LOC-BLR | AJ3: LOC-BLR | AK3: 12.21 | AL3: 90 | AM3: Y | AN3: 4 | AO3: 2 | AP3: VPI-1002
A4: E1003 | B4: Farhan Qureshi | C4: M | D4: 1974-01-28 | E4: 2015-11-16 | F4: LE-01 | G4: LOC-BLR | H4: OU-150 | I4: DES-02 | J4: E | K4: WC-PERM | L4: OFFICE8 | M4: SH-F | N4: E1001 | O4: Arvind Raghunathan | P4: HO | R4: Active | S4: UAN000100037111 | T4: XXXX7051 | V4: CAT-PERM — Permanent | X4: Y | Y4: Sunday weekly off | Z4: Monthly | AA4: Y | AB4: All days | AC4: 2 | AD4: LS-AGM | AE4: AGM_AND_ABOVE | AG4: 60 | AH4: Not applicable — annual credit on 1 January | AI4: LOC-BLR | AJ4: LOC-BLR | AK4: 10.83 | AL4: 90 | AM4: Y | AN4: 4 | AO4: 2 | AP4: VPI-1003
A5: E1004 | B5: Ritu Balachandran | C5: F | D5: 1976-06-19 | E5: 2016-02-01 | F5: LE-01 | G5: LOC-BLR | H5: OU-160 | I5: DES-03 | J5: D | K5: WC-PERM | L5: OFFICE8 | M5: SH-F | N5: E1001 | O5: Arvind Raghunathan | P5: HO | R5: Active | S5: UAN000100037148 | T5: XXXX7068 | V5: CAT-PERM — Permanent | X5: Y | Y5: Sunday weekly off | Z5: Monthly | AA5: Y | AB5: All days | AC5: 2 | AD5: LS-AGM | AE5: AGM_AND_ABOVE | AG5: 60 | AH5: Not applicable — annual credit on 1 January | AI5: LOC-BLR | AJ5: LOC-BLR | AK5: 10.62 | AL5: 80 | AM5: Y | AN5: 4 | AO5: 2 | AP5: VPI-1004
A6: E1005 | B6: Prakash Venugopal | C6: M | D6: 1975-11-07 | E6: 2013-09-09 | F6: LE-01 | G6: LOC-BLR | H6: OU-130 | I6: DES-03 | J6: D | K6: WC-PERM | L6: OFFICE8 | M6: SH-F | N6: E1002 | O6: Meenakshi Sundaram | P6: HO | R6: Active | S6: UAN000100037185 | T6: XXXX7085 | V6: CAT-PERM — Permanent | X6: Y | Y6: Sunday weekly off | Z6: Monthly | AA6: Y | AB6: All days | AC6: 2 | AD6: LS-AGM | AE6: AGM_AND_ABOVE | AG6: 60 | AH6: Not applicable — annual credit on 1 January | AI6: LOC-BLR | AJ6: LOC-BLR | AK6: 13.02 | AL6: 80 | AM6: Y | AN6: 4 | AO6: 2 | AP6: VPI-1005
A7: E1006 | B7: Anita Mathew | C7: F | D7: 1988-04-23 | E7: 2019-06-03 | F7: LE-01 | G7: LOC-BLR | H7: OU-160 | I7: DES-06 | J7: C | K7: WC-PERM | L7: OFFICE8 | M7: SH-F | N7: E1004 | O7: Ritu Balachandran | P7: HO | R7: Active | S7: UAN000100037222 | T7: XXXX7102 | U7: HR Ops demo persona | V7: CAT-PERM — Permanent | X7: Y | Y7: Sunday weekly off | Z7: Monthly | AA7: Y | AB7: All days | AC7: 2 | AD7: LS-STD | AE7: STANDARD | AG7: 60 | AH7: Eligible — six months completed before 2026 | AI7: LOC-BLR | AJ7: LOC-BLR | AK7: 7.29 | AL7: 55 | AM7: Y | AN7: 4 | AO7: 2 | AP7: VPI-1006
A8: E1007 | B8: Deepak Sarangi | C8: M | D8: 1987-12-02 | E8: 2018-08-20 | F8: LE-01 | G8: LOC-BLR | H8: OU-150 | I8: DES-07 | J8: C | K8: WC-PERM | L8: OFFICE8 | M8: SH-F | N8: E1003 | O8: Farhan Qureshi | P8: HO | R8: Active | S8: UAN000100037259 | T8: XXXX7119 | U8: Payroll demo persona | V8: CAT-PERM — Permanent | X8: Y | Y8: Sunday weekly off | Z8: Monthly | AA8: Y | AB8: All days | AC8: 2 | AD8: LS-STD | AE8: STANDARD | AG8: 60 | AH8: Eligible — six months completed before 2026 | AI8: LOC-BLR | AJ8: LOC-BLR | AK8: 8.07 | AL8: 50 | AM8: Y | AN8: 4 | AO8: 2 | AP8: VPI-1007
A9: E1008 | B9: Shalini Krishnamurthy | C9: F | D9: 1995-07-30 | E9: 2022-01-10 | F9: LE-01 | G9: LOC-BLR | H9: OU-160 | I9: DES-11 | J9: A | K9: WC-PERM | L9: OFFICE8 | M9: SH-F | N9: E1006 | O9: Anita Mathew | P9: HO | R9: Active | S9: UAN000100037296 | T9: XXXX7136 | V9: CAT-PERM — Permanent | X9: Y | Y9: Sunday weekly off | Z9: Monthly | AA9: Y | AB9: All days | AC9: 2 | AD9: LS-STD | AE9: STANDARD | AG9: 60 | AH9: Eligible — six months completed before 2026 | AI9: LOC-BLR | AJ9: LOC-BLR | AK9: 4.68 | AL9: 30 | AM9: N | AN9: 4 | AO9: 2 | AP9: VPI-1008
A10: E1009 | B10: Vikram Chauhan | C10: M | D10: 1990-02-14 | E10: 2020-03-02 | F10: LE-01 | G10: LOC-BLR | H10: OU-160 | I10: DES-10 | J10: B | K10: WC-PERM | L10: OFFICE8 | M10: SH-F | N10: E1004 | O10: Ritu Balachandran | P10: HO | R10: Active | S10: UAN000100037333 | T10: XXXX7153 | U10: Compliance owner | V10: CAT-PERM — Permanent | X10: Y | Y10: Sunday weekly off | Z10: Monthly | AA10: Y | AB10: All days | AC10: 2 | AD10: LS-STD | AE10: STANDARD | AG10: 60 | AH10: Eligible — six months completed before 2026 | AI10: LOC-BLR | AJ10: LOC-BLR | AK10: 6.54 | AL10: 34 | AM10: N | AN10: 4 | AO10: 2 | AP10: VPI-1009
A11: E1010 | B11: Nandita Bose | C11: F | D11: 1985-10-11 | E11: 2017-05-15 | F11: LE-01 | G11: LOC-BLR | H11: OU-150 | I11: DES-05 | J11: C | K11: WC-PERM | L11: OFFICE8 | M11: SH-F | N11: E1003 | O11: Farhan Qureshi | P11: HO | R11: Active | S11: UAN000100037370 | T11: XXXX7170 | V11: CAT-PERM — Permanent | X11: Y | Y11: Sunday weekly off | Z11: Monthly | AA11: Y | AB11: All days | AC11: 2 | AD11: LS-STD | AE11: STANDARD | AG11: 60 | AH11: Eligible — six months completed before 2026 | AI11: LOC-BLR | AJ11: LOC-BLR | AK11: 9.34 | AL11: 60 | AM11: Y | AN11: 4 | AO11: 2 | AP11: VPI-1010
A12: E1011 | B12: Rohit Agarwal | C12: M | D12: 1993-05-26 | E12: 2021-09-06 | F12: LE-01 | G12: LOC-BLR | H12: OU-150 | I12: DES-11 | J12: A | K12: WC-PERM | L12: OFFICE8 | M12: SH-F | N12: E1010 | O12: Nandita Bose | P12: HO | R12: Active | S12: UAN000100037407 | T12: XXXX7187 | V12: CAT-PERM — Permanent | X12: Y | Y12: Sunday weekly off | Z12: Monthly | AA12: Y | AB12: All days | AC12: 2 | AD12: LS-STD | AE12: STANDARD | AG12: 60 | AH12: Eligible — six months completed before 2026 | AI12: LOC-BLR | AJ12: LOC-BLR | AK12: 5.02 | AL12: 30 | AM12: N | AN12: 4 | AO12: 2 | AP12: VPI-1011
A13: E1012 | B13: Sameer Kulkarni | C13: M | D13: 1986-08-08 | E13: 2019-02-11 | F13: LE-01 | G13: LOC-BLR | H13: OU-170 | I13: DES-06 | J13: C | K13: WC-PERM | L13: OFFICE8 | M13: SH-F | N13: E1003 | O13: Farhan Qureshi | P13: HO | R13: Active | S13: UAN000100037444 | T13: XXXX7204 | V13: CAT-PERM — Permanent | X13: Y | Y13: Sunday weekly off | Z13: Monthly | AA13: Y | AB13: All days | AC13: 2 | AD13: LS-STD | AE13: STANDARD | AG13: 60 | AH13: Eligible — six months completed before 2026 | AI13: LOC-BLR | AJ13: LOC-BLR | AK13: 7.59 | AL13: 55 | AM13: Y | AN13: 4 | AO13: 2 | AP13: VPI-1012
A14: E1013 | B14: Tanvi Deshmukh | C14: F | D14: 1997-01-17 | E14: 2023-07-17 | F14: LE-01 | G14: LOC-BLR | H14: OU-170 | I14: DES-09 | J14: B | K14: WC-PERM | L14: OFFICE8 | M14: SH-F | N14: E1012 | O14: Sameer Kulkarni | P14: HO | R14: Active | S14: UAN000100037481 | T14: XXXX7221 | V14: CAT-PERM — Permanent | X14: Y | Y14: Sunday weekly off | Z14: Monthly | AA14: Y | AB14: All days | AC14: 2 | AD14: LS-STD | AE14: STANDARD | AG14: 60 | AH14: Eligible — six months completed before 2026 | AI14: LOC-BLR | AJ14: LOC-BLR | AK14: 3.16 | AL14: 35 | AM14: N | AN14: 4 | AO14: 2 | AP14: VPI-1013
A15: E1014 | B15: Harish Nambiar | C15: M | D15: 1983-03-05 | E15: 2018-04-02 | F15: LE-01 | G15: LOC-BLR | H15: OU-140 | I15: DES-05 | J15: C | K15: WC-PERM | L15: OFFICE8 | M15: SH-F | N15: E1001 | O15: Arvind Raghunathan | P15: HO | R15: Active | S15: UAN000100037518 | T15: XXXX7238 | V15: CAT-PERM — Permanent | X15: Y | Y15: Sunday weekly off | Z15: Monthly | AA15: Y | AB15: All days | AC15: 2 | AD15: LS-STD | AE15: STANDARD | AG15: 60 | AH15: Eligible — six months completed before 2026 | AI15: LOC-BLR | AJ15: LOC-BLR | AK15: 8.45 | AL15: 60 | AM15: Y | AN15: 4 | AO15: 2 | AP15: VPI-1014
A16: E1015 | B16: Pooja Trivedi | C16: F | D16: 1989-09-21 | E16: 2020-10-05 | F16: LE-01 | G16: LOC-BLR | H16: OU-140 | I16: DES-06 | J16: C | K16: WC-PERM | L16: OFFICE8 | M16: SH-F | N16: E1014 | O16: Harish Nambiar | P16: HO | R16: Active | S16: UAN000100037555 | T16: XXXX7255 | V16: CAT-PERM — Permanent | X16: Y | Y16: Sunday weekly off | Z16: Monthly | AA16: Y | AB16: All days | AC16: 2 | AD16: LS-STD | AE16: STANDARD | AG16: 60 | AH16: Eligible — six months completed before 2026 | AI16: LOC-BLR | AJ16: LOC-BLR | AK16: 5.94 | AL16: 55 | AM16: Y | AN16: 4 | AO16: 2 | AP16: VPI-1015
A17: E1016 | B17: Basavaraj Hiremath | C17: M | D17: 1973-07-14 | E17: 2014-01-06 | F17: LE-01 | G17: LOC-PLA | H17: OU-110 | I17: DES-03 | J17: D | K17: WC-PERM | L17: STAFF9 | M17: SH-E | N17: E1002 | O17: Meenakshi Sundaram | P17: PLANT-BLR | R17: Active | S17: UAN000100037592 | T17: XXXX7272 | V17: CAT-PERM — Permanent | X17: Y | Y17: Sunday weekly off | Z17: Monthly | AA17: Y | AB17: All days | AC17: 2 | AD17: LS-AGM | AE17: AGM_AND_ABOVE | AG17: 60 | AH17: Not applicable — annual credit on 1 January | AI17: LOC-PLA | AJ17: LOC-PLA | AK17: 12.69 | AL17: 80 | AM17: Y | AN17: 4 | AO17: 2 | AP17: VPI-1016
A18: E1017 | B18: Nikhil Iyer | C18: M | D18: 1984-05-09 | E18: 2017-08-21 | F18: LE-01 | G18: LOC-PLA | H18: OU-111 | I18: DES-05 | J18: C | K18: WC-PERM | L18: STAFF9 | M18: SH-E | N18: E1016 | O18: Basavaraj Hiremath | P18: PLANT-BLR | R18: Active | S18: UAN000100037629 | T18: XXXX7289 | V18: CAT-PERM — Permanent | X18: Y | Y18: Sunday weekly off | Z18: Monthly | AA18: Y | AB18: All days | AC18: 2 | AD18: LS-STD | AE18: STANDARD | AG18: 60 | AH18: Eligible — six months completed before 2026 | AI18: LOC-PLA | AJ18: LOC-PLA | AK18: 9.07 | AL18: 60 | AM18: Y | AN18: 4 | AO18: 2 | AP18: VPI-1017
A19: E1018 | B19: Ravi Kulkarni | C19: M | D19: 1991-11-23 | E19: 2019-11-04 | F19: LE-01 | G19: LOC-PLA | H19: OU-111 | I19: DES-08 | J19: B | K19: WC-PERM | L19: PLANT12 | M19: SH-A | N19: E1017 | O19: Nikhil Iyer | P19: PLANT-BLR | R19: Active | S19: UAN000100037666 | T19: XXXX7306 | U19: Point 1 — 19h20m cross-midnight day | V19: CAT-PERM — Permanent | X19: Y | Y19: Sunday weekly off | Z19: Monthly | AA19: Y | AB19: All days | AC19: 2 | AD19: LS-STD | AE19: STANDARD | AG19: 60 | AH19: Eligible — six months completed before 2026 | AI19: LOC-PLA | AJ19: LOC-PLA | AK19: 6.86 | AL19: 40 | AM19: N | AN19: 4 | AO19: 2 | AP19: VPI-1018
A20: E1019 | B20: Sneha Nair | C20: F | D20: 1994-02-06 | E20: 2021-06-14 | F20: LE-01 | G20: LOC-PLA | H20: OU-111 | I20: DES-09 | J20: B | K20: WC-PERM | L20: PLANT12 | M20: SH-A | N20: E1017 | O20: Nikhil Iyer | P20: PLANT-BLR | R20: Active | S20: UAN000100037703 | T20: XXXX7323 | U20: Point 12 — four late instances | V20: CAT-PERM — Permanent | X20: Y | Y20: Sunday weekly off | Z20: Monthly | AA20: Y | AB20: All days | AC20: 2 | AD20: LS-STD | AE20: STANDARD | AG20: 60 | AH20: Eligible — six months completed before 2026 | AI20: LOC-PLA | AJ20: LOC-PLA | AK20: 5.25 | AL20: 35 | AM20: N | AN20: 4 | AO20: 2 | AP20: VPI-1019
A21: E1020 | B21: Arjun Bhat | C21: M | D21: 1996-06-29 | E21: 2022-02-07 | F21: LE-01 | G21: LOC-PLA | H21: OU-112 | I21: DES-09 | J21: B | K21: WC-PERM | L21: PLANT12 | M21: SH-A | N21: E1021 | O21: Rekha Deshpande | P21: PLANT-BLR | R21: Active | S21: UAN000100037740 | T21: XXXX7340 | U21: Point 13 — punches into B shift | V21: CAT-PERM — Permanent | X21: Y | Y21: Sunday weekly off | Z21: Monthly | AA21: Y | AB21: All days | AC21: 2 | AD21: LS-STD | AE21: STANDARD | AG21: 60 | AH21: Eligible — six months completed before 2026 | AI21: LOC-PLA | AJ21: LOC-PLA | AK21: 4.6 | AL21: 35 | AM21: N | AN21: 4 | AO21: 2 | AP21: VPI-1020
A22: E1021 | B22: Rekha Deshpande | C22: F | D22: 1982-12-16 | E22: 2016-09-12 | F22: LE-01 | G22: LOC-PLA | H22: OU-112 | I22: DES-06 | J22: C | K22: WC-PERM | L22: STAFF9 | M22: SH-E | N22: E1016 | O22: Basavaraj Hiremath | P22: PLANT-BLR | R22: Active | S22: UAN000100037777 | T22: XXXX7357 | U22: Manager demo persona | V22: CAT-PERM — Permanent | X22: Y | Y22: Sunday weekly off | Z22: Monthly | AA22: Y | AB22: All days | AC22: 2 | AD22: LS-STD | AE22: STANDARD | AG22: 60 | AH22: Eligible — six months completed before 2026 | AI22: LOC-PLA | AJ22: LOC-PLA | AK22: 10.01 | AL22: 55 | AM22: Y | AN22: 4 | AO22: 2 | AP22: VPI-1021
A23: E1022 | B23: Mohan Joseph | C23: M | D23: 1992-08-03 | E23: 2020-07-01 | F23: LE-01 | G23: LOC-PLA | H23: OU-112 | I23: DES-12 | J23: A | K23: WC-PERM | L23: PLANT12 | M23: SH-A | N23: E1021 | O23: Rekha Deshpande | P23: PLANT-BLR | R23: Active | S23: UAN000100037814 | T23: XXXX7374 | U23: Points 12, 9 — half day, absent, special-terms loan | V23: CAT-PERM — Permanent | X23: Y | Y23: Sunday weekly off | Z23: Monthly | AA23: Y | AB23: All days | AC23: 2 | AD23: LS-STD | AE23: STANDARD | AG23: 60 | AH23: Eligible — six months completed before 2026 | AI23: LOC-PLA | AJ23: LOC-PLA | AK23: 6.21 | AL23: 25 | AM23: N | AN23: 4 | AO23: 2 | AP23: VPI-1022
A24: E1023 | B24: Kavya Venkatesh | C24: F | D24: 1995-04-18 | E24: 2021-03-15 | F24: LE-01 | G24: LOC-PLA | H24: OU-113 | I24: DES-11 | J24: A | K24: WC-PERM | L24: PLANT12 | M24: SH-A | N24: E1024 | O24: Srinivas Achar | P24: PLANT-BLR | R24: Active | S24: UAN000100037851 | T24: XXXX7391 | U24: Point 11 — gate pass 2 x 2h | V24: CAT-PERM — Permanent | X24: Y | Y24: Sunday weekly off | Z24: Monthly | AA24: Y | AB24: All days | AC24: 2 | AD24: LS-STD | AE24: STANDARD | AG24: 60 | AH24: Eligible — six months completed before 2026 | AI24: LOC-PLA | AJ24: LOC-PLA | AK24: 5.5 | AL24: 30 | AM24: N | AN24: 4 | AO24: 2 | AP24: VPI-1023
A25: E1024 | B25: Srinivas Achar | C25: M | D25: 1980-10-27 | E25: 2015-12-01 | F25: LE-01 | G25: LOC-PLA | H25: OU-113 | I25: DES-07 | J25: C | K25: WC-PERM | L25: STAFF9 | M25: SH-E | N25: E1016 | O25: Basavaraj Hiremath | P25: PLANT-BLR | R25: Active | S25: UAN000100037888 | T25: XXXX7408 | V25: CAT-PERM — Permanent | X25: Y | Y25: Sunday weekly off | Z25: Monthly | AA25: Y | AB25: All days | AC25: 2 | AD25: LS-STD | AE25: STANDARD | AG25: 60 | AH25: Eligible — six months completed before 2026 | AI25: LOC-PLA | AJ25: LOC-PLA | AK25: 10.79 | AL25: 50 | AM25: Y | AN25: 4 | AO25: 2 | AP25: VPI-1024
A26: E1025 | B26: Lakshmi Gowda | C26: F | D26: 1998-03-09 | E26: 2023-01-09 | F26: LE-01 | G26: LOC-PLA | H26: OU-111 | I26: DES-13 | J26: A | K26: WC-PERM | L26: PLANT12 | M26: SH-A | N26: E1017 | O26: Nikhil Iyer | P26: PLANT-BLR | R26: Active | S26: UAN000100037925 | T26: XXXX7425 | V26: CAT-PERM — Permanent | X26: Y | Y26: Sunday weekly off | Z26: Monthly | AA26: Y | AB26: All days | AC26: 2 | AD26: LS-STD | AE26: STANDARD | AG26: 60 | AH26: Eligible — six months completed before 2026 | AI26: LOC-PLA | AJ26: LOC-PLA | AK26: 3.68 | AL26: 20 | AM26: N | AN26: 4 | AO26: 2 | AP26: VPI-1025
A27: E1026 | B27: Manjunath Poojary | C27: M | D27: 1990-01-31 | E27: 2019-04-22 | F27: LE-01 | G27: LOC-PLA | H27: OU-114 | I27: DES-14 | J27: A | K27: WC-PERM | L27: PLANT12 | M27: SH-B | N27: E1027 | O27: Girish Deshpande | P27: PLANT-BLR | R27: Active | S27: UAN000100037962 | T27: XXXX7442 | U27: Night shift | V27: CAT-PERM — Permanent | X27: Y | Y27: Sunday weekly off | Z27: Monthly | AA27: Y | AB27: All days | AC27: 2 | AD27: LS-STD | AE27: STANDARD | AG27: 60 | AH27: Eligible — six months completed before 2026 | AI27: LOC-PLA | AJ27: LOC-PLA | AK27: 7.4 | AL27: 20 | AM27: N | AN27: 4 | AO27: 2 | AP27: VPI-1026
A28: E1027 | B28: Girish Deshpande | C28: M | D28: 1981-06-11 | E28: 2017-02-13 | F28: LE-01 | G28: LOC-PLA | H28: OU-114 | I28: DES-07 | J28: C | K28: WC-PERM | L28: STAFF9 | M28: SH-E | N28: E1016 | O28: Basavaraj Hiremath | P28: PLANT-BLR | R28: Active | S28: UAN000100037999 | T28: XXXX7459 | V28: CAT-PERM — Permanent | X28: Y | Y28: Sunday weekly off | Z28: Monthly | AA28: Y | AB28: All days | AC28: 2 | AD28: LS-STD | AE28: STANDARD | AG28: 60 | AH28: Eligible — six months completed before 2026 | AI28: LOC-PLA | AJ28: LOC-PLA | AK28: 9.59 | AL28: 50 | AM28: Y | AN28: 4 | AO28: 2 | AP28: VPI-1027
A29: E1028 | B29: Yashoda Rani | C29: F | D29: 1989-05-02 | E29: 2018-10-29 | F29: LE-01 | G29: LOC-PLA | H29: OU-112 | I29: DES-12 | J29: A | K29: WC-PERM | L29: PLANT12 | M29: SH-A | N29: E1021 | O29: Rekha Deshpande | P29: PLANT-BLR | R29: Active | S29: UAN000100038036 | T29: XXXX7476 | U29: Point 6 — comp-off nearing lapse | V29: CAT-PERM — Permanent | X29: Y | Y29: Sunday weekly off | Z29: Monthly | AA29: Y | AB29: All days | AC29: 2 | AD29: LS-STD | AE29: STANDARD | AG29: 60 | AH29: Eligible — six months completed before 2026 | AI29: LOC-PLA | AJ29: LOC-PLA | AK29: 7.88 | AL29: 25 | AM29: N | AN29: 4 | AO29: 2 | AP29: VPI-1028
A30: E1029 | B30: Prashant Salian | C30: M | D30: 2000-09-15 | E30: 2024-08-01 | F30: LE-01 | G30: LOC-PLA | H30: OU-111 | I30: DES-13 | J30: A | K30: WC-PERM | L30: PLANT12 | M30: SH-B | N30: E1017 | O30: Nikhil Iyer | P30: PLANT-BLR | R30: Active | S30: UAN000100038073 | T30: XXXX7493 | V30: CAT-PERM — Permanent | X30: Y | Y30: Sunday weekly off | Z30: Monthly | AA30: Y | AB30: All days | AC30: 2 | AD30: LS-STD | AE30: STANDARD | AG30: 60 | AH30: Eligible — six months completed before 2026 | AI30: LOC-PLA | AJ30: LOC-PLA | AK30: 2.12 | AL30: 20 | AM30: N | AN30: 4 | AO30: 2 | AP30: VPI-1029
A31: E1030 | B31: Chetan Bhandary | C31: M | D31: 2003-04-26 | E31: 2026-07-01 | F31: LE-01 | G31: LOC-PLA | H31: OU-111 | I31: DES-15 | J31: T | K31: WC-TRN | L31: STAFF9 | M31: SH-E | N31: E1017 | O31: Nikhil Iyer | P31: PLANT-BLR | R31: Active | S31: UAN000100038110 | T31: XXXX7510 | U31: Point 7 — GET, July joiner, 3 CL/SL | V31: CAT-TRN — Trainee | W31: SUB-TRN — Engineer trainee | X31: Y | Y31: Sunday weekly off | Z31: Monthly | AA31: Y | AB31: All days | AC31: 2 | AD31: LS-TRN | AE31: TRAINEE_GET | AF31: GET | AG31: 60 | AH31: Not applicable — scheme accrues no EL | AI31: LOC-PLA | AJ31: LOC-PLA | AK31: 0.21 | AL31: 15 | AM31: N | AN31: 4 | AO31: 2 | AP31: VPI-1030
A32: E1031 | B32: Divya Hegde | C32: F | D32: 2004-08-12 | E32: 2026-07-01 | F32: LE-01 | G32: LOC-PLA | H32: OU-113 | I32: DES-16 | J32: T | K32: WC-TRN | L32: STAFF9 | M32: SH-E | N32: E1024 | O32: Srinivas Achar | P32: PLANT-BLR | R32: Active | S32: UAN000100038147 | T32: XXXX7527 | U32: Point 7 — DET, July joiner, 3 CL/SL | V32: CAT-TRN — Trainee | W32: SUB-TRN — Engineer trainee | X32: Y | Y32: Sunday weekly off | Z32: Monthly | AA32: Y | AB32: All days | AC32: 2 | AD32: LS-TRN | AE32: TRAINEE_DET | AF32: DET | AG32: 60 | AH32: Not applicable — scheme accrues no EL | AI32: LOC-PLA | AJ32: LOC-PLA | AK32: 0.21 | AL32: 14 | AM32: N | AN32: 4 | AO32: 2 | AP32: VPI-1031
A33: E1032 | B33: Shivanna Muniyappa | C33: M | D33: 1987-02-20 | E33: 2025-04-01 | F33: LE-01 | G33: LOC-PLA | H33: OU-111 | I33: DES-18 | J33: H | K33: WC-CONT | L33: PLANT12 | M33: SH-A | N33: E1017 | O33: Nikhil Iyer | P33: PLANT-BLR | Q33: VN-02 | R33: Active | S33: UAN000100038184 | T33: XXXX7544 | U33: Point 2 — daily wage, no rest day | V33: CAT-CONT — Contractual | X33: N | Z33: Daily | AA33: Y | AB33: All days | AC33: 2 | AD33: LS-NONE | AE33: NOT_ELIGIBLE | AH33: Not applicable — scheme accrues no EL | AI33: LOC-PLA | AJ33: LOC-PLA | AK33: 1.46 | AL33: 5 | AM33: N | AP33: VPI-1032 | AQ33: no rest day — resolves at category level; not leave eligible
A34: E1033 | B34: Ratnamma Devaraju | C34: F | D34: 1990-11-05 | E34: 2025-06-15 | F34: LE-01 | G34: LOC-PLA | H34: OU-112 | I34: DES-18 | J34: H | K34: WC-CONT | L34: PLANT12 | M34: SH-A | N34: E1021 | O34: Rekha Deshpande | P34: PLANT-BLR | Q34: VN-02 | R34: Active | S34: UAN000100038221 | T34: XXXX7561 | U34: Point 2 — daily wage, works Sunday | V34: CAT-CONT — Contractual | X34: N | Z34: Daily | AA34: Y | AB34: All days | AC34: 2 | AD34: LS-NONE | AE34: NOT_ELIGIBLE | AH34: Not applicable — scheme accrues no EL | AI34: LOC-PLA | AJ34: LOC-PLA | AK34: 1.25 | AL34: 5 | AM34: N | AP34: VPI-1033 | AQ34: no rest day — resolves at category level; not leave eligible
A35: E1034 | B35: Imran Shaikh | C35: M | D35: 1993-07-08 | E35: 2025-02-10 | F35: LE-01 | G35: LOC-PLA | H35: OU-112 | I35: DES-13 | J35: A | K35: WC-3PE | L35: PLANT12 | M35: SH-A | N35: E1021 | O35: Rekha Deshpande | P35: PLANT-BLR | Q35: VN-01 | R35: Active | S35: UAN000100038258 | T35: XXXX7578 | U35: Points 3, 4 — 3P employee, has rest days, OT rest/holiday only | V35: CAT-3P — Third party | W35: SUB-EMP — Employee | X35: Y | Y35: Sunday weekly off | Z35: Monthly | AA35: Y | AB35: Rest days and holidays only | AC35: 2 | AD35: LS-NONE | AE35: NOT_ELIGIBLE | AH35: Not applicable — scheme accrues no EL | AI35: LOC-PLA | AJ35: LOC-PLA | AK35: 1.59 | AL35: 20 | AM35: N | AP35: VPI-1034 | AQ35: OT only on a rest day or holiday; not leave eligible
A36: E1035 | B36: Ashok Naik | C36: M | D36: 1991-12-19 | E36: 2025-03-01 | F36: LE-01 | G36: LOC-PLA | H36: OU-114 | I36: DES-14 | J36: A | K36: WC-3PE | L36: PLANT12 | M36: SH-A | N36: E1027 | O36: Girish Deshpande | P36: PLANT-BLR | Q36: VN-01 | R36: Active | S36: UAN000100038295 | T36: XXXX7595 | V36: CAT-3P — Third party | W36: SUB-EMP — Employee | X36: Y | Y36: Sunday weekly off | Z36: Monthly | AA36: Y | AB36: Rest days and holidays only | AC36: 2 | AD36: LS-NONE | AE36: NOT_ELIGIBLE | AH36: Not applicable — scheme accrues no EL | AI36: LOC-PLA | AJ36: LOC-PLA | AK36: 1.54 | AL36: 20 | AM36: N | AP36: VPI-1035 | AQ36: OT only on a rest day or holiday; not leave eligible
A37: E1036 | B37: Lakshmi Rao | C37: F | D37: 1994-06-03 | E37: 2025-05-20 | F37: LE-01 | G37: LOC-PLA | H37: OU-121 | I37: DES-17 | J37: H | K37: WC-3PH | L37: PLANT12 | M37: SH-A | N37: E1037 | O37: Venkatesh Murthy | P37: PLANT-BLR | Q37: VN-01 | R37: Active | S37: UAN000100038332 | T37: XXXX7612 | U37: Point 3 — helper, no rest days | V37: CAT-3P — Third party | W37: SUB-HLP — Helper | X37: N | Z37: Daily | AA37: Y | AB37: Rest days and holidays only | AC37: 2 | AD37: LS-NONE | AE37: NOT_ELIGIBLE | AH37: Not applicable — scheme accrues no EL | AI37: LOC-PLA | AJ37: LOC-PLA | AK37: 1.32 | AL37: 5 | AM37: N | AP37: VPI-1036 | AQ37: no rest day — resolves at sub-category (Helper) level; OT only on a rest day or holiday; not leave eligible
A38: E1037 | B38: Venkatesh Murthy | C38: M | D38: 1986-09-28 | E38: 2019-07-08 | F38: LE-01 | G38: LOC-PLA | H38: OU-121 | I38: DES-11 | J38: A | K38: WC-PERM | L38: STAFF9 | M38: SH-E | N38: E1016 | O38: Basavaraj Hiremath | P38: PLANT-BLR | R38: Active | S38: UAN000100038369 | T38: XXXX7629 | V38: CAT-PERM — Permanent | X38: Y | Y38: Sunday weekly off | Z38: Monthly | AA38: Y | AB38: All days | AC38: 2 | AD38: LS-STD | AE38: STANDARD | AG38: 60 | AH38: Eligible — six months completed before 2026 | AI38: LOC-PLA | AJ38: LOC-PLA | AK38: 7.19 | AL38: 30 | AM38: N | AN38: 4 | AO38: 2 | AP38: VPI-1037
A39: E1038 | B39: Parvathi Bai | C39: F | D39: 1996-01-22 | E39: 2026-01-12 | F39: LE-01 | G39: LOC-PLA | H39: OU-121 | I39: DES-17 | J39: H | K39: WC-3PH | L39: PLANT12 | M39: SH-A | N39: E1037 | O39: Venkatesh Murthy | P39: PLANT-BLR | Q39: VN-01 | R39: Active | S39: UAN000100038406 | T39: XXXX7646 | U39: Point 7 — January joiner reference | V39: CAT-3P — Third party | W39: SUB-HLP — Helper | X39: N | Z39: Daily | AA39: Y | AB39: Rest days and holidays only | AC39: 2 | AD39: LS-NONE | AE39: NOT_ELIGIBLE | AH39: Not applicable — scheme accrues no EL | AI39: LOC-PLA | AJ39: LOC-PLA | AK39: 0.67 | AL39: 5 | AM39: N | AP39: VPI-1038 | AQ39: no rest day — resolves at sub-category (Helper) level; OT only on a rest day or holiday; not leave eligible
A40: E1039 | B40: Sanjay Pawar | C40: M | D40: 1977-04-17 | E40: 2015-06-01 | F40: LE-01 | G40: LOC-PUN | H40: OU-110 | I40: DES-03 | J40: D | K40: WC-PERM | L40: STAFF9 | M40: SH-E | N40: E1002 | O40: Meenakshi Sundaram | P40: PLANT-PUN | R40: Active | S40: UAN000100038443 | T40: XXXX7663 | V40: CAT-PERM — Permanent | X40: Y | Y40: Sunday weekly off | Z40: Monthly | AA40: Y | AB40: All days | AC40: 2 | AD40: LS-AGM | AE40: AGM_AND_ABOVE | AG40: 60 | AH40: Not applicable — annual credit on 1 January | AI40: LOC-PUN | AJ40: LOC-PUN | AK40: 11.29 | AL40: 80 | AM40: Y | AN40: 4 | AO40: 2 | AP40: VPI-1039
A41: E1040 | B41: Aditi Joshi | C41: F | D41: 1985-08-24 | E41: 2018-11-19 | F41: LE-01 | G41: LOC-PUN | H41: OU-112 | I41: DES-06 | J41: C | K41: WC-PERM | L41: STAFF9 | M41: SH-E | N41: E1039 | O41: Sanjay Pawar | P41: PLANT-PUN | R41: Active | S41: UAN000100038480 | T41: XXXX7680 | U41: Point 9 — guarantor, now blocked | V41: CAT-PERM — Permanent | X41: Y | Y41: Sunday weekly off | Z41: Monthly | AA41: Y | AB41: All days | AC41: 2 | AD41: LS-STD | AE41: STANDARD | AG41: 60 | AH41: Eligible — six months completed before 2026 | AI41: LOC-PUN | AJ41: LOC-PUN | AK41: 7.82 | AL41: 55 | AM41: Y | AN41: 4 | AO41: 2 | AP41: VPI-1040
A42: E1041 | B42: Mahesh Shinde | C42: M | D42: 1988-10-13 | E42: 2020-01-20 | F42: LE-01 | G42: LOC-PUN | H42: OU-111 | I42: DES-08 | J42: B | K42: WC-PERM | L42: PLANT10 | M42: SH-C | N42: E1040 | O42: Aditi Joshi | P42: PLANT-PUN | R42: Active | S42: UAN000100038517 | T42: XXXX7697 | U42: Point 9 — guarantor, loan application rejected | V42: CAT-PERM — Permanent | X42: Y | Y42: Sunday weekly off | Z42: Monthly | AA42: Y | AB42: All days | AC42: 2 | AD42: LS-STD | AE42: STANDARD | AG42: 60 | AH42: Eligible — six months completed before 2026 | AI42: LOC-PUN | AJ42: LOC-PUN | AK42: 6.65 | AL42: 40 | AM42: N | AN42: 4 | AO42: 2 | AP42: VPI-1041
A43: E1042 | B43: Swapnil Kadam | C43: M | D43: 1994-03-07 | E43: 2022-09-05 | F43: LE-01 | G43: LOC-PUN | H43: OU-114 | I43: DES-09 | J43: B | K43: WC-PERM | L43: PLANT10 | M43: SH-C | N43: E1040 | O43: Aditi Joshi | P43: PLANT-PUN | R43: In notice | S43: UAN000100038554 | T43: XXXX7714 | U43: Point 16 — in notice, LWD 18 Sep | V43: CAT-PERM — Permanent | X43: Y | Y43: Sunday weekly off | Z43: Monthly | AA43: Y | AB43: All days | AC43: 2 | AD43: LS-STD | AE43: STANDARD | AG43: 60 | AH43: Eligible — six months completed before 2026 | AI43: LOC-PUN | AJ43: LOC-PUN | AK43: 4.03 | AL43: 35 | AM43: N | AN43: 4 | AO43: 2 | AP43: VPI-1042
A44: E1043 | B44: Neha Mishra | C44: F | D44: 1992-12-01 | E44: 2021-11-02 | F44: LE-01 | G44: LOC-PUN | H44: OU-160 | I44: DES-11 | J44: A | K44: WC-PERM | L44: STAFF9 | M44: SH-E | N44: E1039 | O44: Sanjay Pawar | P44: PLANT-PUN | R44: Active | S44: UAN000100038591 | T44: XXXX7731 | U44: Point 5 — early return from 10-day leave | V44: CAT-PERM — Permanent | X44: Y | Y44: Sunday weekly off | Z44: Monthly | AA44: Y | AB44: All days | AC44: 2 | AD44: LS-STD | AE44: STANDARD | AG44: 60 | AH44: Eligible — six months completed before 2026 | AI44: LOC-PUN | AJ44: LOC-PUN | AK44: 4.87 | AL44: 30 | AM44: N | AN44: 4 | AO44: 2 | AP44: VPI-1043
A45: E1044 | B45: Rahul Gaikwad | C45: M | D45: 1989-06-16 | E45: 2019-03-11 | F45: LE-01 | G45: LOC-PUN | H45: OU-112 | I45: DES-12 | J45: A | K45: WC-PERM | L45: PLANT10 | M45: SH-C | N45: E1040 | O45: Aditi Joshi | P45: PLANT-PUN | R45: Active | S45: UAN000100038628 | T45: XXXX7748 | U45: Point 9 — active loan, 4x basic | V45: CAT-PERM — Permanent | X45: Y | Y45: Sunday weekly off | Z45: Monthly | AA45: Y | AB45: All days | AC45: 2 | AD45: LS-STD | AE45: STANDARD | AG45: 60 | AH45: Eligible — six months completed before 2026 | AI45: LOC-PUN | AJ45: LOC-PUN | AK45: 7.52 | AL45: 25 | AM45: N | AN45: 4 | AO45: 2 | AP45: VPI-1044
A46: E1045 | B46: Sunita Bhosale | C46: F | D46: 1997-10-04 | E46: 2023-05-08 | F46: LE-01 | G46: LOC-PUN | H46: OU-113 | I46: DES-13 | J46: A | K46: WC-PERM | L46: PLANT10 | M46: SH-D | N46: E1040 | O46: Aditi Joshi | P46: PLANT-PUN | R46: Active | S46: UAN000100038665 | T46: XXXX7765 | V46: CAT-PERM — Permanent | X46: Y | Y46: Sunday weekly off | Z46: Monthly | AA46: Y | AB46: All days | AC46: 2 | AD46: LS-STD | AE46: STANDARD | AG46: 60 | AH46: Eligible — six months completed before 2026 | AI46: LOC-PUN | AJ46: LOC-PUN | AK46: 3.36 | AL46: 20 | AM46: N | AN46: 4 | AO46: 2 | AP46: VPI-1045
A47: E1046 | B47: Dattatray More | C47: M | D47: 1992-02-11 | E47: 2026-02-02 | F47: LE-01 | G47: LOC-PUN | H47: OU-111 | I47: DES-18 | J47: H | K47: WC-CONT | L47: PLANT10 | M47: SH-C | N47: E1040 | O47: Aditi Joshi | P47: PLANT-PUN | Q47: VN-03 | R47: Active | S47: UAN000100038702 | T47: XXXX7782 | U47: Point 7 — February joiner, 5 CL/SL | V47: CAT-CONT — Contractual | X47: N | Z47: Daily | AA47: Y | AB47: All days | AC47: 2 | AD47: LS-NONE | AE47: NOT_ELIGIBLE | AH47: Not applicable — scheme accrues no EL | AI47: LOC-PUN | AJ47: LOC-PUN | AK47: 0.62 | AL47: 5 | AM47: N | AP47: VPI-1046 | AQ47: no rest day — resolves at category level; not leave eligible
A48: E1047 | B48: Koteswara Rao | C48: M | D48: 1976-05-30 | E48: 2016-08-16 | F48: LE-02 | G48: LOC-HYD | H48: OU-110 | I48: DES-03 | J48: D | K48: WC-PERM | L48: STAFF9 | M48: SH-E | N48: E1002 | O48: Meenakshi Sundaram | P48: PLANT-HYD | R48: Active | S48: UAN000100038739 | T48: XXXX7799 | V48: CAT-PERM — Permanent | X48: Y | Y48: Sunday weekly off | Z48: Monthly | AA48: Y | AB48: All days | AC48: 2 | AD48: LS-AGM | AE48: AGM_AND_ABOVE | AG48: 60 | AH48: Not applicable — annual credit on 1 January | AI48: LOC-HYD | AJ48: LOC-HYD | AK48: 10.08 | AL48: 80 | AM48: Y | AN48: 4 | AO48: 2 | AP48: VPI-1047
A49: E1048 | B49: Sirisha Yadav | C49: F | D49: 1987-11-09 | E49: 2019-09-23 | F49: LE-02 | G49: LOC-HYD | H49: OU-113 | I49: DES-06 | J49: C | K49: WC-PERM | L49: STAFF9 | M49: SH-E | N49: E1047 | O49: Koteswara Rao | P49: PLANT-HYD | R49: Active | S49: UAN000100038776 | T49: XXXX7816 | V49: CAT-PERM — Permanent | X49: Y | Y49: Sunday weekly off | Z49: Monthly | AA49: Y | AB49: All days | AC49: 2 | AD49: LS-STD | AE49: STANDARD | AG49: 60 | AH49: Eligible — six months completed before 2026 | AI49: LOC-HYD | AJ49: LOC-HYD | AK49: 6.98 | AL49: 55 | AM49: Y | AN49: 4 | AO49: 2 | AP49: VPI-1048
A50: E1049 | B50: Naveen Bandaru | C50: M | D50: 1990-08-27 | E50: 2021-04-12 | F50: LE-02 | G50: LOC-HYD | H50: OU-130 | I50: DES-08 | J50: B | K50: WC-PERM | L50: STAFF9 | M50: SH-E | N50: E1047 | O50: Koteswara Rao | P50: PLANT-HYD | R50: Active | S50: UAN000100038813 | T50: XXXX7833 | V50: CAT-PERM — Permanent | X50: Y | Y50: Sunday weekly off | Z50: Monthly | AA50: Y | AB50: All days | AC50: 2 | AD50: LS-STD | AE50: STANDARD | AG50: 60 | AH50: Eligible — six months completed before 2026 | AI50: LOC-HYD | AJ50: LOC-HYD | AK50: 5.43 | AL50: 40 | AM50: N | AN50: 4 | AO50: 2 | AP50: VPI-1049
A51: E1050 | B51: Suresh Pillai | C51: M | D51: 1983-01-19 | E51: 2017-10-30 | F51: LE-02 | G51: LOC-HYD | H51: OU-122 | I51: DES-10 | J51: B | K51: WC-PERM | L51: STAFF9 | M51: SH-E | N51: E1047 | O51: Koteswara Rao | P51: PLANT-HYD | R51: Active | S51: UAN000100038850 | T51: XXXX7850 | U51: Points 6, 9 — comp-off credits, released guarantor | V51: CAT-PERM — Permanent | X51: Y | Y51: Sunday weekly off | Z51: Monthly | AA51: Y | AB51: All days | AC51: 2 | AD51: LS-STD | AE51: STANDARD | AG51: 60 | AH51: Eligible — six months completed before 2026 | AI51: LOC-HYD | AJ51: LOC-HYD | AK51: 8.88 | AL51: 34 | AM51: N | AN51: 4 | AO51: 2 | AP51: VPI-1050
A52: E1051 | B52: Haritha Reddy | C52: F | D52: 1999-04-02 | E52: 2024-02-19 | F52: LE-02 | G52: LOC-HYD | H52: OU-112 | I52: DES-09 | J52: B | K52: WC-PERM | L52: PLANT12 | M52: SH-A | N52: E1048 | O52: Sirisha Yadav | P52: PLANT-HYD | R52: Active | S52: UAN000100038887 | T52: XXXX7867 | V52: CAT-PERM — Permanent | X52: Y | Y52: Sunday weekly off | Z52: Monthly | AA52: Y | AB52: All days | AC52: 2 | AD52: LS-STD | AE52: STANDARD | AG52: 60 | AH52: Eligible — six months completed before 2026 | AI52: LOC-HYD | AJ52: LOC-HYD | AK52: 2.57 | AL52: 35 | AM52: N | AN52: 4 | AO52: 2 | AP52: VPI-1051
A53: E1052 | B53: Anjaneyulu Gadde | C53: M | D53: 1993-09-11 | E53: 2022-12-05 | F53: LE-02 | G53: LOC-HYD | H53: OU-111 | I53: DES-13 | J53: A | K53: WC-PERM | L53: PLANT12 | M53: SH-B | N53: E1049 | O53: Naveen Bandaru | P53: PLANT-HYD | R53: Active | S53: UAN000100038924 | T53: XXXX7884 | V53: CAT-PERM — Permanent | X53: Y | Y53: Sunday weekly off | Z53: Monthly | AA53: Y | AB53: All days | AC53: 2 | AD53: LS-STD | AE53: STANDARD | AG53: 60 | AH53: Eligible — six months completed before 2026 | AI53: LOC-HYD | AJ53: LOC-HYD | AK53: 3.78 | AL53: 20 | AM53: N | AN53: 4 | AO53: 2 | AP53: VPI-1052
A54: E1053 | B54: Padmaja Cheruku | C54: F | D54: 1995-03-25 | E54: 2026-03-09 | F54: LE-02 | G54: LOC-HYD | H54: OU-121 | I54: DES-17 | J54: H | K54: WC-3PH | L54: PLANT12 | M54: SH-A | N54: E1050 | O54: Suresh Pillai | P54: PLANT-HYD | Q54: VN-04 | R54: Active | S54: UAN000100038961 | T54: XXXX7901 | U54: Point 7 — March joiner, 5 CL/SL | V54: CAT-3P — Third party | W54: SUB-HLP — Helper | X54: N | Z54: Daily | AA54: Y | AB54: Rest days and holidays only | AC54: 2 | AD54: LS-NONE | AE54: NOT_ELIGIBLE | AH54: Not applicable — scheme accrues no EL | AI54: LOC-HYD | AJ54: LOC-HYD | AK54: 0.52 | AL54: 5 | AM54: N | AP54: VPI-1053 | AQ54: no rest day — resolves at sub-category (Helper) level; OT only on a rest day or holiday; not leave eligible
A55: E1054 | B55: Selvaraj Murugan | C55: M | D55: 1974-12-08 | E55: 2015-02-02 | F55: LE-02 | G55: LOC-CHN | H55: OU-110 | I55: DES-03 | J55: D | K55: WC-PERM | L55: STAFF9 | M55: SH-E | N55: E1002 | O55: Meenakshi Sundaram | P55: PLANT-CHN | R55: Active | S55: UAN000100038998 | T55: XXXX7918 | V55: CAT-PERM — Permanent | X55: Y | Y55: Sunday weekly off | Z55: Monthly | AA55: Y | AB55: All days | AC55: 2 | AD55: LS-AGM | AE55: AGM_AND_ABOVE | AG55: 60 | AH55: Not applicable — annual credit on 1 January | AI55: LOC-CHN | AJ55: LOC-CHN | AK55: 11.62 | AL55: 80 | AM55: Y | AN55: 4 | AO55: 2 | AP55: VPI-1054
A56: E1055 | B56: Kalaivani Subramani | C56: F | D56: 1986-07-21 | E56: 2020-06-22 | F56: LE-02 | G56: LOC-CHN | H56: OU-160 | I56: DES-06 | J56: C | K56: WC-PERM | L56: STAFF9 | M56: SH-E | N56: E1054 | O56: Selvaraj Murugan | P56: PLANT-CHN | R56: Active | S56: UAN000100039035 | T56: XXXX7935 | V56: CAT-PERM — Permanent | X56: Y | Y56: Sunday weekly off | Z56: Monthly | AA56: Y | AB56: All days | AC56: 2 | AD56: LS-STD | AE56: STANDARD | AG56: 60 | AH56: Eligible — six months completed before 2026 | AI56: LOC-CHN | AJ56: LOC-CHN | AK56: 6.23 | AL56: 55 | AM56: Y | AN56: 4 | AO56: 2 | AP56: VPI-1055
A57: E1056 | B57: Anand Krishnan | C57: M | D57: 1985-02-28 | E57: 2018-01-15 | F57: LE-02 | G57: LOC-CHN | H57: OU-111 | I57: DES-08 | J57: B | K57: WC-PERM | L57: PLANT12 | M57: SH-A | N57: E1054 | O57: Selvaraj Murugan | P57: HO | R57: Active | S57: UAN000100039072 | T57: XXXX7952 | U57: Point 8 — HO payroll, plant attendance. Point 9 — 6x basic | V57: CAT-PERM — Permanent | X57: Y | Y57: Sunday weekly off | Z57: Monthly | AA57: Y | AB57: All days | AC57: 2 | AD57: LS-STD | AE57: STANDARD | AG57: 60 | AH57: Eligible — six months completed before 2026 | AI57: LOC-BLR | AJ57: LOC-CHN | AK57: 8.67 | AL57: 40 | AM57: N | AN57: 4 | AO57: 2 | AP57: VPI-1056 | AQ57: payrolled at head office while attending at LOC-CHN — point 8
A58: E1057 | B58: Bhuvaneswari Raman | C58: F | D58: 1998-05-14 | E58: 2023-03-27 | F58: LE-02 | G58: LOC-CHN | H58: OU-113 | I58: DES-11 | J58: A | K58: WC-PERM | L58: PLANT12 | M58: SH-A | N58: E1055 | O58: Kalaivani Subramani | P58: PLANT-CHN | R58: Active | S58: UAN000100039109 | T58: XXXX7969 | V58: CAT-PERM — Permanent | X58: Y | Y58: Sunday weekly off | Z58: Monthly | AA58: Y | AB58: All days | AC58: 2 | AD58: LS-STD | AE58: STANDARD | AG58: 60 | AH58: Eligible — six months completed before 2026 | AI58: LOC-CHN | AJ58: LOC-CHN | AK58: 3.47 | AL58: 30 | AM58: N | AN58: 4 | AO58: 2 | AP58: VPI-1057
A59: E1058 | B59: Karthik Chidambaram | C59: M | D59: 1996-09-06 | E59: 2025-09-01 | F59: LE-02 | G59: LOC-CHN | H59: OU-114 | I59: DES-09 | J59: B | K59: WC-PERM | L59: PLANT12 | M59: SH-A | N59: E1054 | O59: Selvaraj Murugan | P59: PLANT-CHN | R59: Active | S59: UAN000100039146 | T59: XXXX7986 | V59: CAT-PERM — Permanent | X59: Y | Y59: Sunday weekly off | Z59: Monthly | AA59: Y | AB59: All days | AC59: 2 | AD59: LS-STD | AE59: STANDARD | AG59: 60 | AH59: Eligible — six months completed before 2026 | AI59: LOC-CHN | AJ59: LOC-CHN | AK59: 1.04 | AL59: 35 | AM59: N | AN59: 4 | AO59: 2 | AP59: VPI-1058
A60: E1059 | B60: Vetrivel Pandian | C60: M | D60: 1991-01-12 | E60: 2021-08-09 | F60: LE-02 | G60: LOC-CHN | H60: OU-112 | I60: DES-12 | J60: A | K60: WC-PERM | L60: PLANT12 | M60: SH-B | N60: E1054 | O60: Selvaraj Murugan | P60: PLANT-CHN | R60: Active | S60: UAN000100039183 | T60: XXXX8003 | V60: CAT-PERM — Permanent | X60: Y | Y60: Sunday weekly off | Z60: Monthly | AA60: Y | AB60: All days | AC60: 2 | AD60: LS-STD | AE60: STANDARD | AG60: 60 | AH60: Eligible — six months completed before 2026 | AI60: LOC-CHN | AJ60: LOC-CHN | AK60: 5.1 | AL60: 25 | AM60: N | AN60: 4 | AO60: 2 | AP60: VPI-1059
A61: E1060 | B61: Jayanthi Elangovan | C61: F | D61: 2001-06-23 | E61: 2026-04-06 | F61: LE-02 | G61: LOC-CHN | H61: OU-111 | I61: DES-13 | J61: A | K61: WC-PERM | L61: PLANT12 | M61: SH-A | N61: E1054 | O61: Selvaraj Murugan | P61: PLANT-CHN | R61: Active | S61: UAN000100039220 | T61: XXXX8020 | U61: Point 7 — April joiner, 4 CL/SL | V61: CAT-PERM — Permanent | X61: Y | Y61: Sunday weekly off | Z61: Monthly | AA61: Y | AB61: All days | AC61: 2 | AD61: LS-STD | AE61: STANDARD | AG61: 60 | AH61: 2026-10-06 | AI61: LOC-CHN | AJ61: LOC-CHN | AK61: 0.44 | AL61: 20 | AM61: N | AN61: 4 | AO61: 2 | AP61: VPI-1060
A62: E1061 | B62: Murugesan Palani | C62: M | D62: 1990-10-30 | E62: 2026-05-11 | F62: LE-02 | G62: LOC-CHN | H62: OU-111 | I62: DES-18 | J62: H | K62: WC-CONT | L62: PLANT12 | M62: SH-A | N62: E1054 | O62: Selvaraj Murugan | P62: PLANT-CHN | Q62: VN-05 | R62: Active | S62: UAN000100039257 | T62: XXXX8037 | U62: Points 2, 7 — May joiner, daily wage | V62: CAT-CONT — Contractual | X62: N | Z62: Daily | AA62: Y | AB62: All days | AC62: 2 | AD62: LS-NONE | AE62: NOT_ELIGIBLE | AH62: Not applicable — scheme accrues no EL | AI62: LOC-CHN | AJ62: LOC-CHN | AK62: 0.35 | AL62: 5 | AM62: N | AP62: VPI-1061 | AQ62: no rest day — resolves at category level; not leave eligible
A63: E1062 | B63: Saravanan Thangavel | C63: M | D63: 1992-04-09 | E63: 2025-12-01 | F63: LE-02 | G63: LOC-CHN | H63: OU-114 | I63: DES-14 | J63: A | K63: WC-3PE | L63: PLANT12 | M63: SH-A | N63: E1054 | O63: Selvaraj Murugan | P63: PLANT-CHN | Q63: VN-05 | R63: Active | S63: UAN000100039294 | T63: XXXX8054 | V63: CAT-3P — Third party | W63: SUB-EMP — Employee | X63: Y | Y63: Sunday weekly off | Z63: Monthly | AA63: Y | AB63: Rest days and holidays only | AC63: 2 | AD63: LS-NONE | AE63: NOT_ELIGIBLE | AH63: Not applicable — scheme accrues no EL | AI63: LOC-CHN | AJ63: LOC-CHN | AK63: 0.79 | AL63: 20 | AM63: N | AP63: VPI-1062 | AQ63: OT only on a rest day or holiday; not leave eligible
A64: E1063 | B64: Revathi Natarajan | C64: F | D64: 2004-02-17 | E64: 2026-02-16 | F64: LE-02 | G64: LOC-CHN | H64: OU-113 | I64: DES-19 | J64: T | K64: WC-APP | L64: STAFF9 | M64: SH-E | N64: E1055 | O64: Kalaivani Subramani | P64: PLANT-CHN | R64: Active | T64: XXXX8071 | U64: Apprentice — no PF/ESI | V64: CAT-APP — Apprentice | X64: Y | Y64: Sunday weekly off | Z64: Monthly | AA64: Y | AB64: All days | AC64: 2 | AD64: LS-NONE | AE64: NOT_ELIGIBLE | AF64: Apprentice | AH64: Not applicable — scheme accrues no EL | AI64: LOC-CHN | AJ64: LOC-CHN | AK64: 0.58 | AL64: 10 | AM64: N | AP64: VPI-1063 | AQ64: not leave eligible
A65: E1064 | B65: Gopinath Sekar | C65: M | D65: 1971-08-05 | E65: 2026-06-01 | F65: LE-02 | G65: LOC-CHN | H65: OU-180 | I65: DES-20 | J65: C | K65: WC-CONS | L65: OFFICE8 | M65: SH-F | N65: E1054 | O65: Selvaraj Murugan | P65: HO | R65: Active | T65: XXXX8088 | U65: Consultant — TDS 194J, no leave | V65: CAT-RET — Retainer | X65: N | Z65: Monthly | AA65: Y | AB65: All days | AC65: 2 | AD65: LS-NONE | AE65: NOT_ELIGIBLE | AH65: Not applicable — scheme accrues no EL | AI65: LOC-BLR | AJ65: LOC-CHN | AK65: 0.29 | AL65: 50 | AM65: Y | AP65: VPI-1064 | AQ65: no rest day — resolves at category level; payrolled at head office while attending at LOC-CHN — point 8; not leave eligible
A66: E1065 | B66: Ishita Chatterjee | C66: F | D66: 1999-11-27 | E66: 2026-08-17 | F66: LE-01 | G66: LOC-BLR | H66: OU-130 | I66: DES-09 | J66: B | K66: WC-PERM | L66: OFFICE8 | M66: SH-F | N66: E1005 | O66: Prakash Venugopal | P66: HO | R66: Active | S66: UAN000100039405 | T66: XXXX8105 | U66: Point 7 — August joiner, 2 CL/SL | V66: CAT-PERM — Permanent | X66: Y | Y66: Sunday weekly off | Z66: Monthly | AA66: Y | AB66: All days | AC66: 2 | AD66: LS-STD | AE66: STANDARD | AG66: 60 | AH66: 2027-02-17 | AI66: LOC-BLR | AJ66: LOC-BLR | AK66: 0.08 | AL66: 35 | AM66: N | AN66: 4 | AO66: 2 | AP66: VPI-1065
A67: E1066 | B67: Abhinav Rastogi | C67: M | D67: 1997-07-13 | E67: 2026-09-01 | F67: LE-01 | G67: LOC-PUN | H67: OU-122 | I67: DES-11 | J67: A | K67: WC-PERM | L67: STAFF9 | M67: SH-E | N67: E1039 | O67: Sanjay Pawar | P67: PLANT-PUN | R67: Active | S67: UAN000100039442 | T67: XXXX8122 | U67: Point 7 — September joiner, 2 CL/SL | V67: CAT-PERM — Permanent | X67: Y | Y67: Sunday weekly off | Z67: Monthly | AA67: Y | AB67: All days | AC67: 2 | AD67: LS-STD | AE67: STANDARD | AG67: 60 | AH67: 2027-03-01 | AI67: LOC-PUN | AJ67: LOC-PUN | AK67: 0.04 | AL67: 30 | AM67: N | AN67: 4 | AO67: 2 | AP67: VPI-1066
A68: E1067 | B68: Ankita Bhargava | C68: F | D68: 1995-12-04 | E68: 2026-03-16 | F68: LE-01 | G68: LOC-BLR | H68: OU-113 | I68: DES-09 | J68: B | K68: WC-PERM | L68: OFFICE8 | M68: SH-F | N68: E1005 | O68: Prakash Venugopal | P68: HO | R68: Active | S68: UAN000100039479 | T68: XXXX8139 | U68: Point 7 — completes 6 months 16 Sep, 9 EL credited | V68: CAT-PERM — Permanent | X68: Y | Y68: Sunday weekly off | Z68: Monthly | AA68: Y | AB68: All days | AC68: 2 | AD68: LS-STD | AE68: STANDARD | AG68: 60 | AH68: 2026-09-16 | AI68: LOC-BLR | AJ68: LOC-BLR | AK68: 0.5 | AL68: 35 | AM68: N | AN68: 4 | AO68: 2 | AP68: VPI-1067
A69: E1068 | B69: Dinesh Vaidya | C69: M | D69: 1987-03-18 | E69: 2019-05-06 | F69: LE-01 | G69: LOC-PUN | H69: OU-130 | I69: DES-08 | J69: B | K69: WC-PERM | L69: STAFF9 | M69: SH-E | N69: E1039 | O69: Sanjay Pawar | P69: PLANT-PUN | R69: In notice | S69: UAN000100039516 | T69: XXXX8156 | U69: Point 16 — resigned, LWD 30 Sep, F&F | V69: CAT-PERM — Permanent | X69: Y | Y69: Sunday weekly off | Z69: Monthly | AA69: Y | AB69: All days | AC69: 2 | AD69: LS-STD | AE69: STANDARD | AG69: 60 | AH69: Eligible — six months completed before 2026 | AI69: LOC-PUN | AJ69: LOC-PUN | AK69: 7.36 | AL69: 40 | AM69: N | AN69: 4 | AO69: 2 | AP69: VPI-1068
A70: E1069 | B70: Meera Prabhu | C70: F | D70: 1993-02-11 | E70: 2026-01-12 | F70: LE-01 | G70: LOC-PLA | H70: OU-113 | I70: DES-11 | J70: A | K70: WC-PERM | L70: STAFF9 | M70: SH-E | N70: E1024 | O70: Srinivas Achar | P70: PLANT-BLR | R70: Active | S70: UAN000100039553 | T70: XXXX7418 | U70: Added v1.1 — the January 2026 joiner the proration ladder needed (PR-01, 6 CL and 6 SL). Fills the one vacancy that sheet 10 showed against SM-004. | V70: CAT-PERM — Permanent | X70: Y | Y70: Sunday weekly off | Z70: Monthly | AA70: Y | AB70: All days | AC70: 2 | AD70: LS-STD | AE70: STANDARD | AG70: 60 | AH70: 2026-07-12 | AI70: LOC-PLA | AJ70: LOC-PLA | AK70: 0.67 | AL70: 30 | AM70: N | AN70: 4 | AO70: 2 | AP70: VPI-1069
A72: 69 workers across 9 worker classes, 5 sites and 4 states. E1056 is the point-8 record: located at Chennai, payrolled at head office. Payroll group and location are independent by design. ADDED v1.1 — columns V to AQ carry the policy attributes the WIP requirements are actually about: rest-day applicability (R-03, R-04), OT eligibility basis (R-05), leave scheme and COFF lapse (R-07, R-08), payroll versus attendance location (R-09), continuous service for the loan ceiling (R-10) and the gate-pass entitlement (R-12). Every value is derived from 38_Employment_Categories, 05_Designations and 06_Worker_Classes, so the resolution order in rule RL-05 can be demonstrated rather than asserted.

Sheet 13_Salary_Structure
A1: Employee code | B1: Name | C1: Worker class | D1: Wage type | E1: Basic (INR) | F1: DA (INR) | G1: HRA (INR) | H1: Conveyance (INR) | I1: Special allowance (INR) | J1: Daily rate (INR) | K1: Monthly retainer (INR) | L1: Monthly gross (INR) | M1: Wage base — Basic+DA (INR) | N1: Excluded components (INR) | O1: Excluded as % of gross | P1: 50% floor add-back (INR) | Q1: Statutory wage base (INR)
A2: E1001 | B2: Arvind Raghunathan | C2: WC-PERM | D2: Monthly | E2: 182000 | F2: 21840 | G2: 72800 | H2: 1600 | I2: 50960 | L2: =IF($D2<>"Monthly","",SUM($E2:$I2)) -> 329200 | M2: =IF($D2<>"Monthly","",$E2+$F2) -> 203840 | N2: =IF($D2<>"Monthly","",$L2-$M2) -> 125360 | O2: =IF($D2<>"Monthly","",$N2/$L2) -> 0.38080194 | P2: =IF($D2<>"Monthly","",MAX(0,$N2-0.5*$L2)) -> 0 | Q2: =IF($D2<>"Monthly","",$M2+$P2) -> 203840
A3: E1002 | B3: Meenakshi Sundaram | C3: WC-PERM | D3: Monthly | E3: 182250 | F3: 21870 | G3: 72900 | H3: 1600 | I3: 51030 | L3: =IF($D3<>"Monthly","",SUM($E3:$I3)) -> 329650 | M3: =IF($D3<>"Monthly","",$E3+$F3) -> 204120 | N3: =IF($D3<>"Monthly","",$L3-$M3) -> 125530 | O3: =IF($D3<>"Monthly","",$N3/$L3) -> 0.38079782 | P3: =IF($D3<>"Monthly","",MAX(0,$N3-0.5*$L3)) -> 0 | Q3: =IF($D3<>"Monthly","",$M3+$P3) -> 204120
A4: E1003 | B4: Farhan Qureshi | C4: WC-PERM | D4: Monthly | E4: 182500 | F4: 21900 | G4: 73000 | H4: 1600 | I4: 51100 | L4: =IF($D4<>"Monthly","",SUM($E4:$I4)) -> 330100 | M4: =IF($D4<>"Monthly","",$E4+$F4) -> 204400 | N4: =IF($D4<>"Monthly","",$L4-$M4) -> 125700 | O4: =IF($D4<>"Monthly","",$N4/$L4) -> 0.3807937 | P4: =IF($D4<>"Monthly","",MAX(0,$N4-0.5*$L4)) -> 0 | Q4: =IF($D4<>"Monthly","",$M4+$P4) -> 204400
A5: E1004 | B5: Ritu Balachandran | C5: WC-PERM | D5: Monthly | E5: 108750 | F5: 13050 | G5: 43500 | H5: 1600 | I5: 30450 | L5: =IF($D5<>"Monthly","",SUM($E5:$I5)) -> 197350 | M5: =IF($D5<>"Monthly","",$E5+$F5) -> 121800 | N5: =IF($D5<>"Monthly","",$L5-$M5) -> 75550 | O5: =IF($D5<>"Monthly","",$N5/$L5) -> 0.3828224 | P5: =IF($D5<>"Monthly","",MAX(0,$N5-0.5*$L5)) -> 0 | Q5: =IF($D5<>"Monthly","",$M5+$P5) -> 121800
A6: E1005 | B6: Prakash Venugopal | C6: WC-PERM | D6: Monthly | E6: 109000 | F6: 13080 | G6: 43600 | H6: 1600 | I6: 30520 | L6: =IF($D6<>"Monthly","",SUM($E6:$I6)) -> 197800 | M6: =IF($D6<>"Monthly","",$E6+$F6) -> 122080 | N6: =IF($D6<>"Monthly","",$L6-$M6) -> 75720 | O6: =IF($D6<>"Monthly","",$N6/$L6) -> 0.38281092 | P6: =IF($D6<>"Monthly","",MAX(0,$N6-0.5*$L6)) -> 0 | Q6: =IF($D6<>"Monthly","",$M6+$P6) -> 122080
A7: E1006 | B7: Anita Mathew | C7: WC-PERM | D7: Monthly | E7: 62250 | F7: 7470 | G7: 24900 | H7: 1600 | I7: 17430 | L7: =IF($D7<>"Monthly","",SUM($E7:$I7)) -> 113650 | M7: =IF($D7<>"Monthly","",$E7+$F7) -> 69720 | N7: =IF($D7<>"Monthly","",$L7-$M7) -> 43930 | O7: =IF($D7<>"Monthly","",$N7/$L7) -> 0.38653762 | P7: =IF($D7<>"Monthly","",MAX(0,$N7-0.5*$L7)) -> 0 | Q7: =IF($D7<>"Monthly","",$M7+$P7) -> 69720
A8: E1007 | B8: Deepak Sarangi | C8: WC-PERM | D8: Monthly | E8: 62500 | F8: 7500 | G8: 25000 | H8: 1600 | I8: 17500 | L8: =IF($D8<>"Monthly","",SUM($E8:$I8)) -> 114100 | M8: =IF($D8<>"Monthly","",$E8+$F8) -> 70000 | N8: =IF($D8<>"Monthly","",$L8-$M8) -> 44100 | O8: =IF($D8<>"Monthly","",$N8/$L8) -> 0.38650307 | P8: =IF($D8<>"Monthly","",MAX(0,$N8-0.5*$L8)) -> 0 | Q8: =IF($D8<>"Monthly","",$M8+$P8) -> 70000
A9: E1008 | B9: Shalini Krishnamurthy | C9: WC-PERM | D9: Monthly | E9: 21500 | F9: 2580 | G9: 8600 | H9: 1600 | I9: 6020 | L9: =IF($D9<>"Monthly","",SUM($E9:$I9)) -> 40300 | M9: =IF($D9<>"Monthly","",$E9+$F9) -> 24080 | N9: =IF($D9<>"Monthly","",$L9-$M9) -> 16220 | O9: =IF($D9<>"Monthly","",$N9/$L9) -> 0.40248139 | P9: =IF($D9<>"Monthly","",MAX(0,$N9-0.5*$L9)) -> 0 | Q9: =IF($D9<>"Monthly","",$M9+$P9) -> 24080
A10: E1009 | B10: Vikram Chauhan | C10: WC-PERM | D10: Monthly | E10: 37750 | F10: 4530 | G10: 15100 | H10: 1600 | I10: 10570 | L10: =IF($D10<>"Monthly","",SUM($E10:$I10)) -> 69550 | M10: =IF($D10<>"Monthly","",$E10+$F10) -> 42280 | N10: =IF($D10<>"Monthly","",$L10-$M10) -> 27270 | O10: =IF($D10<>"Monthly","",$N10/$L10) -> 0.39209202 | P10: =IF($D10<>"Monthly","",MAX(0,$N10-0.5*$L10)) -> 0 | Q10: =IF($D10<>"Monthly","",$M10+$P10) -> 42280
A11: E1010 | B11: Nandita Bose | C11: WC-PERM | D11: Monthly | E11: 61500 | F11: 7380 | G11: 24600 | H11: 1600 | I11: 17220 | L11: =IF($D11<>"Monthly","",SUM($E11:$I11)) -> 112300 | M11: =IF($D11<>"Monthly","",$E11+$F11) -> 68880 | N11: =IF($D11<>"Monthly","",$L11-$M11) -> 43420 | O11: =IF($D11<>"Monthly","",$N11/$L11) -> 0.38664292 | P11: =IF($D11<>"Monthly","",MAX(0,$N11-0.5*$L11)) -> 0 | Q11: =IF($D11<>"Monthly","",$M11+$P11) -> 68880
A12: E1011 | B12: Rohit Agarwal | C12: WC-PERM | D12: Monthly | E12: 22250 | F12: 2670 | G12: 8900 | H12: 1600 | I12: 6230 | L12: =IF($D12<>"Monthly","",SUM($E12:$I12)) -> 41650 | M12: =IF($D12<>"Monthly","",$E12+$F12) -> 24920 | N12: =IF($D12<>"Monthly","",$L12-$M12) -> 16730 | O12: =IF($D12<>"Monthly","",$N12/$L12) -> 0.40168067 | P12: =IF($D12<>"Monthly","",MAX(0,$N12-0.5*$L12)) -> 0 | Q12: =IF($D12<>"Monthly","",$M12+$P12) -> 24920
A13: E1012 | B13: Sameer Kulkarni | C13: WC-PERM | D13: Monthly | E13: 62000 | F13: 7440 | G13: 24800 | H13: 1600 | I13: 17360 | L13: =IF($D13<>"Monthly","",SUM($E13:$I13)) -> 113200 | M13: =IF($D13<>"Monthly","",$E13+$F13) -> 69440 | N13: =IF($D13<>"Monthly","",$L13-$M13) -> 43760 | O13: =IF($D13<>"Monthly","",$N13/$L13) -> 0.38657244 | P13: =IF($D13<>"Monthly","",MAX(0,$N13-0.5*$L13)) -> 0 | Q13: =IF($D13<>"Monthly","",$M13+$P13) -> 69440
... A32: E1031 | B32: Divya Hegde | C32: WC-TRN | D32: Monthly | E32: 14000 | F32: 1680 | G32: 5600 | H32: 1600 | I32: 3920 | L32: =IF($D32<>"Monthly","",SUM($E32:$I32)) -> 26800 | M32: =IF($D32<>"Monthly","",$E32+$F32) -> 15680 | N32: =IF($D32<>"Monthly","",$L32-$M32) -> 11120 | O32: =IF($D32<>"Monthly","",$N32/$L32) -> 0.41492537 | P32: =IF($D32<>"Monthly","",MAX(0,$N32-0.5*$L32)) -> 0 | Q32: =IF($D32<>"Monthly","",$M32+$P32) -> 15680
A33: E1032 | B33: Shivanna Muniyappa | C33: WC-CONT | D33: Daily | J33: 650 | L33: =IF($D33<>"Monthly","",SUM($E33:$I33)) | M33: =IF($D33<>"Monthly","",$E33+$F33) | N33: =IF($D33<>"Monthly","",$L33-$M33) | O33: =IF($D33<>"Monthly","",$N33/$L33) | P33: =IF($D33<>"Monthly","",MAX(0,$N33-0.5*$L33)) | Q33: =IF($D33<>"Monthly","",$M33+$P33)
A34: E1033 | B34: Ratnamma Devaraju | C34: WC-CONT | D34: Daily | J34: 665 | L34: =IF($D34<>"Monthly","",SUM($E34:$I34)) | M34: =IF($D34<>"Monthly","",$E34+$F34) | N34: =IF($D34<>"Monthly","",$L34-$M34) | O34: =IF($D34<>"Monthly","",$N34/$L34) | P34: =IF($D34<>"Monthly","",MAX(0,$N34-0.5*$L34)) | Q34: =IF($D34<>"Monthly","",$M34+$P34)
A35: E1034 | B35: Imran Shaikh | C35: WC-3PE | D35: Monthly | E35: 22750 | F35: 2730 | G35: 9100 | H35: 1600 | I35: 6370 | L35: =IF($D35<>"Monthly","",SUM($E35:$I35)) -> 42550 | M35: =IF($D35<>"Monthly","",$E35+$F35) -> 25480 | N35: =IF($D35<>"Monthly","",$L35-$M35) -> 17070 | O35: =IF($D35<>"Monthly","",$N35/$L35) -> 0.40117509 | P35: =IF($D35<>"Monthly","",MAX(0,$N35-0.5*$L35)) -> 0 | Q35: =IF($D35<>"Monthly","",$M35+$P35) -> 25480
A36: E1035 | B36: Ashok Naik | C36: WC-3PE | D36: Monthly | E36: 23000 | F36: 2760 | G36: 9200 | H36: 1600 | I36: 6440 | L36: =IF($D36<>"Monthly","",SUM($E36:$I36)) -> 43000 | M36: =IF($D36<>"Monthly","",$E36+$F36) -> 25760 | N36: =IF($D36<>"Monthly","",$L36-$M36) -> 17240 | O36: =IF($D36<>"Monthly","",$N36/$L36) -> 0.40093023 | P36: =IF($D36<>"Monthly","",MAX(0,$N36-0.5*$L36)) -> 0 | Q36: =IF($D36<>"Monthly","",$M36+$P36) -> 25760
A37: E1036 | B37: Lakshmi Rao | C37: WC-3PH | D37: Daily | J37: 635 | L37: =IF($D37<>"Monthly","",SUM($E37:$I37)) | M37: =IF($D37<>"Monthly","",$E37+$F37) | N37: =IF($D37<>"Monthly","",$L37-$M37) | O37: =IF($D37<>"Monthly","",$N37/$L37) | P37: =IF($D37<>"Monthly","",MAX(0,$N37-0.5*$L37)) | Q37: =IF($D37<>"Monthly","",$M37+$P37)
A38: E1037 | B38: Venkatesh Murthy | C38: WC-PERM | D38: Monthly | E38: 21750 | F38: 2610 | G38: 8700 | H38: 1600 | I38: 6090 | L38: =IF($D38<>"Monthly","",SUM($E38:$I38)) -> 40750 | M38: =IF($D38<>"Monthly","",$E38+$F38) -> 24360 | N38: =IF($D38<>"Monthly","",$L38-$M38) -> 16390 | O38: =IF($D38<>"Monthly","",$N38/$L38) -> 0.40220859 | P38: =IF($D38<>"Monthly","",MAX(0,$N38-0.5*$L38)) -> 0 | Q38: =IF($D38<>"Monthly","",$M38+$P38) -> 24360
A39: E1038 | B39: Parvathi Bai | C39: WC-3PH | D39: Daily | J39: 665 | L39: =IF($D39<>"Monthly","",SUM($E39:$I39)) | M39: =IF($D39<>"Monthly","",$E39+$F39) | N39: =IF($D39<>"Monthly","",$L39-$M39) | O39: =IF($D39<>"Monthly","",$N39/$L39) | P39: =IF($D39<>"Monthly","",MAX(0,$N39-0.5*$L39)) | Q39: =IF($D39<>"Monthly","",$M39+$P39)
A40: E1039 | B40: Sanjay Pawar | C40: WC-PERM | D40: Monthly | E40: 108750 | F40: 13050 | G40: 43500 | H40: 1600 | I40: 30450 | L40: =IF($D40<>"Monthly","",SUM($E40:$I40)) -> 197350 | M40: =IF($D40<>"Monthly","",$E40+$F40) -> 121800 | N40: =IF($D40<>"Monthly","",$L40-$M40) -> 75550 | O40: =IF($D40<>"Monthly","",$N40/$L40) -> 0.3828224 | P40: =IF($D40<>"Monthly","",MAX(0,$N40-0.5*$L40)) -> 0 | Q40: =IF($D40<>"Monthly","",$M40+$P40) -> 121800
A41: E1040 | B41: Aditi Joshi | C41: WC-PERM | D41: Monthly | E41: 62000 | F41: 7440 | G41: 24800 | H41: 1600 | I41: 17360 | L41: =IF($D41<>"Monthly","",SUM($E41:$I41)) -> 113200 | M41: =IF($D41<>"Monthly","",$E41+$F41) -> 69440 | N41: =IF($D41<>"Monthly","",$L41-$M41) -> 43760 | O41: =IF($D41<>"Monthly","",$N41/$L41) -> 0.38657244 | P41: =IF($D41<>"Monthly","",MAX(0,$N41-0.5*$L41)) -> 0 | Q41: =IF($D41<>"Monthly","",$M41+$P41) -> 69440
A42: E1041 | B42: Mahesh Shinde | C42: WC-PERM | D42: Monthly | E42: 38750 | F42: 4650 | G42: 15500 | H42: 1600 | I42: 10850 | L42: =IF($D42<>"Monthly","",SUM($E42:$I42)) -> 71350 | M42: =IF($D42<>"Monthly","",$E42+$F42) -> 43400 | N42: =IF($D42<>"Monthly","",$L42-$M42) -> 27950 | O42: =IF($D42<>"Monthly","",$N42/$L42) -> 0.3917309 | P42: =IF($D42<>"Monthly","",MAX(0,$N42-0.5*$L42)) -> 0 | Q42: =IF($D42<>"Monthly","",$M42+$P42) -> 43400
A43: E1042 | B43: Swapnil Kadam | C43: WC-PERM | D43: Monthly | E43: 39000 | F43: 4680 | G43: 15600 | H43: 1600 | I43: 10920 | L43: =IF($D43<>"Monthly","",SUM($E43:$I43)) -> 71800 | M43: =IF($D43<>"Monthly","",$E43+$F43) -> 43680 | N43: =IF($D43<>"Monthly","",$L43-$M43) -> 28120 | O43: =IF($D43<>"Monthly","",$N43/$L43) -> 0.39164345 | P43: =IF($D43<>"Monthly","",MAX(0,$N43-0.5*$L43)) -> 0 | Q43: =IF($D43<>"Monthly","",$M43+$P43) -> 43680
A44: E1043 | B44: Neha Mishra | C44: WC-PERM | D44: Monthly | E44: 21500 | F44: 2580 | G44: 8600 | H44: 1600 | I44: 6020 | L44: =IF($D44<>"Monthly","",SUM($E44:$I44)) -> 40300 | M44: =IF($D44<>"Monthly","",$E44+$F44) -> 24080 | N44: =IF($D44<>"Monthly","",$L44-$M44) -> 16220 | O44: =IF($D44<>"Monthly","",$N44/$L44) -> 0.40248139 | P44: =IF($D44<>"Monthly","",MAX(0,$N44-0.5*$L44)) -> 0 | Q44: =IF($D44<>"Monthly","",$M44+$P44) -> 24080
A45: E1044 | B45: Rahul Gaikwad | C45: WC-PERM | D45: Monthly | E45: 21750 | F45: 2610 | G45: 8700 | H45: 1600 | I45: 6090 | L45: =IF($D45<>"Monthly","",SUM($E45:$I45)) -> 40750 | M45: =IF($D45<>"Monthly","",$E45+$F45) -> 24360 | N45: =IF($D45<>"Monthly","",$L45-$M45) -> 16390 | O45: =IF($D45<>"Monthly","",$N45/$L45) -> 0.40220859 | P45: =IF($D45<>"Monthly","",MAX(0,$N45-0.5*$L45)) -> 0 | Q45: =IF($D45<>"Monthly","",$M45+$P45) -> 24360
A46: E1045 | B46: Sunita Bhosale | C46: WC-PERM | D46: Monthly | E46: 22000 | F46: 2640 | G46: 8800 | H46: 1600 | I46: 6160 | L46: =IF($D46<>"Monthly","",SUM($E46:$I46)) -> 41200 | M46: =IF($D46<>"Monthly","",$E46+$F46) -> 24640 | N46: =IF($D46<>"Monthly","",$L46-$M46) -> 16560 | O46: =IF($D46<>"Monthly","",$N46/$L46) -> 0.40194175 | P46: =IF($D46<>"Monthly","",MAX(0,$N46-0.5*$L46)) -> 0 | Q46: =IF($D46<>"Monthly","",$M46+$P46) -> 24640
A47: E1046 | B47: Dattatray More | C47: WC-CONT | D47: Daily | J47: 635 | L47: =IF($D47<>"Monthly","",SUM($E47:$I47)) | M47: =IF($D47<>"Monthly","",$E47+$F47) | N47: =IF($D47<>"Monthly","",$L47-$M47) | O47: =IF($D47<>"Monthly","",$N47/$L47) | P47: =IF($D47<>"Monthly","",MAX(0,$N47-0.5*$L47)) | Q47: =IF($D47<>"Monthly","",$M47+$P47)
A48: E1047 | B48: Koteswara Rao | C48: WC-PERM | D48: Monthly | E48: 109000 | F48: 13080 | G48: 43600 | H48: 1600 | I48: 30520 | L48: =IF($D48<>"Monthly","",SUM($E48:$I48)) -> 197800 | M48: =IF($D48<>"Monthly","",$E48+$F48) -> 122080 | N48: =IF($D48<>"Monthly","",$L48-$M48) -> 75720 | O48: =IF($D48<>"Monthly","",$N48/$L48) -> 0.38281092 | P48: =IF($D48<>"Monthly","",MAX(0,$N48-0.5*$L48)) -> 0 | Q48: =IF($D48<>"Monthly","",$M48+$P48) -> 122080
A49: E1048 | B49: Sirisha Yadav | C49: WC-PERM | D49: Monthly | E49: 62250 | F49: 7470 | G49: 24900 | H49: 1600 | I49: 17430 | L49: =IF($D49<>"Monthly","",SUM($E49:$I49)) -> 113650 | M49: =IF($D49<>"Monthly","",$E49+$F49) -> 69720 | N49: =IF($D49<>"Monthly","",$L49-$M49) -> 43930 | O49: =IF($D49<>"Monthly","",$N49/$L49) -> 0.38653762 | P49: =IF($D49<>"Monthly","",MAX(0,$N49-0.5*$L49)) -> 0 | Q49: =IF($D49<>"Monthly","",$M49+$P49) -> 69720
A50: E1049 | B50: Naveen Bandaru | C50: WC-PERM | D50: Monthly | E50: 39000 | F50: 4680 | G50: 15600 | H50: 1600 | I50: 52650 | L50: =IF($D50<>"Monthly","",SUM($E50:$I50)) -> 113530 | M50: =IF($D50<>"Monthly","",$E50+$F50) -> 43680 | N50: =IF($D50<>"Monthly","",$L50-$M50) -> 69850 | O50: =IF($D50<>"Monthly","",$N50/$L50) -> 0.61525588 | P50: =IF($D50<>"Monthly","",MAX(0,$N50-0.5*$L50)) -> 13085 | Q50: =IF($D50<>"Monthly","",$M50+$P50) -> 56765
A51: E1050 | B51: Suresh Pillai | C51: WC-PERM | D51: Monthly | E51: 37500 | F51: 4500 | G51: 15000 | H51: 1600 | I51: 10500 | L51: =IF($D51<>"Monthly","",SUM($E51:$I51)) -> 69100 | M51: =IF($D51<>"Monthly","",$E51+$F51) -> 42000 | N51: =IF($D51<>"Monthly","",$L51-$M51) -> 27100 | O51: =IF($D51<>"Monthly","",$N51/$L51) -> 0.39218524 | P51: =IF($D51<>"Monthly","",MAX(0,$N51-0.5*$L51)) -> 0 | Q51: =IF($D51<>"Monthly","",$M51+$P51) -> 42000
A52: E1051 | B52: Haritha Reddy | C52: WC-PERM | D52: Monthly | E52: 37750 | F52: 4530 | G52: 15100 | H52: 1600 | I52: 10570 | L52: =IF($D52<>"Monthly","",SUM($E52:$I52)) -> 69550 | M52: =IF($D52<>"Monthly","",$E52+$F52) -> 42280 | N52: =IF($D52<>"Monthly","",$L52-$M52) -> 27270 | O52: =IF($D52<>"Monthly","",$N52/$L52) -> 0.39209202 | P52: =IF($D52<>"Monthly","",MAX(0,$N52-0.5*$L52)) -> 0 | Q52: =IF($D52<>"Monthly","",$M52+$P52) -> 42280
A53: E1052 | B53: Anjaneyulu Gadde | C53: WC-PERM | D53: Monthly | E53: 22000 | F53: 2640 | G53: 8800 | H53: 1600 | I53: 6160 | L53: =IF($D53<>"Monthly","",SUM($E53:$I53)) -> 41200 | M53: =IF($D53<>"Monthly","",$E53+$F53) -> 24640 | N53: =IF($D53<>"Monthly","",$L53-$M53) -> 16560 | O53: =IF($D53<>"Monthly","",$N53/$L53) -> 0.40194175 | P53: =IF($D53<>"Monthly","",MAX(0,$N53-0.5*$L53)) -> 0 | Q53: =IF($D53<>"Monthly","",$M53+$P53) -> 24640
A54: E1053 | B54: Padmaja Cheruku | C54: WC-3PH | D54: Daily | J54: 665 | L54: =IF($D54<>"Monthly","",SUM($E54:$I54)) | M54: =IF($D54<>"Monthly","",$E54+$F54) | N54: =IF($D54<>"Monthly","",$L54-$M54) | O54: =IF($D54<>"Monthly","",$N54/$L54) | P54: =IF($D54<>"Monthly","",MAX(0,$N54-0.5*$L54)) | Q54: =IF($D54<>"Monthly","",$M54+$P54)
A55: E1054 | B55: Selvaraj Murugan | C55: WC-PERM | D55: Monthly | E55: 109000 | F55: 13080 | G55: 43600 | H55: 1600 | I55: 30520 | L55: =IF($D55<>"Monthly","",SUM($E55:$I55)) -> 197800 | M55: =IF($D55<>"Monthly","",$E55+$F55) -> 122080 | N55: =IF($D55<>"Monthly","",$L55-$M55) -> 75720 | O55: =IF($D55<>"Monthly","",$N55/$L55) -> 0.38281092 | P55: =IF($D55<>"Monthly","",MAX(0,$N55-0.5*$L55)) -> 0 | Q55: =IF($D55<>"Monthly","",$M55+$P55) -> 122080
A56: E1055 | B56: Kalaivani Subramani | C56: WC-PERM | D56: Monthly | E56: 62250 | F56: 7470 | G56: 24900 | H56: 1600 | I56: 17430 | L56: =IF($D56<>"Monthly","",SUM($E56:$I56)) -> 113650 | M56: =IF($D56<>"Monthly","",$E56+$F56) -> 69720 | N56: =IF($D56<>"Monthly","",$L56-$M56) -> 43930 | O56: =IF($D56<>"Monthly","",$N56/$L56) -> 0.38653762 | P56: =IF($D56<>"Monthly","",MAX(0,$N56-0.5*$L56)) -> 0 | Q56: =IF($D56<>"Monthly","",$M56+$P56) -> 69720
A57: E1056 | B57: Anand Krishnan | C57: WC-PERM | D57: Monthly | E57: 39000 | F57: 4680 | G57: 15600 | H57: 1600 | I57: 10920 | L57: =IF($D57<>"Monthly","",SUM($E57:$I57)) -> 71800 | M57: =IF($D57<>"Monthly","",$E57+$F57) -> 43680 | N57: =IF($D57<>"Monthly","",$L57-$M57) -> 28120 | O57: =IF($D57<>"Monthly","",$N57/$L57) -> 0.39164345 | P57: =IF($D57<>"Monthly","",MAX(0,$N57-0.5*$L57)) -> 0 | Q57: =IF($D57<>"Monthly","",$M57+$P57) -> 43680
A58: E1057 | B58: Bhuvaneswari Raman | C58: WC-PERM | D58: Monthly | E58: 21500 | F58: 2580 | G58: 8600 | H58: 1600 | I58: 6020 | L58: =IF($D58<>"Monthly","",SUM($E58:$I58)) -> 40300 | M58: =IF($D58<>"Monthly","",$E58+$F58) -> 24080 | N58: =IF($D58<>"Monthly","",$L58-$M58) -> 16220 | O58: =IF($D58<>"Monthly","",$N58/$L58) -> 0.40248139 | P58: =IF($D58<>"Monthly","",MAX(0,$N58-0.5*$L58)) -> 0 | Q58: =IF($D58<>"Monthly","",$M58+$P58) -> 24080
A59: E1058 | B59: Karthik Chidambaram | C59: WC-PERM | D59: Monthly | E59: 37750 | F59: 4530 | G59: 15100 | H59: 1600 | I59: 10570 | L59: =IF($D59<>"Monthly","",SUM($E59:$I59)) -> 69550 | M59: =IF($D59<>"Monthly","",$E59+$F59) -> 42280 | N59: =IF($D59<>"Monthly","",$L59-$M59) -> 27270 | O59: =IF($D59<>"Monthly","",$N59/$L59) -> 0.39209202 | P59: =IF($D59<>"Monthly","",MAX(0,$N59-0.5*$L59)) -> 0 | Q59: =IF($D59<>"Monthly","",$M59+$P59) -> 42280
A60: E1059 | B60: Vetrivel Pandian | C60: WC-PERM | D60: Monthly | E60: 22000 | F60: 2640 | G60: 8800 | H60: 1600 | I60: 6160 | L60: =IF($D60<>"Monthly","",SUM($E60:$I60)) -> 41200 | M60: =IF($D60<>"Monthly","",$E60+$F60) -> 24640 | N60: =IF($D60<>"Monthly","",$L60-$M60) -> 16560 | O60: =IF($D60<>"Monthly","",$N60/$L60) -> 0.40194175 | P60: =IF($D60<>"Monthly","",MAX(0,$N60-0.5*$L60)) -> 0 | Q60: =IF($D60<>"Monthly","",$M60+$P60) -> 24640
A61: E1060 | B61: Jayanthi Elangovan | C61: WC-PERM | D61: Monthly | E61: 22250 | F61: 2670 | G61: 8900 | H61: 1600 | I61: 6230 | L61: =IF($D61<>"Monthly","",SUM($E61:$I61)) -> 41650 | M61: =IF($D61<>"Monthly","",$E61+$F61) -> 24920 | N61: =IF($D61<>"Monthly","",$L61-$M61) -> 16730 | O61: =IF($D61<>"Monthly","",$N61/$L61) -> 0.40168067 | P61: =IF($D61<>"Monthly","",MAX(0,$N61-0.5*$L61)) -> 0 | Q61: =IF($D61<>"Monthly","",$M61+$P61) -> 24920
A62: E1061 | B62: Murugesan Palani | C62: WC-CONT | D62: Daily | J62: 635 | L62: =IF($D62<>"Monthly","",SUM($E62:$I62)) | M62: =IF($D62<>"Monthly","",$E62+$F62) | N62: =IF($D62<>"Monthly","",$L62-$M62) | O62: =IF($D62<>"Monthly","",$N62/$L62) | P62: =IF($D62<>"Monthly","",MAX(0,$N62-0.5*$L62)) | Q62: =IF($D62<>"Monthly","",$M62+$P62)
A63: E1062 | B63: Saravanan Thangavel | C63: WC-3PE | D63: Monthly | E63: 22750 | F63: 2730 | G63: 9100 | H63: 1600 | I63: 6370 | L63: =IF($D63<>"Monthly","",SUM($E63:$I63)) -> 42550 | M63: =IF($D63<>"Monthly","",$E63+$F63) -> 25480 | N63: =IF($D63<>"Monthly","",$L63-$M63) -> 17070 | O63: =IF($D63<>"Monthly","",$N63/$L63) -> 0.40117509 | P63: =IF($D63<>"Monthly","",MAX(0,$N63-0.5*$L63)) -> 0 | Q63: =IF($D63<>"Monthly","",$M63+$P63) -> 25480
A64: E1063 | B64: Revathi Natarajan | C64: WC-APP | D64: Monthly | E64: 15000 | F64: 1800 | G64: 6000 | H64: 1600 | I64: 4200 | L64: =IF($D64<>"Monthly","",SUM($E64:$I64)) -> 28600 | M64: =IF($D64<>"Monthly","",$E64+$F64) -> 16800 | N64: =IF($D64<>"Monthly","",$L64-$M64) -> 11800 | O64: =IF($D64<>"Monthly","",$N64/$L64) -> 0.41258741 | P64: =IF($D64<>"Monthly","",MAX(0,$N64-0.5*$L64)) -> 0 | Q64: =IF($D64<>"Monthly","",$M64+$P64) -> 16800
A65: E1064 | B65: Gopinath Sekar | C65: WC-CONS | D65: Retainer | K65: 165000 | L65: =IF($D65<>"Monthly","",SUM($E65:$I65)) | M65: =IF($D65<>"Monthly","",$E65+$F65) | N65: =IF($D65<>"Monthly","",$L65-$M65) | O65: =IF($D65<>"Monthly","",$N65/$L65) | P65: =IF($D65<>"Monthly","",MAX(0,$N65-0.5*$L65)) | Q65: =IF($D65<>"Monthly","",$M65+$P65)
A66: E1065 | B66: Ishita Chatterjee | C66: WC-PERM | D66: Monthly | E66: 37750 | F66: 4530 | G66: 15100 | H66: 1600 | I66: 10570 | L66: =IF($D66<>"Monthly","",SUM($E66:$I66)) -> 69550 | M66: =IF($D66<>"Monthly","",$E66+$F66) -> 42280 | N66: =IF($D66<>"Monthly","",$L66-$M66) -> 27270 | O66: =IF($D66<>"Monthly","",$N66/$L66) -> 0.39209202 | P66: =IF($D66<>"Monthly","",MAX(0,$N66-0.5*$L66)) -> 0 | Q66: =IF($D66<>"Monthly","",$M66+$P66) -> 42280
A67: E1066 | B67: Abhinav Rastogi | C67: WC-PERM | D67: Monthly | E67: 22000 | F67: 2640 | G67: 8800 | H67: 1600 | I67: 6160 | L67: =IF($D67<>"Monthly","",SUM($E67:$I67)) -> 41200 | M67: =IF($D67<>"Monthly","",$E67+$F67) -> 24640 | N67: =IF($D67<>"Monthly","",$L67-$M67) -> 16560 | O67: =IF($D67<>"Monthly","",$N67/$L67) -> 0.40194175 | P67: =IF($D67<>"Monthly","",MAX(0,$N67-0.5*$L67)) -> 0 | Q67: =IF($D67<>"Monthly","",$M67+$P67) -> 24640
A68: E1067 | B68: Ankita Bhargava | C68: WC-PERM | D68: Monthly | E68: 38250 | F68: 4590 | G68: 15300 | H68: 1600 | I68: 10710 | L68: =IF($D68<>"Monthly","",SUM($E68:$I68)) -> 70450 | M68: =IF($D68<>"Monthly","",$E68+$F68) -> 42840 | N68: =IF($D68<>"Monthly","",$L68-$M68) -> 27610 | O68: =IF($D68<>"Monthly","",$N68/$L68) -> 0.39190916 | P68: =IF($D68<>"Monthly","",MAX(0,$N68-0.5*$L68)) -> 0 | Q68: =IF($D68<>"Monthly","",$M68+$P68) -> 42840
A69: E1068 | B69: Dinesh Vaidya | C69: WC-PERM | D69: Monthly | E69: 38500 | F69: 4620 | G69: 15400 | H69: 1600 | I69: 10780 | L69: =IF($D69<>"Monthly","",SUM($E69:$I69)) -> 70900 | M69: =IF($D69<>"Monthly","",$E69+$F69) -> 43120 | N69: =IF($D69<>"Monthly","",$L69-$M69) -> 27780 | O69: =IF($D69<>"Monthly","",$N69/$L69) -> 0.39181946 | P69: =IF($D69<>"Monthly","",MAX(0,$N69-0.5*$L69)) -> 0 | Q69: =IF($D69<>"Monthly","",$M69+$P69) -> 43120
A70: E1069 | B70: Meera Prabhu | C70: WC-PERM | D70: Monthly | E70: 21750 | F70: 2610 | G70: 8700 | H70: 1600 | I70: 6090 | L70: =IF($D70<>"Monthly","",SUM($E70:$I70)) -> 40750 | M70: =IF($D70<>"Monthly","",$E70+$F70) -> 24360 | N70: =IF($D70<>"Monthly","",$L70-$M70) -> 16390 | O70: =IF($D70<>"Monthly","",$N70/$L70) -> 0.40220859 | P70: =IF($D70<>"Monthly","",MAX(0,$N70-0.5*$L70)) -> 0 | Q70: =IF($D70<>"Monthly","",$M70+$P70) -> 24360
A72: Columns L to Q are formulas implementing the Code on Wages 50% floor test from the blueprint. E1014 and E1049 are structured so that excluded components exceed 50% of gross and an add-back is required — use these two to demo the wage-base node and the structure simulator. ADDED v1.1: E1069 Meera Prabhu, carrying the same formulas as every other row.

Sheet 14_Leave_Types
A1: Leave type | B1: Name | C1: Unit | D1: Accrual | E1: Carry forward | F1: Year-end action | G1: Max per month | H1: Cannot be combined with | I1: Expiry rule | J1: Applies to bands | K1: Demo point
A2: EL | B2: Earned Leave | C2: Day | D2: Band-dependent | E2: Yes, up to 45 days | F2: Encash | G2: 10 | H2: CL | I2: None | J2: AGM_AND_ABOVE, STANDARD | K2: Point 7
A3: CL | B3: Casual Leave | C3: Day | D3: Annual on 1 Jan, prorated for joiners | E3: No | F3: Lapse | G3: 2 | H3: EL, SL | I3: 31 Dec | J3: AGM_AND_ABOVE, STANDARD, TRAINEE_GET, TRAINEE_DET | K3: Point 7
A4: SL | B4: Sick Leave | C4: Day | D4: Annual on 1 Jan, prorated for joiners | E4: No | F4: Lapse | H4: CL | I4: 31 Dec | J4: AGM_AND_ABOVE, STANDARD | K4: Point 7
A5: CO | B5: Compensatory Off | C5: Day | D5: On rest-day or holiday working | E5: No | F5: Lapse | I5: 60 days from each credit | J5: All eligible classes | K5: Point 6
A6: BL | B6: Birthday Leave | C6: Day | D6: One day, on or around date of birth | E6: No | F6: Lapse | G6: 1 | I6: Birth month | J6: AGM_AND_ABOVE, STANDARD | K6: Point 7
A7: ML | B7: Maternity Leave | C7: Day | D7: Statutory, on eligibility | E7: Not applicable | F7: Not applicable | I7: Per Maternity Benefit Act | J7: All eligible classes
A8: LOP | B8: Loss of Pay | C8: Day | D8: Not accrued | E8: Not applicable | F8: Not applicable | J8: All
A10: Casual leave cannot be taken with or merged into earned or sick leave, and is capped at 2 days a month. Earned leave is capped at 10 days a month. Both are validation rules on the request, evaluated before the approval chain starts.

Sheet 15_Leave_Accrual_Policy
A1: Policy code | B1: Leave band | C1: Leave type | D1: Annual days | E1: Accrual frequency | F1: Days per period | G1: Eligibility wait (months) | H1: Credit on completion | I1: Credit date | J1: Demo point | K1: Leave scheme | L1: Availing cap per month
A2: LP-01 | B2: AGM_AND_ABOVE | C2: EL | D2: 18 | E2: Annual | F2: 18 | G2: 0 | I2: 1 January | J2: Point 7 | K2: LS-AGM | L2: 10
A3: LP-02 | B3: AGM_AND_ABOVE | C3: CL | D3: 6 | E3: Annual | F3: 6 | G3: 0 | I3: 1 January | J3: Point 7 | K3: LS-AGM | L3: 2
A4: LP-03 | B4: AGM_AND_ABOVE | C4: SL | D4: 6 | E4: Annual | F4: 6 | G4: 0 | I4: 1 January | J4: Point 7 | K4: LS-AGM
A5: LP-04 | B5: STANDARD | C5: EL | D5: 18 | E5: Monthly | F5: 1.5 | G5: 6 | H5: 9 | I5: Last day of each month | J5: Point 7 | K5: LS-STD | L5: 10
A6: LP-05 | B6: STANDARD | C6: CL | D6: 6 | E6: Annual | F6: 6 | G6: 0 | I6: 1 January | J6: Point 7 | K6: LS-STD | L6: 2
A7: LP-06 | B7: STANDARD | C7: SL | D7: 6 | E7: Annual | F7: 6 | G7: 0 | I7: 1 January | J7: Point 7 | K7: LS-STD
A8: LP-07 | B8: TRAINEE_GET | C8: CL | D8: 6 | E8: Annual | F8: 6 | G8: 0 | I8: 1 January | J8: Point 7 | K8: LS-TRN | L8: 2
A9: LP-08 | B9: TRAINEE_DET | C9: CL | D9: 6 | E9: Annual | F9: 6 | G9: 0 | I9: 1 January | J9: Point 7 | K9: LS-TRN | L9: 2
A10: LP-09 | B10: AGM_AND_ABOVE | C10: BL | D10: 1 | E10: Annual | F10: 1 | G10: 0 | I10: Birth month | J10: Point 7 | K10: LS-AGM | L10: 1
A11: LP-10 | B11: STANDARD | C11: BL | D11: 1 | E11: Annual | F11: 1 | G11: 0 | I11: Birth month | J11: Point 7 | K11: LS-STD | L11: 1
A13: Standard-band employees accrue no earned leave for six months; on completing six months they receive 9 days as a single credit, then 1.5 days a month. E1067 Ankita Bhargava completes six months on 16 September 2026 — use her to show the credit landing. ADDED v1.1: every policy row now names the leave scheme it belongs to (39_Leave_Schemes) and its monthly availing cap. The cap is enforced on the application, never on the accrual.

Sheet 16_Leave_Proration
A1: Rule code | B1: Joining month from | C1: Joining month to | D1: CL days | E1: SL days | F1: Example employee | G1: Demo point | H1: Leave-eligible check
A2: PR-01 | B2: January | C2: January | D2: 6 | E2: 6 | F2: E1069 Meera Prabhu — joined 12 Jan 2026 (WC-PERM, leave eligible) | G2: Point 7 | H2: Verified — worker class is leave eligible
A3: PR-02 | B3: February | C3: March | D3: 5 | E3: 5 | F3: E1067 Ankita Bhargava — joined 16 Mar 2026 (WC-PERM, leave eligible) | G3: Point 7 | H3: Verified — worker class is leave eligible
A4: PR-03 | B4: April | C4: May | D4: 4 | E4: 4 | F4: E1060 Jayanthi Elangovan — joined 06 Apr 2026 (WC-PERM, leave eligible) | G4: Point 7 | H4: Verified — worker class is leave eligible
A5: PR-04 | B5: June | C5: July | D5: 3 | E5: 3 | F5: E1030 Chetan Bhandary — joined 01 Jul 2026 (WC-TRN, CL only) | G5: Point 7 | H5: Verified — trainee scheme, CL only
A6: PR-05 | B6: August | C6: September | D6: 2 | E6: 2 | F6: E1065 Ishita Chatterjee — joined 17 Aug 2026 (WC-PERM, leave eligible) | G6: Point 7 | H6: Verified — worker class is leave eligible
A7: PR-06 | B7: October | C7: 4 December | D7: 1 | E7: 1 | F7: No current employee — see 61_Preboarding_Chain, C-2026-0071 joins 05 Oct 2026 | G7: Point 7 | H7: No record yet
A8: PR-07 | B8: 5 December | C8: 31 December | D8: 0 | E8: 0 | F8: No current employee — depends on the answer to open question Q-02 | G8: Point 7 | H8: No record yet
A10: CORRECTED v1.1. In v1.0 the PR-01 and PR-02 examples named E1038 Parvathi Bai and E1046 Dattatray More, who are a third-party helper and a contractual daily-wage worker — neither is leave eligible, so neither could carry a proration credit. PR-01 now points at E1069, added in v1.1 for exactly this rung; PR-02 points at E1067, who was already the worked example in sheet 15. Every named example is now a worker whose class actually accrues leave.

Sheet 17_Leave_Ledger
A1: Ledger ID | B1: Employee code | C1: Name | D1: Leave type | E1: Transaction | F1: Days | G1: Effective date | H1: Expires on | I1: Narration | J1: Source reference | K1: Demo point
A2: LL-0001 | B2: E1004 | C2: Ritu Balachandran | D2: EL | E2: Credit | F2: 18 | G2: 2026-01-01 | I2: Annual credit, AGM band | J2: LP-01 | K2: Point 7
A3: LL-0002 | B3: E1004 | C3: Ritu Balachandran | D3: CL | E3: Credit | F3: 6 | G3: 2026-01-01 | H3: 2026-12-31 | I3: Annual credit | J3: LP-02 | K3: Point 7
A4: LL-0003 | B4: E1004 | C4: Ritu Balachandran | D4: SL | E4: Credit | F4: 6 | G4: 2026-01-01 | H4: 2026-12-31 | I4: Annual credit | J4: LP-03 | K4: Point 7
A5: LL-0004 | B5: E1004 | C5: Ritu Balachandran | D5: EL | E5: Debit | F5: 5 | G5: 2026-05-18 | I5: Leave taken, LV-2026-0402
A6: LL-0005 | B6: E1019 | C6: Sneha Nair | D6: CL | E6: Credit | F6: 6 | G6: 2026-01-01 | H6: 2026-12-31 | I6: Annual credit | J6: LP-05 | K6: Point 7
A7: LL-0006 | B7: E1019 | C7: Sneha Nair | D7: SL | E7: Credit | F7: 6 | G7: 2026-01-01 | H7: 2026-12-31 | I7: Annual credit | J7: LP-06 | K7: Point 7
A8: LL-0007 | B8: E1019 | C8: Sneha Nair | D8: EL | E8: Credit | F8: 12 | G8: 2026-08-31 | I8: Monthly accrual Jan–Aug at 1.5/month | J8: LP-04 | K8: Point 7
A9: LL-0008 | B9: E1019 | C9: Sneha Nair | D9: CL | E9: Debit | F9: 2 | G9: 2026-06-11 | I9: Leave taken, LV-2026-0488
A10: LL-0009 | B10: E1043 | C10: Neha Mishra | D10: EL | E10: Credit | F10: 12 | G10: 2026-08-31 | I10: Monthly accrual Jan–Aug | J10: LP-04
A11: LL-0010 | B11: E1043 | C11: Neha Mishra | D11: CL | E11: Credit | F11: 6 | G11: 2026-01-01 | H11: 2026-12-31 | I11: Annual credit | J11: LP-05
A12: LL-0011 | B12: E1043 | C12: Neha Mishra | D12: EL | E12: Debit | F12: 10 | G12: 2026-09-07 | I12: Applied 10 days, LV-2026-0774 | K12: Point 5
A13: LL-0012 | B13: E1043 | C13: Neha Mishra | D13: EL | E13: Reversal | F13: 3 | G13: 2026-09-14 | I13: Early return from LV-2026-0774 — unused days re-credited, attendance recomputed for 14, 15 and 16 Sep | K13: Point 5
A14: LL-0013 | B14: E1067 | C14: Ankita Bhargava | D14: CL | E14: Credit | F14: 5 | G14: 2026-03-16 | H14: 2026-12-31 | I14: Proration rule PR-02, March joiner | J14: LP-05 | K14: Point 7
A15: LL-0014 | B15: E1067 | C15: Ankita Bhargava | D15: SL | E15: Credit | F15: 5 | G15: 2026-03-16 | H15: 2026-12-31 | I15: Proration rule PR-02, March joiner | J15: LP-06 | K15: Point 7
A16: LL-0015 | B16: E1067 | C16: Ankita Bhargava | D16: EL | E16: Credit | F16: 9 | G16: 2026-09-16 | I16: Six months completed — single 9-day credit | J16: LP-04 | K16: Point 7
A17: LL-0016 | B17: E1060 | C17: Jayanthi Elangovan | D17: CL | E17: Credit | F17: 4 | G17: 2026-04-06 | H17: 2026-12-31 | I17: Proration rule PR-03, April joiner | J17: LP-05 | K17: Point 7
A18: LL-0017 | B18: E1060 | C18: Jayanthi Elangovan | D18: SL | E18: Credit | F18: 4 | G18: 2026-04-06 | H18: 2026-12-31 | I18: Proration rule PR-03, April joiner | J18: LP-06 | K18: Point 7
A19: LL-0018 | B19: E1030 | C19: Chetan Bhandary | D19: CL | E19: Credit | F19: 3 | G19: 2026-07-01 | H19: 2026-12-31 | I19: Proration rule PR-04, GET trainee | J19: LP-07 | K19: Point 7
A20: LL-0019 | B20: E1031 | C20: Divya Hegde | D20: CL | E20: Credit | F20: 3 | G20: 2026-07-01 | H20: 2026-12-31 | I20: Proration rule PR-04, DET trainee | J20: LP-08 | K20: Point 7
A21: LL-0020 | B21: E1065 | C21: Ishita Chatterjee | D21: CL | E21: Credit | F21: 2 | G21: 2026-08-17 | H21: 2026-12-31 | I21: Proration rule PR-05, August joiner | J21: LP-05 | K21: Point 7
A22: LL-0021 | B22: E1065 | C22: Ishita Chatterjee | D22: SL | E22: Credit | F22: 2 | G22: 2026-08-17 | H22: 2026-12-31 | I22: Proration rule PR-05, August joiner | J22: LP-06 | K22: Point 7
A23: LL-0022 | B23: E1028 | C23: Yashoda Rani | D23: CO | E23: Credit | F23: 1 | G23: 2026-07-12 | H23: 2026-09-10 | I23: Rest-day working 12 Jul | J23: CO-2026-0231 | K23: Point 6
A24: LL-0023 | B24: E1028 | C24: Yashoda Rani | D24: CO | E24: Credit | F24: 1 | G24: 2026-09-06 | H24: 2026-11-05 | I24: Rest-day working 06 Sep | J24: CO-2026-0288 | K24: Point 6
A25: LL-0024 | B25: E1050 | C25: Suresh Pillai | D25: CO | E25: Credit | F25: 1 | G25: 2026-08-09 | H25: 2026-10-08 | I25: Rest-day working 09 Aug | J25: CO-2026-0266 | K25: Point 6
A26: LL-0025 | B26: E1050 | C26: Suresh Pillai | D26: CO | E26: Debit | F26: 1 | G26: 2026-08-28 | I26: Comp-off availed | J26: CO-2026-0244
A27: LL-0026 | B27: E1018 | C27: Ravi Kulkarni | D27: EL | E27: Credit | F27: 12 | G27: 2026-08-31 | I27: Monthly accrual Jan–Aug | J27: LP-04
A28: LL-0027 | B28: E1018 | C28: Ravi Kulkarni | D28: CL | E28: Credit | F28: 6 | G28: 2026-01-01 | H28: 2026-12-31 | I28: Annual credit | J28: LP-05
A29: LL-0028 | B29: E1022 | C29: Mohan Joseph | D29: CL | E29: Credit | F29: 6 | G29: 2026-01-01 | H29: 2026-12-31 | I29: Annual credit | J29: LP-05
A30: LL-0029 | B30: E1022 | C30: Mohan Joseph | D30: CL | E30: No movement — application rejected | F30: 0 | G30: 2026-09-09 | I30: CORRECTED v1.1. In v1.0 this row was a 2-day CL debit whose own narration said no leave was applied and LOP was raised. A debit with no leave behind it silently removes two days from the balance. Kept as a zero-day row so the rejected application is still visible.
A31: LL-0030 | B31: E1056 | C31: Anand Krishnan | D31: EL | E31: Credit | F31: 12 | G31: 2026-08-31 | I31: Monthly accrual Jan–Aug | J31: LP-04
A32: LL-0031 | B32: E1069 | C32: Meera Prabhu | D32: CL | E32: Credit | F32: 6 | G32: 2026-01-12 | H32: 2026-12-31 | I32: Proration rule PR-01, January joiner | J32: LP-05 | K32: Point 7
A33: LL-0032 | B33: E1069 | C33: Meera Prabhu | D33: SL | E33: Credit | F33: 6 | G33: 2026-01-12 | H33: 2026-12-31 | I33: Proration rule PR-01, January joiner | J33: LP-06 | K33: Point 7
A34: LL-0033 | B34: E1069 | C34: Meera Prabhu | D34: EL | E34: Credit | F34: 9 | G34: 2026-07-12 | I34: Six months completed 12 Jul — single 9-day catch-up credit | J34: LP-04 | K34: Point 7
A35: LL-0034 | B35: E1069 | C35: Meera Prabhu | D35: EL | E35: Credit | F35: 1.5 | G35: 2026-08-31 | I35: Monthly accrual resumes at 1.5 after the catch-up | J35: LP-04 | K35: Point 7
A36: LL-0035 | B36: E1069 | C36: Meera Prabhu | D36: CL | E36: Debit | F36: 1 | G36: 2026-08-21 | I36: Leave taken, LV-2026-0712
A37: LL-0036 | B37: E1068 | C37: Dinesh Vaidya | D37: EL | E37: Credit | F37: 12 | G37: 2026-08-31 | I37: Monthly accrual Jan–Aug | J37: LP-04
A38: LL-0037 | B38: E1068 | C38: Dinesh Vaidya | D38: EL | E38: Debit | F38: 4 | G38: 2026-05-11 | I38: Leave taken, LV-2026-0361
A39: LL-0038 | B39: E1068 | C39: Dinesh Vaidya | D39: EL | E39: Credit | F39: 1.5 | G39: 2026-09-30 | I39: September accrual, credited on the last working day | J39: LP-04 | K39: Point 16
A40: LL-0039 | B40: E1042 | C40: Swapnil Kadam | D40: EL | E40: Credit | F40: 12 | G40: 2026-08-31 | I40: Monthly accrual Jan–Aug | J40: LP-04
A41: LL-0040 | B41: E1042 | C41: Swapnil Kadam | D41: EL | E41: Debit | F41: 6 | G41: 2026-04-20 | I41: Leave taken, LV-2026-0288
A42: LL-0041 | B42: E1028 | C42: Yashoda Rani | D42: CO | E42: Debit | F42: 1 | G42: 2026-09-09 | I42: Comp-off availed against CO-2026-0231, LV-2026-0788 | J42: CO-2026-0231 | K42: ADDED v1.1 — sheet 19 showed this credit consumed but the ledger had no debit, so the balance read one day high
A43: LL-0042 | B43: E1050 | C43: Suresh Pillai | D43: CO | E43: Credit | F43: 1 | G43: 2026-06-29 | H43: 2026-08-28 | I43: Holiday working, stock count | J43: CO-2026-0244 | K43: ADDED v1.1 — the credit behind the LL-0025 debit was missing
A44: LL-0043 | B44: E1041 | C44: Mahesh Shinde | D44: CO | E44: Credit | F44: 1 | G44: 2026-09-13 | H44: 2026-11-12 | I44: Rest-day working, preventive maintenance | J44: CO-2026-0301 | K44: ADDED v1.1 — credit existed only in sheet 19
A45: LL-0044 | B45: E1044 | C45: Rahul Gaikwad | D45: CO | E45: Credit | F45: 1 | G45: 2026-05-31 | H45: 2026-07-30 | I45: Rest-day working | J45: CO-2026-0198 | K45: ADDED v1.1 — credit existed only in sheet 19
A46: LL-0045 | B46: E1044 | C46: Rahul Gaikwad | D46: CO | E46: Lapse | F46: 1 | G46: 2026-07-30 | I46: Lapsed unconsumed on its expiry date — nightly lapse run LAPSE-2026-07-30 | J46: CO-2026-0198 | K46: Point 6 — ADDED v1.1. Without this row the lapse existed as a status in sheet 19 but never touched the balance
A48: Balance is a projection over this ledger, not a stored column. Comp-off expiry, joiner proration and the early-return reversal all fall out of the ledger model — LL-0022 and LL-0023 are two credits for the same person on two separate 60-day clocks, which a single balance cannot express. ADDED v1.1: LL-0031 to LL-0035 give the January rung of the proration ladder and a second worked example of the six-month catch-up — E1069 already past it, E1067 landing on 16 September during the demo window. RECONCILED v1.1. Sheet 19 held six comp-off credits; the ledger carried only three of them and none of the consumptions or the lapse, so a balance built from the ledger disagreed with the comp-off register for four of the five workers. Every credit, availing and lapse in sheet 19 now has a matching ledger movement, and 53_Leave_Balance_AsOn is derived from this sheet alone. Reconcile the two before the demo — being asked to explain a balance and finding the ledger short is the worst moment to discover it.

Sheet 18_Leave_Requests
A1: Request ID | B1: Employee code | C1: Name | D1: Leave type | E1: From | F1: To | G1: Days applied | H1: Days availed | I1: Status | J1: Step 1 — Supervisor | K1: Step 2 — HOD | L1: Step 3 — HR Head | M1: HR edit | N1: Demo point
A2: LV-2026-0774 | B2: E1043 | C2: Neha Mishra | D2: EL | E2: 2026-09-07 | F2: 2026-09-16 | G2: 10 | H2: 7 | I2: Availed, early return | J2: E1039 approved 05 Sep | K2: E1039 approved 05 Sep | L2: E1004 approved 06 Sep | M2: E1006 closed the request on 14 Sep on early return; 3 unused days re-credited | N2: Point 5
A3: LV-2026-0801 | B3: E1019 | C3: Sneha Nair | D3: CL | E3: 2026-09-21 | F3: 2026-09-22 | G3: 2 | I3: Pending | J3: E1017 pending | N3: Point 7
A4: LV-2026-0802 | B4: E1019 | C4: Sneha Nair | D4: CL + EL | E4: 2026-09-24 | F4: 2026-09-28 | G4: 5 | I4: Rejected by rule | J4: Not routed | M4: Blocked at validation — casual leave cannot be combined with earned leave | N4: Point 7
A5: LV-2026-0803 | B5: E1018 | C5: Ravi Kulkarni | D5: EL | E5: 2026-10-05 | F5: 2026-10-16 | G5: 11 | I5: Rejected by rule | J5: Not routed | M5: Blocked at validation — exceeds the 10-day monthly cap on earned leave | N5: Point 7
A6: LV-2026-0788 | B6: E1028 | C6: Yashoda Rani | D6: CO | E6: 2026-09-09 | F6: 2026-09-09 | G6: 1 | I6: Approved | J6: E1021 approved 08 Sep | K6: E1016 approved 08 Sep | L6: E1004 approved 08 Sep | M6: Consumed against CO-2026-0231 before it lapsed on 10 Sep | N6: Point 6
A7: LV-2026-0795 | B7: E1057 | C7: Bhuvaneswari Raman | D7: SL | E7: 2026-09-10 | F7: 2026-09-11 | G7: 2 | H7: 2 | I7: Availed | J7: E1055 approved 10 Sep | K7: E1054 approved 10 Sep | L7: E1004 approved 11 Sep
A8: LV-2026-0812 | B8: E1067 | C8: Ankita Bhargava | D8: EL | E8: 2026-09-18 | F8: 2026-09-18 | G8: 1 | I8: Pending | J8: E1005 pending | M8: Applied the day after the 9-day credit landed | N8: Point 7
A10: Approval runs Supervisor, then HOD, then HR Head, sequentially. Two requests are rejected at validation before the chain starts, which is where combination and cap rules belong.

Sheet 19_CompOff_Ledger
A1: Credit ID | B1: Employee code | C1: Name | D1: Earned on | E1: Reason | F1: Days | G1: Expires on | H1: Status | I1: Consumed on | J1: Days remaining | K1: Demo point
A2: CO-2026-0231 | B2: E1028 | C2: Yashoda Rani | D2: 2026-07-12 | E2: Rest-day working, Assembly line changeover | F2: 1 | G2: 2026-09-10 | H2: Consumed | I2: 2026-09-09 | J2: 0 | K2: Point 6
A3: CO-2026-0288 | B3: E1028 | C3: Yashoda Rani | D3: 2026-09-06 | E3: Rest-day working, month-end despatch | F3: 1 | G3: 2026-11-05 | H3: Open | J3: 1 | K3: Point 6
A4: CO-2026-0244 | B4: E1050 | C4: Suresh Pillai | D4: 2026-06-29 | E4: Holiday working, stock count | F4: 1 | G4: 2026-08-28 | H4: Consumed | I4: 2026-08-28 | J4: 0 | K4: Point 6
A5: CO-2026-0266 | B5: E1050 | C5: Suresh Pillai | D5: 2026-08-09 | E5: Rest-day working, inbound clearance | F5: 1 | G5: 2026-10-08 | H5: Open | J5: 1 | K5: Point 6
A6: CO-2026-0301 | B6: E1041 | C6: Mahesh Shinde | D6: 2026-09-13 | E6: Rest-day working, preventive maintenance | F6: 1 | G6: 2026-11-12 | H6: Open | J6: 1 | K6: Point 6
A7: CO-2026-0198 | B7: E1044 | C7: Rahul Gaikwad | D7: 2026-05-31 | E7: Rest-day working | F7: 1 | G7: 2026-07-30 | H7: Lapsed | J7: 0 | K7: Point 6 — show a credit that expired unconsumed
A9: Each credit carries its own 60-day clock. Yashoda Rani holds two credits expiring nine weeks apart; Rahul Gaikwad has one that lapsed unused. This is the clearest single demonstration of why the leave model has to be a ledger.

Sheet 20_Punch_Events
A1: Event ID | B1: Employee code | C1: Name | D1: Attendance date | E1: Segment | F1: Direction | G1: Time | H1: Calendar date of punch | I1: Source | J1: Device | K1: Note
A2: PE-00001 | B2: E1018 | C2: Ravi Kulkarni | D2: 2026-09-01 | E2: 1 | F2: IN | G2: 07:55 | H2: 2026-09-01 | I2: Biometric | J2: BIO-PLA-01
A3: PE-00002 | B3: E1018 | C3: Ravi Kulkarni | D3: 2026-09-01 | E3: 1 | F3: OUT | G3: 20:06 | H3: 2026-09-01 | I3: Biometric | J3: BIO-PLA-01
A4: PE-00003 | B4: E1018 | C4: Ravi Kulkarni | D4: 2026-09-02 | E4: 1 | F4: IN | G4: 07:58 | H4: 2026-09-02 | I4: Biometric | J4: BIO-PLA-02
A5: PE-00004 | B5: E1018 | C5: Ravi Kulkarni | D5: 2026-09-02 | E5: 1 | F5: OUT | G5: 20:11 | H5: 2026-09-02 | I5: Biometric | J5: BIO-PLA-02
A6: PE-00005 | B6: E1018 | C6: Ravi Kulkarni | D6: 2026-09-03 | E6: 1 | F6: IN | G6: 07:53 | H6: 2026-09-03 | I6: Biometric | J6: BIO-PLA-03
A7: PE-00006 | B7: E1018 | C7: Ravi Kulkarni | D7: 2026-09-03 | E7: 1 | F7: OUT | G7: 20:03 | H7: 2026-09-03 | I7: Biometric | J7: BIO-PLA-03
A8: PE-00007 | B8: E1018 | C8: Ravi Kulkarni | D8: 2026-09-04 | E8: 1 | F8: IN | G8: 08:00 | H8: 2026-09-04 | I8: Biometric | J8: BIO-PLA-01
A9: PE-00008 | B9: E1018 | C9: Ravi Kulkarni | D9: 2026-09-04 | E9: 1 | F9: OUT | G9: 20:14 | H9: 2026-09-04 | I9: Biometric | J9: BIO-PLA-01
A10: PE-00009 | B10: E1018 | C10: Ravi Kulkarni | D10: 2026-09-05 | E10: 1 | F10: IN | G10: 07:56 | H10: 2026-09-05 | I10: Biometric | J10: BIO-PLA-02
A11: PE-00010 | B11: E1018 | C11: Ravi Kulkarni | D11: 2026-09-05 | E11: 1 | F11: OUT | G11: 20:08 | H11: 2026-09-05 | I11: Biometric | J11: BIO-PLA-02
A12: PE-00011 | B12: E1018 | C12: Ravi Kulkarni | D12: 2026-09-07 | E12: 1 | F12: IN | G12: 07:54 | H12: 2026-09-07 | I12: Biometric | J12: BIO-PLA-01
A13: PE-00012 | B13: E1018 | C13: Ravi Kulkarni | D13: 2026-09-07 | E13: 1 | F13: OUT | G13: 20:17 | H13: 2026-09-07 | I13: Biometric | J13: BIO-PLA-01
... A16: PE-00015 | B16: E1018 | C16: Ravi Kulkarni | D16: 2026-09-08 | E16: 2 | F16: IN | G16: 21:15 | H16: 2026-09-08 | I16: Biometric | J16: BIO-PLA-02
A17: PE-00016 | B17: E1018 | C17: Ravi Kulkarni | D17: 2026-09-08 | E17: 2 | F17: OUT | G17: 03:20 | H17: 2026-09-09 | I17: Biometric | J17: BIO-PLA-02 | K17: Next calendar day
A18: PE-00017 | B18: E1018 | C18: Ravi Kulkarni | D18: 2026-09-09 | E18: 1 | F18: IN | G18: 09:25 | H18: 2026-09-09 | I18: Biometric | J18: BIO-PLA-03
A19: PE-00018 | B19: E1018 | C19: Ravi Kulkarni | D19: 2026-09-09 | E19: 1 | F19: OUT | G19: 20:10 | H19: 2026-09-09 | I19: Biometric | J19: BIO-PLA-03
A20: PE-00019 | B20: E1018 | C20: Ravi Kulkarni | D20: 2026-09-10 | E20: 1 | F20: IN | G20: 08:01 | H20: 2026-09-10 | I20: Biometric | J20: BIO-PLA-01
A21: PE-00020 | B21: E1018 | C21: Ravi Kulkarni | D21: 2026-09-10 | E21: 1 | F21: OUT | G21: 20:12 | H21: 2026-09-10 | I21: Biometric | J21: BIO-PLA-01
A22: PE-00021 | B22: E1018 | C22: Ravi Kulkarni | D22: 2026-09-11 | E22: 1 | F22: IN | G22: 07:52 | H22: 2026-09-11 | I22: Biometric | J22: BIO-PLA-02
A23: PE-00022 | B23: E1018 | C23: Ravi Kulkarni | D23: 2026-09-11 | E23: 1 | F23: OUT | G23: 20:04 | H23: 2026-09-11 | I23: Biometric | J23: BIO-PLA-02
A24: PE-00023 | B24: E1018 | C24: Ravi Kulkarni | D24: 2026-09-12 | E24: 1 | F24: IN | G24: 08:02 | H24: 2026-09-12 | I24: Biometric | J24: BIO-PLA-03
A25: PE-00024 | B25: E1018 | C25: Ravi Kulkarni | D25: 2026-09-12 | E25: 1 | F25: OUT | G25: 20:19 | H25: 2026-09-12 | I25: Biometric | J25: BIO-PLA-03
A26: PE-00025 | B26: E1018 | C26: Ravi Kulkarni | D26: 2026-09-14 | E26: 1 | F26: IN | G26: 08:00 | H26: 2026-09-14 | I26: Biometric | J26: BIO-PLA-02
A27: PE-00026 | B27: E1018 | C27: Ravi Kulkarni | D27: 2026-09-14 | E27: 1 | F27: OUT | G27: 20:10 | H27: 2026-09-14 | I27: Biometric | J27: BIO-PLA-02
A28: PE-00027 | B28: E1018 | C28: Ravi Kulkarni | D28: 2026-09-15 | E28: 1 | F28: IN | G28: 07:57 | H28: 2026-09-15 | I28: Biometric | J28: BIO-PLA-03
A29: PE-00028 | B29: E1018 | C29: Ravi Kulkarni | D29: 2026-09-15 | E29: 1 | F29: OUT | G29: 20:06 | H29: 2026-09-15 | I29: Biometric | J29: BIO-PLA-03
... A62: PE-00061 | B62: E1020 | C62: Arjun Bhat | D62: 2026-09-04 | E62: 1 | F62: IN | G62: 20:05 | H62: 2026-09-04 | I62: Biometric | J62: BIO-PLA-01
A63: PE-00062 | B63: E1020 | C63: Arjun Bhat | D63: 2026-09-04 | E63: 1 | F63: OUT | G63: 08:40 | H63: 2026-09-05 | I63: Biometric | J63: BIO-PLA-01 | K63: Next calendar day
A64: PE-00063 | B64: E1020 | C64: Arjun Bhat | D64: 2026-09-05 | E64: 1 | F64: IN | G64: 07:56 | H64: 2026-09-05 | I64: Biometric | J64: BIO-PLA-02
A65: PE-00064 | B65: E1020 | C65: Arjun Bhat | D65: 2026-09-05 | E65: 1 | F65: OUT | G65: 20:08 | H65: 2026-09-05 | I65: Biometric | J65: BIO-PLA-02
A66: PE-00065 | B66: E1020 | C66: Arjun Bhat | D66: 2026-09-07 | E66: 1 | F66: IN | G66: 07:54 | H66: 2026-09-07 | I66: Biometric | J66: BIO-PLA-01
A67: PE-00066 | B67: E1020 | C67: Arjun Bhat | D67: 2026-09-07 | E67: 1 | F67: OUT | G67: 20:17 | H67: 2026-09-07 | I67: Biometric | J67: BIO-PLA-01
A68: PE-00067 | B68: E1020 | C68: Arjun Bhat | D68: 2026-09-08 | E68: 1 | F68: IN | G68: 07:59 | H68: 2026-09-08 | I68: Biometric | J68: BIO-PLA-02
A69: PE-00068 | B69: E1020 | C69: Arjun Bhat | D69: 2026-09-08 | E69: 1 | F69: OUT | G69: 20:05 | H69: 2026-09-08 | I69: Biometric | J69: BIO-PLA-02
A70: PE-00069 | B70: E1020 | C70: Arjun Bhat | D70: 2026-09-09 | E70: 1 | F70: IN | G70: 07:57 | H70: 2026-09-09 | I70: Biometric | J70: BIO-PLA-03
A71: PE-00070 | B71: E1020 | C71: Arjun Bhat | D71: 2026-09-09 | E71: 1 | F71: OUT | G71: 20:09 | H71: 2026-09-09 | I71: Biometric | J71: BIO-PLA-03
A72: PE-00071 | B72: E1020 | C72: Arjun Bhat | D72: 2026-09-10 | E72: 1 | F72: IN | G72: 08:01 | H72: 2026-09-10 | I72: Biometric | J72: BIO-PLA-01
A73: PE-00072 | B73: E1020 | C73: Arjun Bhat | D73: 2026-09-10 | E73: 1 | F73: OUT | G73: 20:12 | H73: 2026-09-10 | I73: Biometric | J73: BIO-PLA-01
A74: PE-00073 | B74: E1020 | C74: Arjun Bhat | D74: 2026-09-11 | E74: 1 | F74: IN | G74: 19:58 | H74: 2026-09-11 | I74: Biometric | J74: BIO-PLA-02
A75: PE-00074 | B75: E1020 | C75: Arjun Bhat | D75: 2026-09-11 | E75: 1 | F75: OUT | G75: 08:36 | H75: 2026-09-12 | I75: Biometric | J75: BIO-PLA-02 | K75: Next calendar day
A76: PE-00075 | B76: E1020 | C76: Arjun Bhat | D76: 2026-09-12 | E76: 1 | F76: IN | G76: 08:02 | H76: 2026-09-12 | I76: Biometric | J76: BIO-PLA-03
A77: PE-00076 | B77: E1020 | C77: Arjun Bhat | D77: 2026-09-12 | E77: 1 | F77: OUT | G77: 20:19 | H77: 2026-09-12 | I77: Biometric | J77: BIO-PLA-03
A78: PE-00077 | B78: E1020 | C78: Arjun Bhat | D78: 2026-09-14 | E78: 1 | F78: IN | G78: 08:00 | H78: 2026-09-14 | I78: Biometric | J78: BIO-PLA-02
A79: PE-00078 | B79: E1020 | C79: Arjun Bhat | D79: 2026-09-14 | E79: 1 | F79: OUT | G79: 20:10 | H79: 2026-09-14 | I79: Biometric | J79: BIO-PLA-02
A80: PE-00079 | B80: E1020 | C80: Arjun Bhat | D80: 2026-09-15 | E80: 1 | F80: IN | G80: 07:57 | H80: 2026-09-15 | I80: Biometric | J80: BIO-PLA-03
A81: PE-00080 | B81: E1020 | C81: Arjun Bhat | D81: 2026-09-15 | E81: 1 | F81: OUT | G81: 20:06 | H81: 2026-09-15 | I81: Biometric | J81: BIO-PLA-03
A82: PE-00081 | B82: E1022 | C82: Mohan Joseph | D82: 2026-09-01 | E82: 1 | F82: IN | G82: 07:55 | H82: 2026-09-01 | I82: Biometric | J82: BIO-PLA-01
A83: PE-00082 | B83: E1022 | C83: Mohan Joseph | D83: 2026-09-01 | E83: 1 | F83: OUT | G83: 20:06 | H83: 2026-09-01 | I83: Biometric | J83: BIO-PLA-01
A84: PE-00083 | B84: E1022 | C84: Mohan Joseph | D84: 2026-09-02 | E84: 1 | F84: IN | G84: 08:05 | H84: 2026-09-02 | I84: Biometric | J84: BIO-PLA-02
A85: PE-00084 | B85: E1022 | C85: Mohan Joseph | D85: 2026-09-02 | E85: 1 | F85: OUT | G85: 18:30 | H85: 2026-09-02 | I85: Biometric | J85: BIO-PLA-02
A86: PE-00085 | B86: E1022 | C86: Mohan Joseph | D86: 2026-09-03 | E86: 1 | F86: IN | G86: 07:53 | H86: 2026-09-03 | I86: Biometric | J86: BIO-PLA-03
A87: PE-00086 | B87: E1022 | C87: Mohan Joseph | D87: 2026-09-03 | E87: 1 | F87: OUT | G87: 20:03 | H87: 2026-09-03 | I87: Biometric | J87: BIO-PLA-03
... A138: PE-00137 | B138: E1026 | C138: Manjunath Poojary | D138: 2026-09-01 | E138: 1 | F138: IN | G138: 19:55 | H138: 2026-09-01 | I138: Biometric | J138: BIO-PLA-01
A139: PE-00138 | B139: E1026 | C139: Manjunath Poojary | D139: 2026-09-01 | E139: 1 | F139: OUT | G139: 08:06 | H139: 2026-09-02 | I139: Biometric | J139: BIO-PLA-01 | K139: Next calendar day
A140: PE-00139 | B140: E1026 | C140: Manjunath Poojary | D140: 2026-09-02 | E140: 1 | F140: IN | G140: 19:58 | H140: 2026-09-02 | I140: Biometric | J140: BIO-PLA-02
A141: PE-00140 | B141: E1026 | C141: Manjunath Poojary | D141: 2026-09-02 | E141: 1 | F141: OUT | G141: 08:11 | H141: 2026-09-03 | I141: Biometric | J141: BIO-PLA-02 | K141: Next calendar day
A142: PE-00141 | B142: E1026 | C142: Manjunath Poojary | D142: 2026-09-03 | E142: 1 | F142: IN | G142: 19:53 | H142: 2026-09-03 | I142: Biometric | J142: BIO-PLA-03
A143: PE-00142 | B143: E1026 | C143: Manjunath Poojary | D143: 2026-09-03 | E143: 1 | F143: OUT | G143: 08:03 | H143: 2026-09-04 | I143: Biometric | J143: BIO-PLA-03 | K143: Next calendar day
A144: PE-00143 | B144: E1026 | C144: Manjunath Poojary | D144: 2026-09-04 | E144: 1 | F144: IN | G144: 20:00 | H144: 2026-09-04 | I144: Biometric | J144: BIO-PLA-01
A145: PE-00144 | B145: E1026 | C145: Manjunath Poojary | D145: 2026-09-04 | E145: 1 | F145: OUT | G145: 08:14 | H145: 2026-09-05 | I145: Biometric | J145: BIO-PLA-01 | K145: Next calendar day
A146: PE-00145 | B146: E1026 | C146: Manjunath Poojary | D146: 2026-09-05 | E146: 1 | F146: IN | G146: 19:56 | H146: 2026-09-05 | I146: Biometric | J146: BIO-PLA-02
A147: PE-00146 | B147: E1026 | C147: Manjunath Poojary | D147: 2026-09-05 | E147: 1 | F147: OUT | G147: 08:08 | H147: 2026-09-06 | I147: Biometric | J147: BIO-PLA-02 | K147: Next calendar day
A148: PE-00147 | B148: E1026 | C148: Manjunath Poojary | D148: 2026-09-07 | E148: 1 | F148: IN | G148: 19:54 | H148: 2026-09-07 | I148: Biometric | J148: BIO-PLA-01
A149: PE-00148 | B149: E1026 | C149: Manjunath Poojary | D149: 2026-09-07 | E149: 1 | F149: OUT | G149: 08:17 | H149: 2026-09-08 | I149: Biometric | J149: BIO-PLA-01 | K149: Next calendar day
A150: PE-00149 | B150: E1026 | C150: Manjunath Poojary | D150: 2026-09-08 | E150: 1 | F150: IN | G150: 19:59 | H150: 2026-09-08 | I150: Biometric | J150: BIO-PLA-02
A151: PE-00150 | B151: E1026 | C151: Manjunath Poojary | D151: 2026-09-08 | E151: 1 | F151: OUT | G151: 08:05 | H151: 2026-09-09 | I151: Biometric | J151: BIO-PLA-02 | K151: Next calendar day
A152: PE-00151 | B152: E1026 | C152: Manjunath Poojary | D152: 2026-09-09 | E152: 1 | F152: IN | G152: 19:57 | H152: 2026-09-09 | I152: Biometric | J152: BIO-PLA-03
A153: PE-00152 | B153: E1026 | C153: Manjunath Poojary | D153: 2026-09-09 | E153: 1 | F153: OUT | G153: 08:09 | H153: 2026-09-10 | I153: Biometric | J153: BIO-PLA-03 | K153: Next calendar day
A154: PE-00153 | B154: E1026 | C154: Manjunath Poojary | D154: 2026-09-10 | E154: 1 | F154: IN | G154: 20:01 | H154: 2026-09-10 | I154: Biometric | J154: BIO-PLA-01
A155: PE-00154 | B155: E1026 | C155: Manjunath Poojary | D155: 2026-09-10 | E155: 1 | F155: OUT | G155: 08:12 | H155: 2026-09-11 | I155: Biometric | J155: BIO-PLA-01 | K155: Next calendar day
A156: PE-00155 | B156: E1026 | C156: Manjunath Poojary | D156: 2026-09-11 | E156: 1 | F156: IN | G156: 19:52 | H156: 2026-09-11 | I156: Biometric | J156: BIO-PLA-02
A157: PE-00156 | B157: E1026 | C157: Manjunath Poojary | D157: 2026-09-11 | E157: 1 | F157: OUT | G157: 08:04 | H157: 2026-09-12 | I157: Biometric | J157: BIO-PLA-02 | K157: Next calendar day
A158: PE-00157 | B158: E1026 | C158: Manjunath Poojary | D158: 2026-09-12 | E158: 1 | F158: IN | G158: 20:02 | H158: 2026-09-12 | I158: Biometric | J158: BIO-PLA-03
A159: PE-00158 | B159: E1026 | C159: Manjunath Poojary | D159: 2026-09-12 | E159: 1 | F159: OUT | G159: 08:19 | H159: 2026-09-13 | I159: Biometric | J159: BIO-PLA-03 | K159: Next calendar day
A160: PE-00159 | B160: E1026 | C160: Manjunath Poojary | D160: 2026-09-14 | E160: 1 | F160: IN | G160: 20:00 | H160: 2026-09-14 | I160: Biometric | J160: BIO-PLA-02
A161: PE-00160 | B161: E1026 | C161: Manjunath Poojary | D161: 2026-09-14 | E161: 1 | F161: OUT | G161: 08:10 | H161: 2026-09-15 | I161: Biometric | J161: BIO-PLA-02 | K161: Next calendar day
A162: PE-00161 | B162: E1026 | C162: Manjunath Poojary | D162: 2026-09-15 | E162: 1 | F162: IN | G162: 19:57 | H162: 2026-09-15 | I162: Biometric | J162: BIO-PLA-03
A163: PE-00162 | B163: E1026 | C163: Manjunath Poojary | D163: 2026-09-15 | E163: 1 | F163: OUT | G163: 08:06 | H163: 2026-09-16 | I163: Biometric | J163: BIO-PLA-03 | K163: Next calendar day
A164: PE-00163 | B164: E1028 | C164: Yashoda Rani | D164: 2026-09-01 | E164: 1 | F164: IN | G164: 07:55 | H164: 2026-09-01 | I164: Biometric | J164: BIO-PLA-01
A165: PE-00164 | B165: E1028 | C165: Yashoda Rani | D165: 2026-09-01 | E165: 1 | F165: OUT | G165: 20:06 | H165: 2026-09-01 | I165: Biometric | J165: BIO-PLA-01
A166: PE-00165 | B166: E1028 | C166: Yashoda Rani | D166: 2026-09-02 | E166: 1 | F166: IN | G166: 07:58 | H166: 2026-09-02 | I166: Biometric | J166: BIO-PLA-02
A167: PE-00166 | B167: E1028 | C167: Yashoda Rani | D167: 2026-09-02 | E167: 1 | F167: OUT | G167: 20:11 | H167: 2026-09-02 | I167: Biometric | J167: BIO-PLA-02
A168: PE-00167 | B168: E1028 | C168: Yashoda Rani | D168: 2026-09-03 | E168: 1 | F168: IN | G168: 07:53 | H168: 2026-09-03 | I168: Biometric | J168: BIO-PLA-03
A169: PE-00168 | B169: E1028 | C169: Yashoda Rani | D169: 2026-09-03 | E169: 1 | F169: OUT | G169: 20:03 | H169: 2026-09-03 | I169: Biometric | J169: BIO-PLA-03
A170: PE-00169 | B170: E1028 | C170: Yashoda Rani | D170: 2026-09-04 | E170: 1 | F170: IN | G170: 08:00 | H170: 2026-09-04 | I170: Biometric | J170: BIO-PLA-01
A171: PE-00170 | B171: E1028 | C171: Yashoda Rani | D171: 2026-09-04 | E171: 1 | F171: OUT | G171: 20:14 | H171: 2026-09-04 | I171: Biometric | J171: BIO-PLA-01
A172: PE-00171 | B172: E1028 | C172: Yashoda Rani | D172: 2026-09-05 | E172: 1 | F172: IN | G172: 07:56 | H172: 2026-09-05 | I172: Biometric | J172: BIO-PLA-02
A173: PE-00172 | B173: E1028 | C173: Yashoda Rani | D173: 2026-09-05 | E173: 1 | F173: OUT | G173: 20:08 | H173: 2026-09-05 | I173: Biometric | J173: BIO-PLA-02
A174: PE-00173 | B174: E1028 | C174: Yashoda Rani | D174: 2026-09-06 | E174: 1 | F174: IN | G174: 08:04 | H174: 2026-09-06 | I174: Biometric | J174: BIO-PLA-03
A175: PE-00174 | B175: E1028 | C175: Yashoda Rani | D175: 2026-09-06 | E175: 1 | F175: OUT | G175: 20:12 | H175: 2026-09-06 | I175: Biometric | J175: BIO-PLA-03
... A322: PE-00321 | B322: E1045 | C322: Sunita Bhosale | D322: 2026-09-01 | E322: 1 | F322: IN | G322: 16:55 | H322: 2026-09-01 | I322: Biometric | J322: BIO-PUN-01
A323: PE-00322 | B323: E1045 | C323: Sunita Bhosale | D323: 2026-09-01 | E323: 1 | F323: OUT | G323: 03:06 | H323: 2026-09-02 | I323: Biometric | J323: BIO-PUN-01 | K323: Next calendar day
A324: PE-00323 | B324: E1045 | C324: Sunita Bhosale | D324: 2026-09-02 | E324: 1 | F324: IN | G324: 16:58 | H324: 2026-09-02 | I324: Biometric | J324: BIO-PUN-02
A325: PE-00324 | B325: E1045 | C325: Sunita Bhosale | D325: 2026-09-02 | E325: 1 | F325: OUT | G325: 03:11 | H325: 2026-09-03 | I325: Biometric | J325: BIO-PUN-02 | K325: Next calendar day
A326: PE-00325 | B326: E1045 | C326: Sunita Bhosale | D326: 2026-09-03 | E326: 1 | F326: IN | G326: 16:53 | H326: 2026-09-03 | I326: Biometric | J326: BIO-PUN-03
A327: PE-00326 | B327: E1045 | C327: Sunita Bhosale | D327: 2026-09-03 | E327: 1 | F327: OUT | G327: 03:03 | H327: 2026-09-04 | I327: Biometric | J327: BIO-PUN-03 | K327: Next calendar day
A328: PE-00327 | B328: E1045 | C328: Sunita Bhosale | D328: 2026-09-04 | E328: 1 | F328: IN | G328: 17:00 | H328: 2026-09-04 | I328: Biometric | J328: BIO-PUN-01
A329: PE-00328 | B329: E1045 | C329: Sunita Bhosale | D329: 2026-09-04 | E329: 1 | F329: OUT | G329: 03:14 | H329: 2026-09-05 | I329: Biometric | J329: BIO-PUN-01 | K329: Next calendar day
A330: PE-00329 | B330: E1045 | C330: Sunita Bhosale | D330: 2026-09-05 | E330: 1 | F330: IN | G330: 16:56 | H330: 2026-09-05 | I330: Biometric | J330: BIO-PUN-02
...

Sheet 21_Expected_Attendance
A1: Record | B1: Employee code | C1: Name | D1: Date | E1: Day | F1: Shift assigned | G1: Shift applied | H1: Shift hours | I1: Shift minutes | J1: Day type | K1: First in | L1: Last out | M1: Gross minutes | N1: Break minutes (recorded, paid) | O1: Gate pass minutes (deducted) | P1: Gate pass credit (approved) | Q1: OT eligibility | R1: Late by (min) | S1: Late instance no | T1: Late beyond allowance | U1: Long-night relief | V1: Note | X1: Net minutes | Y1: Overtime minutes | Z1: Expected status | AA1: Net (h:mm) | AB1: OT (h:mm)
A2: AD-00001 | B2: E1018 | C2: Ravi Kulkarni | D2: 2026-09-01 | E2: Tue | F2: SH-A | G2: SH-A | H2: 12 | I2: 720 | J2: Working | K2: 07:55 | L2: 20:06 | M2: 731 | N2: 60 | O2: 0 | P2: 0 | Q2: All | T2: N | U2: N | X2: =$M2-$O2+$P2 -> 731 | Y2: =IF($M2=0,0,IF($J2="Working",IF($Q2="All",MAX(0,$M2-$I2),0),IF($Q2="None",0,$M2))) -> 11 | Z2: {=IF($J2<>"Working",IF($M2>0,$J2&" — worked",$J2),IF($U2="Y","Present",IF($X2<INDEX('08_Attendance_Rules'!$C$2:$C$5,MATCH($H2,'08_Attendance_Rules'!$A$2:$A$5,0)),"Absent",IF($X2<INDEX('08_Attendance_Rules'!$B$2:$B$5,MATCH($H2,'08_Attendance_Rules'!$A$2:$A$5,0)),"Half Day",IF($T2="Y","Half Day","Present")))))} -> Present | AA2: =IF($X2=0,"-",INT($X2/60)&":"&TEXT(MOD($X2,60),"00")) -> 12:11 | AB2: =IF($Y2=0,"-",INT($Y2/60)&":"&TEXT(MOD($Y2,60),"00")) -> 0:11
A3: AD-00002 | B3: E1018 | C3: Ravi Kulkarni | D3: 2026-09-02 | E3: Wed | F3: SH-A | G3: SH-A | H3: 12 | I3: 720 | J3: Working | K3: 07:58 | L3: 20:11 | M3: 733 | N3: 60 | O3: 0 | P3: 0 | Q3: All | T3: N | U3: N | X3: =$M3-$O3+$P3 -> 733 | Y3: =IF($M3=0,0,IF($J3="Working",IF($Q3="All",MAX(0,$M3-$I3),0),IF($Q3="None",0,$M3))) -> 13 | Z3: {=IF($J3<>"Working",IF($M3>0,$J3&" — worked",$J3),IF($U3="Y","Present",IF($X3<INDEX('08_Attendance_Rules'!$C$2:$C$5,MATCH($H3,'08_Attendance_Rules'!$A$2:$A$5,0)),"Absent",IF($X3<INDEX('08_Attendance_Rules'!$B$2:$B$5,MATCH($H3,'08_Attendance_Rules'!$A$2:$A$5,0)),"Half Day",IF($T3="Y","Half Day","Present")))))} -> Present | AA3: =IF($X3=0,"-",INT($X3/60)&":"&TEXT(MOD($X3,60),"00")) -> 12:13 | AB3: =IF($Y3=0,"-",INT($Y3/60)&":"&TEXT(MOD($Y3,60),"00")) -> 0:13
A4: AD-00003 | B4: E1018 | C4: Ravi Kulkarni | D4: 2026-09-03 | E4: Thu | F4: SH-A | G4: SH-A | H4: 12 | I4: 720 | J4: Working | K4: 07:53 | L4: 20:03 | M4: 730 | N4: 60 | O4: 0 | P4: 0 | Q4: All | T4: N | U4: N | X4: =$M4-$O4+$P4 -> 730 | Y4: =IF($M4=0,0,IF($J4="Working",IF($Q4="All",MAX(0,$M4-$I4),0),IF($Q4="None",0,$M4))) -> 10 | Z4: {=IF($J4<>"Working",IF($M4>0,$J4&" — worked",$J4),IF($U4="Y","Present",IF($X4<INDEX('08_Attendance_Rules'!$C$2:$C$5,MATCH($H4,'08_Attendance_Rules'!$A$2:$A$5,0)),"Absent",IF($X4<INDEX('08_Attendance_Rules'!$B$2:$B$5,MATCH($H4,'08_Attendance_Rules'!$A$2:$A$5,0)),"Half Day",IF($T4="Y","Half Day","Present")))))} -> Present | AA4: =IF($X4=0,"-",INT($X4/60)&":"&TEXT(MOD($X4,60),"00")) -> 12:10 | AB4: =IF($Y4=0,"-",INT($Y4/60)&":"&TEXT(MOD($Y4,60),"00")) -> 0:10
A5: AD-00004 | B5: E1018 | C5: Ravi Kulkarni | D5: 2026-09-04 | E5: Fri | F5: SH-A | G5: SH-A | H5: 12 | I5: 720 | J5: Working | K5: 08:00 | L5: 20:14 | M5: 734 | N5: 60 | O5: 0 | P5: 0 | Q5: All | T5: N | U5: N | X5: =$M5-$O5+$P5 -> 734 | Y5: =IF($M5=0,0,IF($J5="Working",IF($Q5="All",MAX(0,$M5-$I5),0),IF($Q5="None",0,$M5))) -> 14 | Z5: {=IF($J5<>"Working",IF($M5>0,$J5&" — worked",$J5),IF($U5="Y","Present",IF($X5<INDEX('08_Attendance_Rules'!$C$2:$C$5,MATCH($H5,'08_Attendance_Rules'!$A$2:$A$5,0)),"Absent",IF($X5<INDEX('08_Attendance_Rules'!$B$2:$B$5,MATCH($H5,'08_Attendance_Rules'!$A$2:$A$5,0)),"Half Day",IF($T5="Y","Half Day","Present")))))} -> Present | AA5: =IF($X5=0,"-",INT($X5/60)&":"&TEXT(MOD($X5,60),"00")) -> 12:14 | AB5: =IF($Y5=0,"-",INT($Y5/60)&":"&TEXT(MOD($Y5,60),"00")) -> 0:14
A6: AD-00005 | B6: E1018 | C6: Ravi Kulkarni | D6: 2026-09-05 | E6: Sat | F6: SH-A | G6: SH-A | H6: 12 | I6: 720 | J6: Working | K6: 07:56 | L6: 20:08 | M6: 732 | N6: 60 | O6: 0 | P6: 0 | Q6: All | T6: N | U6: N | X6: =$M6-$O6+$P6 -> 732 | Y6: =IF($M6=0,0,IF($J6="Working",IF($Q6="All",MAX(0,$M6-$I6),0),IF($Q6="None",0,$M6))) -> 12 | Z6: {=IF($J6<>"Working",IF($M6>0,$J6&" — worked",$J6),IF($U6="Y","Present",IF($X6<INDEX('08_Attendance_Rules'!$C$2:$C$5,MATCH($H6,'08_Attendance_Rules'!$A$2:$A$5,0)),"Absent",IF($X6<INDEX('08_Attendance_Rules'!$B$2:$B$5,MATCH($H6,'08_Attendance_Rules'!$A$2:$A$5,0)),"Half Day",IF($T6="Y","Half Day","Present")))))} -> Present | AA6: =IF($X6=0,"-",INT($X6/60)&":"&TEXT(MOD($X6,60),"00")) -> 12:12 | AB6: =IF($Y6=0,"-",INT($Y6/60)&":"&TEXT(MOD($Y6,60),"00")) -> 0:12
A7: AD-00006 | B7: E1018 | C7: Ravi Kulkarni | D7: 2026-09-06 | E7: Sun | F7: SH-A | G7: SH-A | H7: 12 | I7: 720 | J7: Weekly Off | M7: 0 | N7: 0 | O7: 0 | P7: 0 | Q7: All | T7: N | U7: N | X7: =$M7-$O7+$P7 -> 0 | Y7: =IF($M7=0,0,IF($J7="Working",IF($Q7="All",MAX(0,$M7-$I7),0),IF($Q7="None",0,$M7))) -> 0 | Z7: {=IF($J7<>"Working",IF($M7>0,$J7&" — worked",$J7),IF($U7="Y","Present",IF($X7<INDEX('08_Attendance_Rules'!$C$2:$C$5,MATCH($H7,'08_Attendance_Rules'!$A$2:$A$5,0)),"Absent",IF($X7<INDEX('08_Attendance_Rules'!$B$2:$B$5,MATCH($H7,'08_Attendance_Rules'!$A$2:$A$5,0)),"Half Day",IF($T7="Y","Half Day","Present")))))} -> Weekly Off | AA7: =IF($X7=0,"-",INT($X7/60)&":"&TEXT(MOD($X7,60),"00")) -> - | AB7: =IF($Y7=0,"-",INT($Y7/60)&":"&TEXT(MOD($Y7,60),"00")) -> -
A8: AD-00007 | B8: E1018 | C8: Ravi Kulkarni | D8: 2026-09-07 | E8: Mon | F8: SH-A | G8: SH-A | H8: 12 | I8: 720 | J8: Working | K8: 07:54 | L8: 20:17 | M8: 743 | N8: 60 | O8: 0 | P8: 0 | Q8: All | T8: N | U8: N | X8: =$M8-$O8+$P8 -> 743 | Y8: =IF($M8=0,0,IF($J8="Working",IF($Q8="All",MAX(0,$M8-$I8),0),IF($Q8="None",0,$M8))) -> 23 | Z8: {=IF($J8<>"Working",IF($M8>0,$J8&" — worked",$J8),IF($U8="Y","Present",IF($X8<INDEX('08_Attendance_Rules'!$C$2:$C$5,MATCH($H8,'08_Attendance_Rules'!$A$2:$A$5,0)),"Absent",IF($X8<INDEX('08_Attendance_Rules'!$B$2:$B$5,MATCH($H8,'08_Attendance_Rules'!$A$2:$A$5,0)),"Half Day",IF($T8="Y","Half Day","Present")))))} -> Present | AA8: =IF($X8=0,"-",INT($X8/60)&":"&TEXT(MOD($X8,60),"00")) -> 12:23 | AB8: =IF($Y8=0,"-",INT($Y8/60)&":"&TEXT(MOD($Y8,60),"00")) -> 0:23
A9: AD-00008 | B9: E1018 | C9: Ravi Kulkarni | D9: 2026-09-08 | E9: Tue | F9: SH-A | G9: SH-A | H9: 12 | I9: 720 | J9: Working | K9: 08:00 | L9: 03:20 | M9: 1160 | N9: 45 | O9: 0 | P9: 0 | Q9: All | T9: N | U9: N | V9: Point 1 — two segments, 45-min dinner break, day runs to 03:20 | X9: =$M9-$O9+$P9 -> 1160 | Y9: =IF($M9=0,0,IF($J9="Working",IF($Q9="All",MAX(0,$M9-$I9),0),IF($Q9="None",0,$M9))) -> 440 | Z9: {=IF($J9<>"Working",IF($M9>0,$J9&" — worked",$J9),IF($U9="Y","Present",IF($X9<INDEX('08_Attendance_Rules'!$C$2:$C$5,MATCH($H9,'08_Attendance_Rules'!$A$2:$A$5,0)),"Absent",IF($X9<INDEX('08_Attendance_Rules'!$B$2:$B$5,MATCH($H9,'08_Attendance_Rules'!$A$2:$A$5,0)),"Half Day",IF($T9="Y","Half Day","Present")))))} -> Present | AA9: =IF($X9=0,"-",INT($X9/60)&":"&TEXT(MOD($X9,60),"00")) -> 19:20 | AB9: =IF($Y9=0,"-",INT($Y9/60)&":"&TEXT(MOD($Y9,60),"00")) -> 7:20
A10: AD-00009 | B10: E1018 | C10: Ravi Kulkarni | D10: 2026-09-09 | E10: Wed | F10: SH-A | G10: SH-A | H10: 12 | I10: 720 | J10: Working | K10: 09:25 | L10: 20:10 | M10: 645 | N10: 45 | O10: 0 | P10: 0 | Q10: All | R10: 85 | T10: N | U10: Y | V10: Point 12 — long-night relief after a 03:20 finish; full day despite 10h45m span | X10: =$M10-$O10+$P10 -> 645 | Y10: =IF($M10=0,0,IF($J10="Working",IF($Q10="All",MAX(0,$M10-$I10),0),IF($Q10="None",0,$M10))) -> 0 | Z10: {=IF($J10<>"Working",IF($M10>0,$J10&" — worked",$J10),IF($U10="Y","Present",IF($X10<INDEX('08_Attendance_Rules'!$C$2:$C$5,MATCH($H10,'08_Attendance_Rules'!$A$2:$A$5,0)),"Absent",IF($X10<INDEX('08_Attendance_Rules'!$B$2:$B$5,MATCH($H10,'08_Attendance_Rules'!$A$2:$A$5,0)),"Half Day",IF($T10="Y","Half Day","Present")))))} -> Present | AA10: =IF($X10=0,"-",INT($X10/60)&":"&TEXT(MOD($X10,60),"00")) -> 10:45 | AB10: =IF($Y10=0,"-",INT($Y10/60)&":"&TEXT(MOD($Y10,60),"00")) -> -
A11: AD-00010 | B11: E1018 | C11: Ravi Kulkarni | D11: 2026-09-10 | E11: Thu | F11: SH-A | G11: SH-A | H11: 12 | I11: 720 | J11: Working | K11: 08:01 | L11: 20:12 | M11: 731 | N11: 60 | O11: 0 | P11: 0 | Q11: All | R11: 1 | T11: N | U11: N | X11: =$M11-$O11+$P11 -> 731 | Y11: =IF($M11=0,0,IF($J11="Working",IF($Q11="All",MAX(0,$M11-$I11),0),IF($Q11="None",0,$M11))) -> 11 | Z11: {=IF($J11<>"Working",IF($M11>0,$J11&" — worked",$J11),IF($U11="Y","Present",IF($X11<INDEX('08_Attendance_Rules'!$C$2:$C$5,MATCH($H11,'08_Attendance_Rules'!$A$2:$A$5,0)),"Absent",IF($X11<INDEX('08_Attendance_Rules'!$B$2:$B$5,MATCH($H11,'08_Attendance_Rules'!$A$2:$A$5,0)),"Half Day",IF($T11="Y","Half Day","Present")))))} -> Present | AA11: =IF($X11=0,"-",INT($X11/60)&":"&TEXT(MOD($X11,60),"00")) -> 12:11 | AB11: =IF($Y11=0,"-",INT($Y11/60)&":"&TEXT(MOD($Y11,60),"00")) -> 0:11
A12: AD-00011 | B12: E1018 | C12: Ravi Kulkarni | D12: 2026-09-11 | E12: Fri | F12: SH-A | G12: SH-A | H12: 12 | I12: 720 | J12: Working | K12: 07:52 | L12: 20:04 | M12: 732 | N12: 60 | O12: 0 | P12: 0 | Q12: All | T12: N | U12: N | X12: =$M12-$O12+$P12 -> 732 | Y12: =IF($M12=0,0,IF($J12="Working",IF($Q12="All",MAX(0,$M12-$I12),0),IF($Q12="None",0,$M12))) -> 12 | Z12: {=IF($J12<>"Working",IF($M12>0,$J12&" — worked",$J12),IF($U12="Y","Present",IF($X12<INDEX('08_Attendance_Rules'!$C$2:$C$5,MATCH($H12,'08_Attendance_Rules'!$A$2:$A$5,0)),"Absent",IF($X12<INDEX('08_Attendance_Rules'!$B$2:$B$5,MATCH($H12,'08_Attendance_Rules'!$A$2:$A$5,0)),"Half Day",IF($T12="Y","Half Day","Present")))))} -> Present | AA12: =IF($X12=0,"-",INT($X12/60)&":"&TEXT(MOD($X12,60),"00")) -> 12:12 | AB12: =IF($Y12=0,"-",INT($Y12/60)&":"&TEXT(MOD($Y12,60),"00")) -> 0:12
A13: AD-00012 | B13: E1018 | C13: Ravi Kulkarni | D13: 2026-09-12 | E13: Sat | F13: SH-A | G13: SH-A | H13: 12 | I13: 720 | J13: Working | K13: 08:02 | L13: 20:19 | M13: 737 | N13: 60 | O13: 0 | P13: 0 | Q13: All | R13: 2 | T13: N | U13: N | X13: =$M13-$O13+$P13 -> 737 | Y13: =IF($M13=0,0,IF($J13="Working",IF($Q13="All",MAX(0,$M13-$I13),0),IF($Q13="None",0,$M13))) -> 17 | Z13: {=IF($J13<>"Working",IF($M13>0,$J13&" — worked",$J13),IF($U13="Y","Present",IF($X13<INDEX('08_Attendance_Rules'!$C$2:$C$5,MATCH($H13,'08_Attendance_Rules'!$A$2:$A$5,0)),"Absent",IF($X13<INDEX('08_Attendance_Rules'!$B$2:$B$5,MATCH($H13,'08_Attendance_Rules'!$A$2:$A$5,0)),"Half Day",IF($T13="Y","Half Day","Present")))))} -> Present | AA13: =IF($X13=0,"-",INT($X13/60)&":"&TEXT(MOD($X13,60),"00")) -> 12:17 | AB13: =IF($Y13=0,"-",INT($Y13/60)&":"&TEXT(MOD($Y13,60),"00")) -> 0:17
A14: AD-00013 | B14: E1018 | C14: Ravi Kulkarni | D14: 2026-09-13 | E14: Sun | F14: SH-A | G14: SH-A | H14: 12 | I14: 720 | J14: Weekly Off | M14: 0 | N14: 0 | O14: 0 | P14: 0 | Q14: All | T14: N | U14: N | X14: =$M14-$O14+$P14 -> 0 | Y14: =IF($M14=0,0,IF($J14="Working",IF($Q14="All",MAX(0,$M14-$I14),0),IF($Q14="None",0,$M14))) -> 0 | Z14: {=IF($J14<>"Working",IF($M14>0,$J14&" — worked",$J14),IF($U14="Y","Present",IF($X14<INDEX('08_Attendance_Rules'!$C$2:$C$5,MATCH($H14,'08_Attendance_Rules'!$A$2:$A$5,0)),"Absent",IF($X14<INDEX('08_Attendance_Rules'!$B$2:$B$5,MATCH($H14,'08_Attendance_Rules'!$A$2:$A$5,0)),"Half Day",IF($T14="Y","Half Day","Present")))))} -> Weekly Off | AA14: =IF($X14=0,"-",INT($X14/60)&":"&TEXT(MOD($X14,60),"00")) -> - | AB14: =IF($Y14=0,"-",INT($Y14/60)&":"&TEXT(MOD($Y14,60),"00")) -> -
A15: AD-00014 | B15: E1018 | C15: Ravi Kulkarni | D15: 2026-09-14 | E15: Mon | F15: SH-A | G15: SH-A | H15: 12 | I15: 720 | J15: Working | K15: 08:00 | L15: 20:10 | M15: 730 | N15: 60 | O15: 0 | P15: 0 | Q15: All | T15: N | U15: N | X15: =$M15-$O15+$P15 -> 730 | Y15: =IF($M15=0,0,IF($J15="Working",IF($Q15="All",MAX(0,$M15-$I15),0),IF($Q15="None",0,$M15))) -> 10 | Z15: {=IF($J15<>"Working",IF($M15>0,$J15&" — worked",$J15),IF($U15="Y","Present",IF($X15<INDEX('08_Attendance_Rules'!$C$2:$C$5,MATCH($H15,'08_Attendance_Rules'!$A$2:$A$5,0)),"Absent",IF($X15<INDEX('08_Attendance_Rules'!$B$2:$B$5,MATCH($H15,'08_Attendance_Rules'!$A$2:$A$5,0)),"Half Day",IF($T15="Y","Half Day","Present")))))} -> Present | AA15: =IF($X15=0,"-",INT($X15/60)&":"&TEXT(MOD($X15,60),"00")) -> 12:10 | AB15: =IF($Y15=0,"-",INT($Y15/60)&":"&TEXT(MOD($Y15,60),"00")) -> 0:10
A16: AD-00015 | B16: E1018 | C16: Ravi Kulkarni | D16: 2026-09-15 | E16: Tue | F16: SH-A | G16: SH-A | H16: 12 | I16: 720 | J16: Working | K16: 07:57 | L16: 20:06 | M16: 729 | N16: 60 | O16: 0 | P16: 0 | Q16: All | T16: N | U16: N | X16: =$M16-$O16+$P16 -> 729 | Y16: =IF($M16=0,0,IF($J16="Working",IF($Q16="All",MAX(0,$M16-$I16),0),IF($Q16="None",0,$M16))) -> 9 | Z16: {=IF($J16<>"Working",IF($M16>0,$J16&" — worked",$J16),IF($U16="Y","Present",IF($X16<INDEX('08_Attendance_Rules'!$C$2:$C$5,MATCH($H16,'08_Attendance_Rules'!$A$2:$A$5,0)),"Absent",IF($X16<INDEX('08_Attendance_Rules'!$B$2:$B$5,MATCH($H16,'08_Attendance_Rules'!$A$2:$A$5,0)),"Half Day",IF($T16="Y","Half Day","Present")))))} -> Present | AA16: =IF($X16=0,"-",INT($X16/60)&":"&TEXT(MOD($X16,60),"00")) -> 12:09 | AB16: =IF($Y16=0,"-",INT($Y16/60)&":"&TEXT(MOD($Y16,60),"00")) -> 0:09
A17: AD-00016 | B17: E1019 | C17: Sneha Nair | D17: 2026-09-01 | E17: Tue | F17: SH-A | G17: SH-A | H17: 12 | I17: 720 | J17: Working | K17: 08:22 | L17: 20:06 | M17: 704 | N17: 60 | O17: 0 | P17: 0 | Q17: All | R17: 22 | S17: 1 | T17: N | U17: N | V17: Late instance 1 — within allowance | X17: =$M17-$O17+$P17 -> 704 | Y17: =IF($M17=0,0,IF($J17="Working",IF($Q17="All",MAX(0,$M17-$I17),0),IF($Q17="None",0,$M17))) -> 0 | Z17: {=IF($J17<>"Working",IF($M17>0,$J17&" — worked",$J17),IF($U17="Y","Present",IF($X17<INDEX('08_Attendance_Rules'!$C$2:$C$5,MATCH($H17,'08_Attendance_Rules'!$A$2:$A$5,0)),"Absent",IF($X17<INDEX('08_Attendance_Rules'!$B$2:$B$5,MATCH($H17,'08_Attendance_Rules'!$A$2:$A$5,0)),"Half Day",IF($T17="Y","Half Day","Present")))))} -> Present | AA17: =IF($X17=0,"-",INT($X17/60)&":"&TEXT(MOD($X17,60),"00")) -> 11:44 | AB17: =IF($Y17=0,"-",INT($Y17/60)&":"&TEXT(MOD($Y17,60),"00")) -> -
A18: AD-00017 | B18: E1019 | C18: Sneha Nair | D18: 2026-09-02 | E18: Wed | F18: SH-A | G18: SH-A | H18: 12 | I18: 720 | J18: Working | K18: 07:58 | L18: 20:11 | M18: 733 | N18: 60 | O18: 0 | P18: 0 | Q18: All | T18: N | U18: N | X18: =$M18-$O18+$P18 -> 733 | Y18: =IF($M18=0,0,IF($J18="Working",IF($Q18="All",MAX(0,$M18-$I18),0),IF($Q18="None",0,$M18))) -> 13 | Z18: {=IF($J18<>"Working",IF($M18>0,$J18&" — worked",$J18),IF($U18="Y","Present",IF($X18<INDEX('08_Attendance_Rules'!$C$2:$C$5,MATCH($H18,'08_Attendance_Rules'!$A$2:$A$5,0)),"Absent",IF($X18<INDEX('08_Attendance_Rules'!$B$2:$B$5,MATCH($H18,'08_Attendance_Rules'!$A$2:$A$5,0)),"Half Day",IF($T18="Y","Half Day","Present")))))} -> Present | AA18: =IF($X18=0,"-",INT($X18/60)&":"&TEXT(MOD($X18,60),"00")) -> 12:13 | AB18: =IF($Y18=0,"-",INT($Y18/60)&":"&TEXT(MOD($Y18,60),"00")) -> 0:13
A19: AD-00018 | B19: E1019 | C19: Sneha Nair | D19: 2026-09-03 | E19: Thu | F19: SH-A | G19: SH-A | H19: 12 | I19: 720 | J19: Working | K19: 08:31 | L19: 20:11 | M19: 700 | N19: 60 | O19: 0 | P19: 0 | Q19: All | R19: 31 | S19: 2 | T19: N | U19: N | V19: Late instance 2 — within allowance | X19: =$M19-$O19+$P19 -> 700 | Y19: =IF($M19=0,0,IF($J19="Working",IF($Q19="All",MAX(0,$M19-$I19),0),IF($Q19="None",0,$M19))) -> 0 | Z19: {=IF($J19<>"Working",IF($M19>0,$J19&" — worked",$J19),IF($U19="Y","Present",IF($X19<INDEX('08_Attendance_Rules'!$C$2:$C$5,MATCH($H19,'08_Attendance_Rules'!$A$2:$A$5,0)),"Absent",IF($X19<INDEX('08_Attendance_Rules'!$B$2:$B$5,MATCH($H19,'08_Attendance_Rules'!$A$2:$A$5,0)),"Half Day",IF($T19="Y","Half Day","Present")))))} -> Present | AA19: =IF($X19=0,"-",INT($X19/60)&":"&TEXT(MOD($X19,60),"00")) -> 11:40 | AB19: =IF($Y19=0,"-",INT($Y19/60)&":"&TEXT(MOD($Y19,60),"00")) -> -
A20: AD-00019 | B20: E1019 | C20: Sneha Nair | D20: 2026-09-04 | E20: Fri | F20: SH-A | G20: SH-A | H20: 12 | I20: 720 | J20: Working | K20: 08:00 | L20: 20:14 | M20: 734 | N20: 60 | O20: 0 | P20: 0 | Q20: All | T20: N | U20: N | X20: =$M20-$O20+$P20 -> 734 | Y20: =IF($M20=0,0,IF($J20="Working",IF($Q20="All",MAX(0,$M20-$I20),0),IF($Q20="None",0,$M20))) -> 14 | Z20: {=IF($J20<>"Working",IF($M20>0,$J20&" — worked",$J20),IF($U20="Y","Present",IF($X20<INDEX('08_Attendance_Rules'!$C$2:$C$5,MATCH($H20,'08_Attendance_Rules'!$A$2:$A$5,0)),"Absent",IF($X20<INDEX('08_Attendance_Rules'!$B$2:$B$5,MATCH($H20,'08_Attendance_Rules'!$A$2:$A$5,0)),"Half Day",IF($T20="Y","Half Day","Present")))))} -> Present | AA20: =IF($X20=0,"-",INT($X20/60)&":"&TEXT(MOD($X20,60),"00")) -> 12:14 | AB20: =IF($Y20=0,"-",INT($Y20/60)&":"&TEXT(MOD($Y20,60),"00")) -> 0:14
A21: AD-00020 | B21: E1019 | C21: Sneha Nair | D21: 2026-09-05 | E21: Sat | F21: SH-A | G21: SH-A | H21: 12 | I21: 720 | J21: Working | K21: 07:56 | L21: 20:08 | M21: 732 | N21: 60 | O21: 0 | P21: 0 | Q21: All | T21: N | U21: N | X21: =$M21-$O21+$P21 -> 732 | Y21: =IF($M21=0,0,IF($J21="Working",IF($Q21="All",MAX(0,$M21-$I21),0),IF($Q21="None",0,$M21))) -> 12 | Z21: {=IF($J21<>"Working",IF($M21>0,$J21&" — worked",$J21),IF($U21="Y","Present",IF($X21<INDEX('08_Attendance_Rules'!$C$2:$C$5,MATCH($H21,'08_Attendance_Rules'!$A$2:$A$5,0)),"Absent",IF($X21<INDEX('08_Attendance_Rules'!$B$2:$B$5,MATCH($H21,'08_Attendance_Rules'!$A$2:$A$5,0)),"Half Day",IF($T21="Y","Half Day","Present")))))} -> Present | AA21: =IF($X21=0,"-",INT($X21/60)&":"&TEXT(MOD($X21,60),"00")) -> 12:12 | AB21: =IF($Y21=0,"-",INT($Y21/60)&":"&TEXT(MOD($Y21,60),"00")) -> 0:12
A22: AD-00021 | B22: E1019 | C22: Sneha Nair | D22: 2026-09-06 | E22: Sun | F22: SH-A | G22: SH-A | H22: 12 | I22: 720 | J22: Weekly Off | M22: 0 | N22: 0 | O22: 0 | P22: 0 | Q22: All | T22: N | U22: N | X22: =$M22-$O22+$P22 -> 0 | Y22: =IF($M22=0,0,IF($J22="Working",IF($Q22="All",MAX(0,$M22-$I22),0),IF($Q22="None",0,$M22))) -> 0 | Z22: {=IF($J22<>"Working",IF($M22>0,$J22&" — worked",$J22),IF($U22="Y","Present",IF($X22<INDEX('08_Attendance_Rules'!$C$2:$C$5,MATCH($H22,'08_Attendance_Rules'!$A$2:$A$5,0)),"Absent",IF($X22<INDEX('08_Attendance_Rules'!$B$2:$B$5,MATCH($H22,'08_Attendance_Rules'!$A$2:$A$5,0)),"Half Day",IF($T22="Y","Half Day","Present")))))} -> Weekly Off | AA22: =IF($X22=0,"-",INT($X22/60)&":"&TEXT(MOD($X22,60),"00")) -> - | AB22: =IF($Y22=0,"-",INT($Y22/60)&":"&TEXT(MOD($Y22,60),"00")) -> -
A23: AD-00022 | B23: E1019 | C23: Sneha Nair | D23: 2026-09-07 | E23: Mon | F23: SH-A | G23: SH-A | H23: 12 | I23: 720 | J23: Working | K23: 08:19 | L23: 20:03 | M23: 704 | N23: 60 | O23: 0 | P23: 0 | Q23: All | R23: 19 | S23: 3 | T23: N | U23: N | V23: Late instance 3 — within allowance | X23: =$M23-$O23+$P23 -> 704 | Y23: =IF($M23=0,0,IF($J23="Working",IF($Q23="All",MAX(0,$M23-$I23),0),IF($Q23="None",0,$M23))) -> 0 | Z23: {=IF($J23<>"Working",IF($M23>0,$J23&" — worked",$J23),IF($U23="Y","Present",IF($X23<INDEX('08_Attendance_Rules'!$C$2:$C$5,MATCH($H23,'08_Attendance_Rules'!$A$2:$A$5,0)),"Absent",IF($X23<INDEX('08_Attendance_Rules'!$B$2:$B$5,MATCH($H23,'08_Attendance_Rules'!$A$2:$A$5,0)),"Half Day",IF($T23="Y","Half Day","Present")))))} -> Present | AA23: =IF($X23=0,"-",INT($X23/60)&":"&TEXT(MOD($X23,60),"00")) -> 11:44 | AB23: =IF($Y23=0,"-",INT($Y23/60)&":"&TEXT(MOD($Y23,60),"00")) -> -
A24: AD-00023 | B24: E1019 | C24: Sneha Nair | D24: 2026-09-08 | E24: Tue | F24: SH-A | G24: SH-A | H24: 12 | I24: 720 | J24: Working | K24: 07:59 | L24: 20:05 | M24: 726 | N24: 60 | O24: 0 | P24: 0 | Q24: All | T24: N | U24: N | X24: =$M24-$O24+$P24 -> 726 | Y24: =IF($M24=0,0,IF($J24="Working",IF($Q24="All",MAX(0,$M24-$I24),0),IF($Q24="None",0,$M24))) -> 6 | Z24: {=IF($J24<>"Working",IF($M24>0,$J24&" — worked",$J24),IF($U24="Y","Present",IF($X24<INDEX('08_Attendance_Rules'!$C$2:$C$5,MATCH($H24,'08_Attendance_Rules'!$A$2:$A$5,0)),"Absent",IF($X24<INDEX('08_Attendance_Rules'!$B$2:$B$5,MATCH($H24,'08_Attendance_Rules'!$A$2:$A$5,0)),"Half Day",IF($T24="Y","Half Day","Present")))))} -> Present | AA24: =IF($X24=0,"-",INT($X24/60)&":"&TEXT(MOD($X24,60),"00")) -> 12:06 | AB24: =IF($Y24=0,"-",INT($Y24/60)&":"&TEXT(MOD($Y24,60),"00")) -> 0:06
A25: AD-00024 | B25: E1019 | C25: Sneha Nair | D25: 2026-09-09 | E25: Wed | F25: SH-A | G25: SH-A | H25: 12 | I25: 720 | J25: Working | K25: 07:57 | L25: 20:09 | M25: 732 | N25: 60 | O25: 0 | P25: 0 | Q25: All | T25: N | U25: N | X25: =$M25-$O25+$P25 -> 732 | Y25: =IF($M25=0,0,IF($J25="Working",IF($Q25="All",MAX(0,$M25-$I25),0),IF($Q25="None",0,$M25))) -> 12 | Z25: {=IF($J25<>"Working",IF($M25>0,$J25&" — worked",$J25),IF($U25="Y","Present",IF($X25<INDEX('08_Attendance_Rules'!$C$2:$C$5,MATCH($H25,'08_Attendance_Rules'!$A$2:$A$5,0)),"Absent",IF($X25<INDEX('08_Attendance_Rules'!$B$2:$B$5,MATCH($H25,'08_Attendance_Rules'!$A$2:$A$5,0)),"Half Day",IF($T25="Y","Half Day","Present")))))} -> Present | AA25: =IF($X25=0,"-",INT($X25/60)&":"&TEXT(MOD($X25,60),"00")) -> 12:12 | AB25: =IF($Y25=0,"-",INT($Y25/60)&":"&TEXT(MOD($Y25,60),"00")) -> 0:12
A26: AD-00025 | B26: E1019 | C26: Sneha Nair | D26: 2026-09-10 | E26: Thu | F26: SH-A | G26: SH-A | H26: 12 | I26: 720 | J26: Working | K26: 08:27 | L26: 20:09 | M26: 702 | N26: 60 | O26: 0 | P26: 0 | Q26: All | R26: 27 | S26: 4 | T26: Y | U26: N | V26: Point 12 — late instance 4, half day | X26: =$M26-$O26+$P26 -> 702 | Y26: =IF($M26=0,0,IF($J26="Working",IF($Q26="All",MAX(0,$M26-$I26),0),IF($Q26="None",0,$M26))) -> 0 | Z26: {=IF($J26<>"Working",IF($M26>0,$J26&" — worked",$J26),IF($U26="Y","Present",IF($X26<INDEX('08_Attendance_Rules'!$C$2:$C$5,MATCH($H26,'08_Attendance_Rules'!$A$2:$A$5,0)),"Absent",IF($X26<INDEX('08_Attendance_Rules'!$B$2:$B$5,MATCH($H26,'08_Attendance_Rules'!$A$2:$A$5,0)),"Half Day",IF($T26="Y","Half Day","Present")))))} -> Half Day | AA26: =IF($X26=0,"-",INT($X26/60)&":"&TEXT(MOD($X26,60),"00")) -> 11:42 | AB26: =IF($Y26=0,"-",INT($Y26/60)&":"&TEXT(MOD($Y26,60),"00")) -> -
A27: AD-00026 | B27: E1019 | C27: Sneha Nair | D27: 2026-09-11 | E27: Fri | F27: SH-A | G27: SH-A | H27: 12 | I27: 720 | J27: Working | K27: 07:52 | L27: 20:04 | M27: 732 | N27: 60 | O27: 0 | P27: 0 | Q27: All | T27: N | U27: N | X27: =$M27-$O27+$P27 -> 732 | Y27: =IF($M27=0,0,IF($J27="Working",IF($Q27="All",MAX(0,$M27-$I27),0),IF($Q27="None",0,$M27))) -> 12 | Z27: {=IF($J27<>"Working",IF($M27>0,$J27&" — worked",$J27),IF($U27="Y","Present",IF($X27<INDEX('08_Attendance_Rules'!$C$2:$C$5,MATCH($H27,'08_Attendance_Rules'!$A$2:$A$5,0)),"Absent",IF($X27<INDEX('08_Attendance_Rules'!$B$2:$B$5,MATCH($H27,'08_Attendance_Rules'!$A$2:$A$5,0)),"Half Day",IF($T27="Y","Half Day","Present")))))} -> Present | AA27: =IF($X27=0,"-",INT($X27/60)&":"&TEXT(MOD($X27,60),"00")) -> 12:12 | AB27: =IF($Y27=0,"-",INT($Y27/60)&":"&TEXT(MOD($Y27,60),"00")) -> 0:12
A28: AD-00027 | B28: E1019 | C28: Sneha Nair | D28: 2026-09-12 | E28: Sat | F28: SH-A | G28: SH-A | H28: 12 | I28: 720 | J28: Working | K28: 08:02 | L28: 20:19 | M28: 737 | N28: 60 | O28: 0 | P28: 0 | Q28: All | R28: 2 | T28: N | U28: N | X28: =$M28-$O28+$P28 -> 737 | Y28: =IF($M28=0,0,IF($J28="Working",IF($Q28="All",MAX(0,$M28-$I28),0),IF($Q28="None",0,$M28))) -> 17 | Z28: {=IF($J28<>"Working",IF($M28>0,$J28&" — worked",$J28),IF($U28="Y","Present",IF($X28<INDEX('08_Attendance_Rules'!$C$2:$C$5,MATCH($H28,'08_Attendance_Rules'!$A$2:$A$5,0)),"Absent",IF($X28<INDEX('08_Attendance_Rules'!$B$2:$B$5,MATCH($H28,'08_Attendance_Rules'!$A$2:$A$5,0)),"Half Day",IF($T28="Y","Half Day","Present")))))} -> Present | AA28: =IF($X28=0,"-",INT($X28/60)&":"&TEXT(MOD($X28,60),"00")) -> 12:17 | AB28: =IF($Y28=0,"-",INT($Y28/60)&":"&TEXT(MOD($Y28,60),"00")) -> 0:17
A29: AD-00028 | B29: E1019 | C29: Sneha Nair | D29: 2026-09-13 | E29: Sun | F29: SH-A | G29: SH-A | H29: 12 | I29: 720 | J29: Weekly Off | M29: 0 | N29: 0 | O29: 0 | P29: 0 | Q29: All | T29: N | U29: N | X29: =$M29-$O29+$P29 -> 0 | Y29: =IF($M29=0,0,IF($J29="Working",IF($Q29="All",MAX(0,$M29-$I29),0),IF($Q29="None",0,$M29))) -> 0 | Z29: {=IF($J29<>"Working",IF($M29>0,$J29&" — worked",$J29),IF($U29="Y","Present",IF($X29<INDEX('08_Attendance_Rules'!$C$2:$C$5,MATCH($H29,'08_Attendance_Rules'!$A$2:$A$5,0)),"Absent",IF($X29<INDEX('08_Attendance_Rules'!$B$2:$B$5,MATCH($H29,'08_Attendance_Rules'!$A$2:$A$5,0)),"Half Day",IF($T29="Y","Half Day","Present")))))} -> Weekly Off | AA29: =IF($X29=0,"-",INT($X29/60)&":"&TEXT(MOD($X29,60),"00")) -> - | AB29: =IF($Y29=0,"-",INT($Y29/60)&":"&TEXT(MOD($Y29,60),"00")) -> -
A30: AD-00029 | B30: E1019 | C30: Sneha Nair | D30: 2026-09-14 | E30: Mon | F30: SH-A | G30: SH-A | H30: 12 | I30: 720 | J30: Working | K30: 08:24 | L30: 20:14 | M30: 710 | N30: 60 | O30: 0 | P30: 0 | Q30: All | R30: 24 | S30: 5 | T30: Y | U30: N | V30: Point 12 — late instance 5, half day | X30: =$M30-$O30+$P30 -> 710 | Y30: =IF($M30=0,0,IF($J30="Working",IF($Q30="All",MAX(0,$M30-$I30),0),IF($Q30="None",0,$M30))) -> 0 | Z30: {=IF($J30<>"Working",IF($M30>0,$J30&" — worked",$J30),IF($U30="Y","Present",IF($X30<INDEX('08_Attendance_Rules'!$C$2:$C$5,MATCH($H30,'08_Attendance_Rules'!$A$2:$A$5,0)),"Absent",IF($X30<INDEX('08_Attendance_Rules'!$B$2:$B$5,MATCH($H30,'08_Attendance_Rules'!$A$2:$A$5,0)),"Half Day",IF($T30="Y","Half Day","Present")))))} -> Half Day | AA30: =IF($X30=0,"-",INT($X30/60)&":"&TEXT(MOD($X30,60),"00")) -> 11:50 | AB30: =IF($Y30=0,"-",INT($Y30/60)&":"&TEXT(MOD($Y30,60),"00")) -> -
A31: AD-00030 | B31: E1019 | C31: Sneha Nair | D31: 2026-09-15 | E31: Tue | F31: SH-A | G31: SH-A | H31: 12 | I31: 720 | J31: Working | K31: 07:57 | L31: 20:06 | M31: 729 | N31: 60 | O31: 0 | P31: 0 | Q31: All | T31: N | U31: N | X31: =$M31-$O31+$P31 -> 729 | Y31: =IF($M31=0,0,IF($J31="Working",IF($Q31="All",MAX(0,$M31-$I31),0),IF($Q31="None",0,$M31))) -> 9 | Z31: {=IF($J31<>"Working",IF($M31>0,$J31&" — worked",$J31),IF($U31="Y","Present",IF($X31<INDEX('08_Attendance_Rules'!$C$2:$C$5,MATCH($H31,'08_Attendance_Rules'!$A$2:$A$5,0)),"Absent",IF($X31<INDEX('08_Attendance_Rules'!$B$2:$B$5,MATCH($H31,'08_Attendance_Rules'!$A$2:$A$5,0)),"Half Day",IF($T31="Y","Half Day","Present")))))} -> Present | AA31: =IF($X31=0,"-",INT($X31/60)&":"&TEXT(MOD($X31,60),"00")) -> 12:09 | AB31: =IF($Y31=0,"-",INT($Y31/60)&":"&TEXT(MOD($Y31,60),"00")) -> 0:09
A32: AD-00031 | B32: E1020 | C32: Arjun Bhat | D32: 2026-09-01 | E32: Tue | F32: SH-A | G32: SH-A | H32: 12 | I32: 720 | J32: Working | K32: 07:55 | L32: 20:06 | M32: 731 | N32: 60 | O32: 0 | P32: 0 | Q32: All | T32: N | U32: N | X32: =$M32-$O32+$P32 -> 731 | Y32: =IF($M32=0,0,IF($J32="Working",IF($Q32="All",MAX(0,$M32-$I32),0),IF($Q32="None",0,$M32))) -> 11 | Z32: {=IF($J32<>"Working",IF($M32>0,$J32&" — worked",$J32),IF($U32="Y","Present",IF($X32<INDEX('08_Attendance_Rules'!$C$2:$C$5,MATCH($H32,'08_Attendance_Rules'!$A$2:$A$5,0)),"Absent",IF($X32<INDEX('08_Attendance_Rules'!$B$2:$B$5,MATCH($H32,'08_Attendance_Rules'!$A$2:$A$5,0)),"Half Day",IF($T32="Y","Half Day","Present")))))} -> Present | AA32: =IF($X32=0,"-",INT($X32/60)&":"&TEXT(MOD($X32,60),"00")) -> 12:11 | AB32: =IF($Y32=0,"-",INT($Y32/60)&":"&TEXT(MOD($Y32,60),"00")) -> 0:11
A33: AD-00032 | B33: E1020 | C33: Arjun Bhat | D33: 2026-09-02 | E33: Wed | F33: SH-A | G33: SH-A | H33: 12 | I33: 720 | J33: Working | K33: 07:58 | L33: 20:11 | M33: 733 | N33: 60 | O33: 0 | P33: 0 | Q33: All | T33: N | U33: N | X33: =$M33-$O33+$P33 -> 733 | Y33: =IF($M33=0,0,IF($J33="Working",IF($Q33="All",MAX(0,$M33-$I33),0),IF($Q33="None",0,$M33))) -> 13 | Z33: {=IF($J33<>"Working",IF($M33>0,$J33&" — worked",$J33),IF($U33="Y","Present",IF($X33<INDEX('08_Attendance_Rules'!$C$2:$C$5,MATCH($H33,'08_Attendance_Rules'!$A$2:$A$5,0)),"Absent",IF($X33<INDEX('08_Attendance_Rules'!$B$2:$B$5,MATCH($H33,'08_Attendance_Rules'!$A$2:$A$5,0)),"Half Day",IF($T33="Y","Half Day","Present")))))} -> Present | AA33: =IF($X33=0,"-",INT($X33/60)&":"&TEXT(MOD($X33,60),"00")) -> 12:13 | AB33: =IF($Y33=0,"-",INT($Y33/60)&":"&TEXT(MOD($Y33,60),"00")) -> 0:13
A34: AD-00033 | B34: E1020 | C34: Arjun Bhat | D34: 2026-09-03 | E34: Thu | F34: SH-A | G34: SH-A | H34: 12 | I34: 720 | J34: Working | K34: 07:53 | L34: 20:03 | M34: 730 | N34: 60 | O34: 0 | P34: 0 | Q34: All | T34: N | U34: N | X34: =$M34-$O34+$P34 -> 730 | Y34: =IF($M34=0,0,IF($J34="Working",IF($Q34="All",MAX(0,$M34-$I34),0),IF($Q34="None",0,$M34))) -> 10 | Z34: {=IF($J34<>"Working",IF($M34>0,$J34&" — worked",$J34),IF($U34="Y","Present",IF($X34<INDEX('08_Attendance_Rules'!$C$2:$C$5,MATCH($H34,'08_Attendance_Rules'!$A$2:$A$5,0)),"Absent",IF($X34<INDEX('08_Attendance_Rules'!$B$2:$B$5,MATCH($H34,'08_Attendance_Rules'!$A$2:$A$5,0)),"Half Day",IF($T34="Y","Half Day","Present")))))} -> Present | AA34: =IF($X34=0,"-",INT($X34/60)&":"&TEXT(MOD($X34,60),"00")) -> 12:10 | AB34: =IF($Y34=0,"-",INT($Y34/60)&":"&TEXT(MOD($Y34,60),"00")) -> 0:10
A35: AD-00034 | B35: E1020 | C35: Arjun Bhat | D35: 2026-09-04 | E35: Fri | F35: SH-A | G35: SH-B | H35: 12 | I35: 720 | J35: Working | K35: 20:05 | L35: 08:40 | M35: 755 | N35: 60 | O35: 0 | P35: 0 | Q35: All | R35: 5 | T35: N | U35: N | V35: Point 13 — in-punch inside B-shift window, shift auto-inferred | X35: =$M35-$O35+$P35 -> 755 | Y35: =IF($M35=0,0,IF($J35="Working",IF($Q35="All",MAX(0,$M35-$I35),0),IF($Q35="None",0,$M35))) -> 35 | Z35: {=IF($J35<>"Working",IF($M35>0,$J35&" — worked",$J35),IF($U35="Y","Present",IF($X35<INDEX('08_Attendance_Rules'!$C$2:$C$5,MATCH($H35,'08_Attendance_Rules'!$A$2:$A$5,0)),"Absent",IF($X35<INDEX('08_Attendance_Rules'!$B$2:$B$5,MATCH($H35,'08_Attendance_Rules'!$A$2:$A$5,0)),"Half Day",IF($T35="Y","Half Day","Present")))))} -> Present | AA35: =IF($X35=0,"-",INT($X35/60)&":"&TEXT(MOD($X35,60),"00")) -> 12:35 | AB35: =IF($Y35=0,"-",INT($Y35/60)&":"&TEXT(MOD($Y35,60),"00")) -> 0:35
A36: AD-00035 | B36: E1020 | C36: Arjun Bhat | D36: 2026-09-05 | E36: Sat | F36: SH-A | G36: SH-A | H36: 12 | I36: 720 | J36: Working | K36: 07:56 | L36: 20:08 | M36: 732 | N36: 60 | O36: 0 | P36: 0 | Q36: All | T36: N | U36: N | X36: =$M36-$O36+$P36 -> 732 | Y36: =IF($M36=0,0,IF($J36="Working",IF($Q36="All",MAX(0,$M36-$I36),0),IF($Q36="None",0,$M36))) -> 12 | Z36: {=IF($J36<>"Working",IF($M36>0,$J36&" — worked",$J36),IF($U36="Y","Present",IF($X36<INDEX('08_Attendance_Rules'!$C$2:$C$5,MATCH($H36,'08_Attendance_Rules'!$A$2:$A$5,0)),"Absent",IF($X36<INDEX('08_Attendance_Rules'!$B$2:$B$5,MATCH($H36,'08_Attendance_Rules'!$A$2:$A$5,0)),"Half Day",IF($T36="Y","Half Day","Present")))))} -> Present | AA36: =IF($X36=0,"-",INT($X36/60)&":"&TEXT(MOD($X36,60),"00")) -> 12:12 | AB36: =IF($Y36=0,"-",INT($Y36/60)&":"&TEXT(MOD($Y36,60),"00")) -> 0:12
A37: AD-00036 | B37: E1020 | C37: Arjun Bhat | D37: 2026-09-06 | E37: Sun | F37: SH-A | G37: SH-A | H37: 12 | I37: 720 | J37: Weekly Off | M37: 0 | N37: 0 | O37: 0 | P37: 0 | Q37: All | T37: N | U37: N | X37: =$M37-$O37+$P37 -> 0 | Y37: =IF($M37=0,0,IF($J37="Working",IF($Q37="All",MAX(0,$M37-$I37),0),IF($Q37="None",0,$M37))) -> 0 | Z37: {=IF($J37<>"Working",IF($M37>0,$J37&" — worked",$J37),IF($U37="Y","Present",IF($X37<INDEX('08_Attendance_Rules'!$C$2:$C$5,MATCH($H37,'08_Attendance_Rules'!$A$2:$A$5,0)),"Absent",IF($X37<INDEX('08_Attendance_Rules'!$B$2:$B$5,MATCH($H37,'08_Attendance_Rules'!$A$2:$A$5,0)),"Half Day",IF($T37="Y","Half Day","Present")))))} -> Weekly Off | AA37: =IF($X37=0,"-",INT($X37/60)&":"&TEXT(MOD($X37,60),"00")) -> - | AB37: =IF($Y37=0,"-",INT($Y37/60)&":"&TEXT(MOD($Y37,60),"00")) -> -
A38: AD-00037 | B38: E1020 | C38: Arjun Bhat | D38: 2026-09-07 | E38: Mon | F38: SH-A | G38: SH-A | H38: 12 | I38: 720 | J38: Working | K38: 07:54 | L38: 20:17 | M38: 743 | N38: 60 | O38: 0 | P38: 0 | Q38: All | T38: N | U38: N | X38: =$M38-$O38+$P38 -> 743 | Y38: =IF($M38=0,0,IF($J38="Working",IF($Q38="All",MAX(0,$M38-$I38),0),IF($Q38="None",0,$M38))) -> 23 | Z38: {=IF($J38<>"Working",IF($M38>0,$J38&" — worked",$J38),IF($U38="Y","Present",IF($X38<INDEX('08_Attendance_Rules'!$C$2:$C$5,MATCH($H38,'08_Attendance_Rules'!$A$2:$A$5,0)),"Absent",IF($X38<INDEX('08_Attendance_Rules'!$B$2:$B$5,MATCH($H38,'08_Attendance_Rules'!$A$2:$A$5,0)),"Half Day",IF($T38="Y","Half Day","Present")))))} -> Present | AA38: =IF($X38=0,"-",INT($X38/60)&":"&TEXT(MOD($X38,60),"00")) -> 12:23 | AB38: =IF($Y38=0,"-",INT($Y38/60)&":"&TEXT(MOD($Y38,60),"00")) -> 0:23
A39: AD-00038 | B39: E1020 | C39: Arjun Bhat | D39: 2026-09-08 | E39: Tue | F39: SH-A | G39: SH-A | H39: 12 | I39: 720 | J39: Working | K39: 07:59 | L39: 20:05 | M39: 726 | N39: 60 | O39: 0 | P39: 0 | Q39: All | T39: N | U39: N | X39: =$M39-$O39+$P39 -> 726 | Y39: =IF($M39=0,0,IF($J39="Working",IF($Q39="All",MAX(0,$M39-$I39),0),IF($Q39="None",0,$M39))) -> 6 | Z39: {=IF($J39<>"Working",IF($M39>0,$J39&" — worked",$J39),IF($U39="Y","Present",IF($X39<INDEX('08_Attendance_Rules'!$C$2:$C$5,MATCH($H39,'08_Attendance_Rules'!$A$2:$A$5,0)),"Absent",IF($X39<INDEX('08_Attendance_Rules'!$B$2:$B$5,MATCH($H39,'08_Attendance_Rules'!$A$2:$A$5,0)),"Half Day",IF($T39="Y","Half Day","Present")))))} -> Present | AA39: =IF($X39=0,"-",INT($X39/60)&":"&TEXT(MOD($X39,60),"00")) -> 12:06 | AB39: =IF($Y39=0,"-",INT($Y39/60)&":"&TEXT(MOD($Y39,60),"00")) -> 0:06
A40: AD-00039 | B40: E1020 | C40: Arjun Bhat | D40: 2026-09-09 | E40: Wed | F40: SH-A | G40: SH-A | H40: 12 | I40: 720 | J40: Working | K40: 07:57 | L40: 20:09 | M40: 732 | N40: 60 | O40: 0 | P40: 0 | Q40: All | T40: N | U40: N | X40: =$M40-$O40+$P40 -> 732 | Y40: =IF($M40=0,0,IF($J40="Working",IF($Q40="All",MAX(0,$M40-$I40),0),IF($Q40="None",0,$M40))) -> 12 | Z40: {=IF($J40<>"Working",IF($M40>0,$J40&" — worked",$J40),IF($U40="Y","Present",IF($X40<INDEX('08_Attendance_Rules'!$C$2:$C$5,MATCH($H40,'08_Attendance_Rules'!$A$2:$A$5,0)),"Absent",IF($X40<INDEX('08_Attendance_Rules'!$B$2:$B$5,MATCH($H40,'08_Attendance_Rules'!$A$2:$A$5,0)),"Half Day",IF($T40="Y","Half Day","Present")))))} -> Present | AA40: =IF($X40=0,"-",INT($X40/60)&":"&TEXT(MOD($X40,60),"00")) -> 12:12 | AB40: =IF($Y40=0,"-",INT($Y40/60)&":"&TEXT(MOD($Y40,60),"00")) -> 0:12
A41: AD-00040 | B41: E1020 | C41: Arjun Bhat | D41: 2026-09-10 | E41: Thu | F41: SH-A | G41: SH-A | H41: 12 | I41: 720 | J41: Working | K41: 08:01 | L41: 20:12 | M41: 731 | N41: 60 | O41: 0 | P41: 0 | Q41: All | R41: 1 | T41: N | U41: N | X41: =$M41-$O41+$P41 -> 731 | Y41: =IF($M41=0,0,IF($J41="Working",IF($Q41="All",MAX(0,$M41-$I41),0),IF($Q41="None",0,$M41))) -> 11 | Z41: {=IF($J41<>"Working",IF($M41>0,$J41&" — worked",$J41),IF($U41="Y","Present",IF($X41<INDEX('08_Attendance_Rules'!$C$2:$C$5,MATCH($H41,'08_Attendance_Rules'!$A$2:$A$5,0)),"Absent",IF($X41<INDEX('08_Attendance_Rules'!$B$2:$B$5,MATCH($H41,'08_Attendance_Rules'!$A$2:$A$5,0)),"Half Day",IF($T41="Y","Half Day","Present")))))} -> Present | AA41: =IF($X41=0,"-",INT($X41/60)&":"&TEXT(MOD($X41,60),"00")) -> 12:11 | AB41: =IF($Y41=0,"-",INT($Y41/60)&":"&TEXT(MOD($Y41,60),"00")) -> 0:11
A42: AD-00041 | B42: E1020 | C42: Arjun Bhat | D42: 2026-09-11 | E42: Fri | F42: SH-A | G42: SH-B | H42: 12 | I42: 720 | J42: Working | K42: 19:58 | L42: 08:36 | M42: 758 | N42: 60 | O42: 0 | P42: 0 | Q42: All | T42: N | U42: N | V42: Point 13 — second inferred B-shift day | X42: =$M42-$O42+$P42 -> 758 | Y42: =IF($M42=0,0,IF($J42="Working",IF($Q42="All",MAX(0,$M42-$I42),0),IF($Q42="None",0,$M42))) -> 38 | Z42: {=IF($J42<>"Working",IF($M42>0,$J42&" — worked",$J42),IF($U42="Y","Present",IF($X42<INDEX('08_Attendance_Rules'!$C$2:$C$5,MATCH($H42,'08_Attendance_Rules'!$A$2:$A$5,0)),"Absent",IF($X42<INDEX('08_Attendance_Rules'!$B$2:$B$5,MATCH($H42,'08_Attendance_Rules'!$A$2:$A$5,0)),"Half Day",IF($T42="Y","Half Day","Present")))))} -> Present | AA42: =IF($X42=0,"-",INT($X42/60)&":"&TEXT(MOD($X42,60),"00")) -> 12:38 | AB42: =IF($Y42=0,"-",INT($Y42/60)&":"&TEXT(MOD($Y42,60),"00")) -> 0:38
A43: AD-00042 | B43: E1020 | C43: Arjun Bhat | D43: 2026-09-12 | E43: Sat | F43: SH-A | G43: SH-A | H43: 12 | I43: 720 | J43: Working | K43: 08:02 | L43: 20:19 | M43: 737 | N43: 60 | O43: 0 | P43: 0 | Q43: All | R43: 2 | T43: N | U43: N | X43: =$M43-$O43+$P43 -> 737 | Y43: =IF($M43=0,0,IF($J43="Working",IF($Q43="All",MAX(0,$M43-$I43),0),IF($Q43="None",0,$M43))) -> 17 | Z43: {=IF($J43<>"Working",IF($M43>0,$J43&" — worked",$J43),IF($U43="Y","Present",IF($X43<INDEX('08_Attendance_Rules'!$C$2:$C$5,MATCH($H43,'08_Attendance_Rules'!$A$2:$A$5,0)),"Absent",IF($X43<INDEX('08_Attendance_Rules'!$B$2:$B$5,MATCH($H43,'08_Attendance_Rules'!$A$2:$A$5,0)),"Half Day",IF($T43="Y","Half Day","Present")))))} -> Present | AA43: =IF($X43=0,"-",INT($X43/60)&":"&TEXT(MOD($X43,60),"00")) -> 12:17 | AB43: =IF($Y43=0,"-",INT($Y43/60)&":"&TEXT(MOD($Y43,60),"00")) -> 0:17
A44: AD-00043 | B44: E1020 | C44: Arjun Bhat | D44: 2026-09-13 | E44: Sun | F44: SH-A | G44: SH-A | H44: 12 | I44: 720 | J44: Weekly Off | M44: 0 | N44: 0 | O44: 0 | P44: 0 | Q44: All | T44: N | U44: N | X44: =$M44-$O44+$P44 -> 0 | Y44: =IF($M44=0,0,IF($J44="Working",IF($Q44="All",MAX(0,$M44-$I44),0),IF($Q44="None",0,$M44))) -> 0 | Z44: {=IF($J44<>"Working",IF($M44>0,$J44&" — worked",$J44),IF($U44="Y","Present",IF($X44<INDEX('08_Attendance_Rules'!$C$2:$C$5,MATCH($H44,'08_Attendance_Rules'!$A$2:$A$5,0)),"Absent",IF($X44<INDEX('08_Attendance_Rules'!$B$2:$B$5,MATCH($H44,'08_Attendance_Rules'!$A$2:$A$5,0)),"Half Day",IF($T44="Y","Half Day","Present")))))} -> Weekly Off | AA44: =IF($X44=0,"-",INT($X44/60)&":"&TEXT(MOD($X44,60),"00")) -> - | AB44: =IF($Y44=0,"-",INT($Y44/60)&":"&TEXT(MOD($Y44,60),"00")) -> -
A45: AD-00044 | B45: E1020 | C45: Arjun Bhat | D45: 2026-09-14 | E45: Mon | F45: SH-A | G45: SH-A | H45: 12 | I45: 720 | J45: Working | K45: 08:00 | L45: 20:10 | M45: 730 | N45: 60 | O45: 0 | P45: 0 | Q45: All | T45: N | U45: N | X45: =$M45-$O45+$P45 -> 730 | Y45: =IF($M45=0,0,IF($J45="Working",IF($Q45="All",MAX(0,$M45-$I45),0),IF($Q45="None",0,$M45))) -> 10 | Z45: {=IF($J45<>"Working",IF($M45>0,$J45&" — worked",$J45),IF($U45="Y","Present",IF($X45<INDEX('08_Attendance_Rules'!$C$2:$C$5,MATCH($H45,'08_Attendance_Rules'!$A$2:$A$5,0)),"Absent",IF($X45<INDEX('08_Attendance_Rules'!$B$2:$B$5,MATCH($H45,'08_Attendance_Rules'!$A$2:$A$5,0)),"Half Day",IF($T45="Y","Half Day","Present")))))} -> Present | AA45: =IF($X45=0,"-",INT($X45/60)&":"&TEXT(MOD($X45,60),"00")) -> 12:10 | AB45: =IF($Y45=0,"-",INT($Y45/60)&":"&TEXT(MOD($Y45,60),"00")) -> 0:10
A46: AD-00045 | B46: E1020 | C46: Arjun Bhat | D46: 2026-09-15 | E46: Tue | F46: SH-A | G46: SH-A | H46: 12 | I46: 720 | J46: Working | K46: 07:57 | L46: 20:06 | M46: 729 | N46: 60 | O46: 0 | P46: 0 | Q46: All | T46: N | U46: N | X46: =$M46-$O46+$P46 -> 729 | Y46: =IF($M46=0,0,IF($J46="Working",IF($Q46="All",MAX(0,$M46-$I46),0),IF($Q46="None",0,$M46))) -> 9 | Z46: {=IF($J46<>"Working",IF($M46>0,$J46&" — worked",$J46),IF($U46="Y","Present",IF($X46<INDEX('08_Attendance_Rules'!$C$2:$C$5,MATCH($H46,'08_Attendance_Rules'!$A$2:$A$5,0)),"Absent",IF($X46<INDEX('08_Attendance_Rules'!$B$2:$B$5,MATCH($H46,'08_Attendance_Rules'!$A$2:$A$5,0)),"Half Day",IF($T46="Y","Half Day","Present")))))} -> Present | AA46: =IF($X46=0,"-",INT($X46/60)&":"&TEXT(MOD($X46,60),"00")) -> 12:09 | AB46: =IF($Y46=0,"-",INT($Y46/60)&":"&TEXT(MOD($Y46,60),"00")) -> 0:09
A47: AD-00046 | B47: E1022 | C47: Mohan Joseph | D47: 2026-09-01 | E47: Tue | F47: SH-A | G47: SH-A | H47: 12 | I47: 720 | J47: Working | K47: 07:55 | L47: 20:06 | M47: 731 | N47: 60 | O47: 0 | P47: 0 | Q47: All | T47: N | U47: N | X47: =$M47-$O47+$P47 -> 731 | Y47: =IF($M47=0,0,IF($J47="Working",IF($Q47="All",MAX(0,$M47-$I47),0),IF($Q47="None",0,$M47))) -> 11 | Z47: {=IF($J47<>"Working",IF($M47>0,$J47&" — worked",$J47),IF($U47="Y","Present",IF($X47<INDEX('08_Attendance_Rules'!$C$2:$C$5,MATCH($H47,'08_Attendance_Rules'!$A$2:$A$5,0)),"Absent",IF($X47<INDEX('08_Attendance_Rules'!$B$2:$B$5,MATCH($H47,'08_Attendance_Rules'!$A$2:$A$5,0)),"Half Day",IF($T47="Y","Half Day","Present")))))} -> Present | AA47: =IF($X47=0,"-",INT($X47/60)&":"&TEXT(MOD($X47,60),"00")) -> 12:11 | AB47: =IF($Y47=0,"-",INT($Y47/60)&":"&TEXT(MOD($Y47,60),"00")) -> 0:11
A48: AD-00047 | B48: E1022 | C48: Mohan Joseph | D48: 2026-09-02 | E48: Wed | F48: SH-A | G48: SH-A | H48: 12 | I48: 720 | J48: Working | K48: 08:05 | L48: 18:30 | M48: 625 | N48: 60 | O48: 0 | P48: 0 | Q48: All | R48: 5 | T48: N | U48: N | V48: Point 12 — net 9h25m, below 11h30m, half day | X48: =$M48-$O48+$P48 -> 625 | Y48: =IF($M48=0,0,IF($J48="Working",IF($Q48="All",MAX(0,$M48-$I48),0),IF($Q48="None",0,$M48))) -> 0 | Z48: {=IF($J48<>"Working",IF($M48>0,$J48&" — worked",$J48),IF($U48="Y","Present",IF($X48<INDEX('08_Attendance_Rules'!$C$2:$C$5,MATCH($H48,'08_Attendance_Rules'!$A$2:$A$5,0)),"Absent",IF($X48<INDEX('08_Attendance_Rules'!$B$2:$B$5,MATCH($H48,'08_Attendance_Rules'!$A$2:$A$5,0)),"Half Day",IF($T48="Y","Half Day","Present")))))} -> Half Day | AA48: =IF($X48=0,"-",INT($X48/60)&":"&TEXT(MOD($X48,60),"00")) -> 10:25 | AB48: =IF($Y48=0,"-",INT($Y48/60)&":"&TEXT(MOD($Y48,60),"00")) -> -
A49: AD-00048 | B49: E1022 | C49: Mohan Joseph | D49: 2026-09-03 | E49: Thu | F49: SH-A | G49: SH-A | H49: 12 | I49: 720 | J49: Working | K49: 07:53 | L49: 20:03 | M49: 730 | N49: 60 | O49: 0 | P49: 0 | Q49: All | T49: N | U49: N | X49: =$M49-$O49+$P49 -> 730 | Y49: =IF($M49=0,0,IF($J49="Working",IF($Q49="All",MAX(0,$M49-$I49),0),IF($Q49="None",0,$M49))) -> 10 | Z49: {=IF($J49<>"Working",IF($M49>0,$J49&" — worked",$J49),IF($U49="Y","Present",IF($X49<INDEX('08_Attendance_Rules'!$C$2:$C$5,MATCH($H49,'08_Attendance_Rules'!$A$2:$A$5,0)),"Absent",IF($X49<INDEX('08_Attendance_Rules'!$B$2:$B$5,MATCH($H49,'08_Attendance_Rules'!$A$2:$A$5,0)),"Half Day",IF($T49="Y","Half Day","Present")))))} -> Present | AA49: =IF($X49=0,"-",INT($X49/60)&":"&TEXT(MOD($X49,60),"00")) -> 12:10 | AB49: =IF($Y49=0,"-",INT($Y49/60)&":"&TEXT(MOD($Y49,60),"00")) -> 0:10
A50: AD-00049 | B50: E1022 | C50: Mohan Joseph | D50: 2026-09-04 | E50: Fri | F50: SH-A | G50: SH-A | H50: 12 | I50: 720 | J50: Working | K50: 08:00 | L50: 20:14 | M50: 734 | N50: 60 | O50: 0 | P50: 0 | Q50: All | T50: N | U50: N | X50: =$M50-$O50+$P50 -> 734 | Y50: =IF($M50=0,0,IF($J50="Working",IF($Q50="All",MAX(0,$M50-$I50),0),IF($Q50="None",0,$M50))) -> 14 | Z50: {=IF($J50<>"Working",IF($M50>0,$J50&" — worked",$J50),IF($U50="Y","Present",IF($X50<INDEX('08_Attendance_Rules'!$C$2:$C$5,MATCH($H50,'08_Attendance_Rules'!$A$2:$A$5,0)),"Absent",IF($X50<INDEX('08_Attendance_Rules'!$B$2:$B$5,MATCH($H50,'08_Attendance_Rules'!$A$2:$A$5,0)),"Half Day",IF($T50="Y","Half Day","Present")))))} -> Present | AA50: =IF($X50=0,"-",INT($X50/60)&":"&TEXT(MOD($X50,60),"00")) -> 12:14 | AB50: =IF($Y50=0,"-",INT($Y50/60)&":"&TEXT(MOD($Y50,60),"00")) -> 0:14
A51: AD-00050 | B51: E1022 | C51: Mohan Joseph | D51: 2026-09-05 | E51: Sat | F51: SH-A | G51: SH-A | H51: 12 | I51: 720 | J51: Working | K51: 07:56 | L51: 20:08 | M51: 732 | N51: 60 | O51: 0 | P51: 0 | Q51: All | T51: N | U51: N | X51: =$M51-$O51+$P51 -> 732 | Y51: =IF($M51=0,0,IF($J51="Working",IF($Q51="All",MAX(0,$M51-$I51),0),IF($Q51="None",0,$M51))) -> 12 | Z51: {=IF($J51<>"Working",IF($M51>0,$J51&" — worked",$J51),IF($U51="Y","Present",IF($X51<INDEX('08_Attendance_Rules'!$C$2:$C$5,MATCH($H51,'08_Attendance_Rules'!$A$2:$A$5,0)),"Absent",IF($X51<INDEX('08_Attendance_Rules'!$B$2:$B$5,MATCH($H51,'08_Attendance_Rules'!$A$2:$A$5,0)),"Half Day",IF($T51="Y","Half Day","Present")))))} -> Present | AA51: =IF($X51=0,"-",INT($X51/60)&":"&TEXT(MOD($X51,60),"00")) -> 12:12 | AB51: =IF($Y51=0,"-",INT($Y51/60)&":"&TEXT(MOD($Y51,60),"00")) -> 0:12
A52: AD-00051 | B52: E1022 | C52: Mohan Joseph | D52: 2026-09-06 | E52: Sun | F52: SH-A | G52: SH-A | H52: 12 | I52: 720 | J52: Weekly Off | M52: 0 | N52: 0 | O52: 0 | P52: 0 | Q52: All | T52: N | U52: N | X52: =$M52-$O52+$P52 -> 0 | Y52: =IF($M52=0,0,IF($J52="Working",IF($Q52="All",MAX(0,$M52-$I52),0),IF($Q52="None",0,$M52))) -> 0 | Z52: {=IF($J52<>"Working",IF($M52>0,$J52&" — worked",$J52),IF($U52="Y","Present",IF($X52<INDEX('08_Attendance_Rules'!$C$2:$C$5,MATCH($H52,'08_Attendance_Rules'!$A$2:$A$5,0)),"Absent",IF($X52<INDEX('08_Attendance_Rules'!$B$2:$B$5,MATCH($H52,'08_Attendance_Rules'!$A$2:$A$5,0)),"Half Day",IF($T52="Y","Half Day","Present")))))} -> Weekly Off | AA52: =IF($X52=0,"-",INT($X52/60)&":"&TEXT(MOD($X52,60),"00")) -> - | AB52: =IF($Y52=0,"-",INT($Y52/60)&":"&TEXT(MOD($Y52,60),"00")) -> -
A53: AD-00052 | B53: E1022 | C53: Mohan Joseph | D53: 2026-09-07 | E53: Mon | F53: SH-A | G53: SH-A | H53: 12 | I53: 720 | J53: Working | K53: 07:54 | L53: 20:17 | M53: 743 | N53: 60 | O53: 0 | P53: 0 | Q53: All | T53: N | U53: N | X53: =$M53-$O53+$P53 -> 743 | Y53: =IF($M53=0,0,IF($J53="Working",IF($Q53="All",MAX(0,$M53-$I53),0),IF($Q53="None",0,$M53))) -> 23 | Z53: {=IF($J53<>"Working",IF($M53>0,$J53&" — worked",$J53),IF($U53="Y","Present",IF($X53<INDEX('08_Attendance_Rules'!$C$2:$C$5,MATCH($H53,'08_Attendance_Rules'!$A$2:$A$5,0)),"Absent",IF($X53<INDEX('08_Attendance_Rules'!$B$2:$B$5,MATCH($H53,'08_Attendance_Rules'!$A$2:$A$5,0)),"Half Day",IF($T53="Y","Half Day","Present")))))} -> Present | AA53: =IF($X53=0,"-",INT($X53/60)&":"&TEXT(MOD($X53,60),"00")) -> 12:23 | AB53: =IF($Y53=0,"-",INT($Y53/60)&":"&TEXT(MOD($Y53,60),"00")) -> 0:23
A54: AD-00053 | B54: E1022 | C54: Mohan Joseph | D54: 2026-09-08 | E54: Tue | F54: SH-A | G54: SH-A | H54: 12 | I54: 720 | J54: Working | K54: 07:59 | L54: 20:05 | M54: 726 | N54: 60 | O54: 0 | P54: 0 | Q54: All | T54: N | U54: N | X54: =$M54-$O54+$P54 -> 726 | Y54: =IF($M54=0,0,IF($J54="Working",IF($Q54="All",MAX(0,$M54-$I54),0),IF($Q54="None",0,$M54))) -> 6 | Z54: {=IF($J54<>"Working",IF($M54>0,$J54&" — worked",$J54),IF($U54="Y","Present",IF($X54<INDEX('08_Attendance_Rules'!$C$2:$C$5,MATCH($H54,'08_Attendance_Rules'!$A$2:$A$5,0)),"Absent",IF($X54<INDEX('08_Attendance_Rules'!$B$2:$B$5,MATCH($H54,'08_Attendance_Rules'!$A$2:$A$5,0)),"Half Day",IF($T54="Y","Half Day","Present")))))} -> Present | AA54: =IF($X54=0,"-",INT($X54/60)&":"&TEXT(MOD($X54,60),"00")) -> 12:06 | AB54: =IF($Y54=0,"-",INT($Y54/60)&":"&TEXT(MOD($Y54,60),"00")) -> 0:06
A55: AD-00054 | B55: E1022 | C55: Mohan Joseph | D55: 2026-09-09 | E55: Wed | F55: SH-A | G55: SH-A | H55: 12 | I55: 720 | J55: Working | K55: 08:10 | L55: 13:15 | M55: 305 | N55: 0 | O55: 0 | P55: 0 | Q55: All | R55: 10 | T55: N | U55: N | V55: Point 12 — net 5h05m, below 6h30m, absent | X55: =$M55-$O55+$P55 -> 305 | Y55: =IF($M55=0,0,IF($J55="Working",IF($Q55="All",MAX(0,$M55-$I55),0),IF($Q55="None",0,$M55))) -> 0 | Z55: {=IF($J55<>"Working",IF($M55>0,$J55&" — worked",$J55),IF($U55="Y","Present",IF($X55<INDEX('08_Attendance_Rules'!$C$2:$C$5,MATCH($H55,'08_Attendance_Rules'!$A$2:$A$5,0)),"Absent",IF($X55<INDEX('08_Attendance_Rules'!$B$2:$B$5,MATCH($H55,'08_Attendance_Rules'!$A$2:$A$5,0)),"Half Day",IF($T55="Y","Half Day","Present")))))} -> Absent | AA55: =IF($X55=0,"-",INT($X55/60)&":"&TEXT(MOD($X55,60),"00")) -> 5:05 | AB55: =IF($Y55=0,"-",INT($Y55/60)&":"&TEXT(MOD($Y55,60),"00")) -> -
A56: AD-00055 | B56: E1022 | C56: Mohan Joseph | D56: 2026-09-10 | E56: Thu | F56: SH-A | G56: SH-A | H56: 12 | I56: 720 | J56: Working | K56: 08:01 | L56: 20:12 | M56: 731 | N56: 60 | O56: 0 | P56: 0 | Q56: All | R56: 1 | T56: N | U56: N | X56: =$M56-$O56+$P56 -> 731 | Y56: =IF($M56=0,0,IF($J56="Working",IF($Q56="All",MAX(0,$M56-$I56),0),IF($Q56="None",0,$M56))) -> 11 | Z56: {=IF($J56<>"Working",IF($M56>0,$J56&" — worked",$J56),IF($U56="Y","Present",IF($X56<INDEX('08_Attendance_Rules'!$C$2:$C$5,MATCH($H56,'08_Attendance_Rules'!$A$2:$A$5,0)),"Absent",IF($X56<INDEX('08_Attendance_Rules'!$B$2:$B$5,MATCH($H56,'08_Attendance_Rules'!$A$2:$A$5,0)),"Half Day",IF($T56="Y","Half Day","Present")))))} -> Present | AA56: =IF($X56=0,"-",INT($X56/60)&":"&TEXT(MOD($X56,60),"00")) -> 12:11 | AB56: =IF($Y56=0,"-",INT($Y56/60)&":"&TEXT(MOD($Y56,60),"00")) -> 0:11
A57: AD-00056 | B57: E1022 | C57: Mohan Joseph | D57: 2026-09-11 | E57: Fri | F57: SH-A | G57: SH-A | H57: 12 | I57: 720 | J57: Working | K57: 07:52 | L57: 20:04 | M57: 732 | N57: 60 | O57: 0 | P57: 0 | Q57: All | T57: N | U57: N | X57: =$M57-$O57+$P57 -> 732 | Y57: =IF($M57=0,0,IF($J57="Working",IF($Q57="All",MAX(0,$M57-$I57),0),IF($Q57="None",0,$M57))) -> 12 | Z57: {=IF($J57<>"Working",IF($M57>0,$J57&" — worked",$J57),IF($U57="Y","Present",IF($X57<INDEX('08_Attendance_Rules'!$C$2:$C$5,MATCH($H57,'08_Attendance_Rules'!$A$2:$A$5,0)),"Absent",IF($X57<INDEX('08_Attendance_Rules'!$B$2:$B$5,MATCH($H57,'08_Attendance_Rules'!$A$2:$A$5,0)),"Half Day",IF($T57="Y","Half Day","Present")))))} -> Present | AA57: =IF($X57=0,"-",INT($X57/60)&":"&TEXT(MOD($X57,60),"00")) -> 12:12 | AB57: =IF($Y57=0,"-",INT($Y57/60)&":"&TEXT(MOD($Y57,60),"00")) -> 0:12
A58: AD-00057 | B58: E1022 | C58: Mohan Joseph | D58: 2026-09-12 | E58: Sat | F58: SH-A | G58: SH-A | H58: 12 | I58: 720 | J58: Working | K58: 08:02 | L58: 20:19 | M58: 737 | N58: 60 | O58: 0 | P58: 0 | Q58: All | R58: 2 | T58: N | U58: N | X58: =$M58-$O58+$P58 -> 737 | Y58: =IF($M58=0,0,IF($J58="Working",IF($Q58="All",MAX(0,$M58-$I58),0),IF($Q58="None",0,$M58))) -> 17 | Z58: {=IF($J58<>"Working",IF($M58>0,$J58&" — worked",$J58),IF($U58="Y","Present",IF($X58<INDEX('08_Attendance_Rules'!$C$2:$C$5,MATCH($H58,'08_Attendance_Rules'!$A$2:$A$5,0)),"Absent",IF($X58<INDEX('08_Attendance_Rules'!$B$2:$B$5,MATCH($H58,'08_Attendance_Rules'!$A$2:$A$5,0)),"Half Day",IF($T58="Y","Half Day","Present")))))} -> Present | AA58: =IF($X58=0,"-",INT($X58/60)&":"&TEXT(MOD($X58,60),"00")) -> 12:17 | AB58: =IF($Y58=0,"-",INT($Y58/60)&":"&TEXT(MOD($Y58,60),"00")) -> 0:17
A59: AD-00058 | B59: E1022 | C59: Mohan Joseph | D59: 2026-09-13 | E59: Sun | F59: SH-A | G59: SH-A | H59: 12 | I59: 720 | J59: Weekly Off | M59: 0 | N59: 0 | O59: 0 | P59: 0 | Q59: All | T59: N | U59: N | X59: =$M59-$O59+$P59 -> 0 | Y59: =IF($M59=0,0,IF($J59="Working",IF($Q59="All",MAX(0,$M59-$I59),0),IF($Q59="None",0,$M59))) -> 0 | Z59: {=IF($J59<>"Working",IF($M59>0,$J59&" — worked",$J59),IF($U59="Y","Present",IF($X59<INDEX('08_Attendance_Rules'!$C$2:$C$5,MATCH($H59,'08_Attendance_Rules'!$A$2:$A$5,0)),"Absent",IF($X59<INDEX('08_Attendance_Rules'!$B$2:$B$5,MATCH($H59,'08_Attendance_Rules'!$A$2:$A$5,0)),"Half Day",IF($T59="Y","Half Day","Present")))))} -> Weekly Off | AA59: =IF($X59=0,"-",INT($X59/60)&":"&TEXT(MOD($X59,60),"00")) -> - | AB59: =IF($Y59=0,"-",INT($Y59/60)&":"&TEXT(MOD($Y59,60),"00")) -> -
A60: AD-00059 | B60: E1022 | C60: Mohan Joseph | D60: 2026-09-14 | E60: Mon | F60: SH-A | G60: SH-A | H60: 12 | I60: 720 | J60: Working | K60: 08:00 | L60: 20:10 | M60: 730 | N60: 60 | O60: 0 | P60: 0 | Q60: All | T60: N | U60: N | X60: =$M60-$O60+$P60 -> 730 | Y60: =IF($M60=0,0,IF($J60="Working",IF($Q60="All",MAX(0,$M60-$I60),0),IF($Q60="None",0,$M60))) -> 10 | Z60: {=IF($J60<>"Working",IF($M60>0,$J60&" — worked",$J60),IF($U60="Y","Present",IF($X60<INDEX('08_Attendance_Rules'!$C$2:$C$5,MATCH($H60,'08_Attendance_Rules'!$A$2:$A$5,0)),"Absent",IF($X60<INDEX('08_Attendance_Rules'!$B$2:$B$5,MATCH($H60,'08_Attendance_Rules'!$A$2:$A$5,0)),"Half Day",IF($T60="Y","Half Day","Present")))))} -> Present | AA60: =IF($X60=0,"-",INT($X60/60)&":"&TEXT(MOD($X60,60),"00")) -> 12:10 | AB60: =IF($Y60=0,"-",INT($Y60/60)&":"&TEXT(MOD($Y60,60),"00")) -> 0:10
A61: AD-00060 | B61: E1022 | C61: Mohan Joseph | D61: 2026-09-15 | E61: Tue | F61: SH-A | G61: SH-A | H61: 12 | I61: 720 | J61: Working | K61: 07:57 | L61: 20:06 | M61: 729 | N61: 60 | O61: 0 | P61: 0 | Q61: All | T61: N | U61: N | X61: =$M61-$O61+$P61 -> 729 | Y61: =IF($M61=0,0,IF($J61="Working",IF($Q61="All",MAX(0,$M61-$I61),0),IF($Q61="None",0,$M61))) -> 9 | Z61: {=IF($J61<>"Working",IF($M61>0,$J61&" — worked",$J61),IF($U61="Y","Present",IF($X61<INDEX('08_Attendance_Rules'!$C$2:$C$5,MATCH($H61,'08_Attendance_Rules'!$A$2:$A$5,0)),"Absent",IF($X61<INDEX('08_Attendance_Rules'!$B$2:$B$5,MATCH($H61,'08_Attendance_Rules'!$A$2:$A$5,0)),"Half Day",IF($T61="Y","Half Day","Present")))))} -> Present | AA61: =IF($X61=0,"-",INT($X61/60)&":"&TEXT(MOD($X61,60),"00")) -> 12:09 | AB61: =IF($Y61=0,"-",INT($Y61/60)&":"&TEXT(MOD($Y61,60),"00")) -> 0:09
A62: AD-00061 | B62: E1023 | C62: Kavya Venkatesh | D62: 2026-09-01 | E62: Tue | F62: SH-A | G62: SH-A | H62: 12 | I62: 720 | J62: Working | K62: 07:55 | L62: 20:06 | M62: 731 | N62: 60 | O62: 0 | P62: 0 | Q62: All | T62: N | U62: N | X62: =$M62-$O62+$P62 -> 731 | Y62: =IF($M62=0,0,IF($J62="Working",IF($Q62="All",MAX(0,$M62-$I62),0),IF($Q62="None",0,$M62))) -> 11 | Z62: {=IF($J62<>"Working",IF($M62>0,$J62&" — worked",$J62),IF($U62="Y","Present",IF($X62<INDEX('08_Attendance_Rules'!$C$2:$C$5,MATCH($H62,'08_Attendance_Rules'!$A$2:$A$5,0)),"Absent",IF($X62<INDEX('08_Attendance_Rules'!$B$2:$B$5,MATCH($H62,'08_Attendance_Rules'!$A$2:$A$5,0)),"Half Day",IF($T62="Y","Half Day","Present")))))} -> Present | AA62: =IF($X62=0,"-",INT($X62/60)&":"&TEXT(MOD($X62,60),"00")) -> 12:11 | AB62: =IF($Y62=0,"-",INT($Y62/60)&":"&TEXT(MOD($Y62,60),"00")) -> 0:11
A63: AD-00062 | B63: E1023 | C63: Kavya Venkatesh | D63: 2026-09-02 | E63: Wed | F63: SH-A | G63: SH-A | H63: 12 | I63: 720 | J63: Working | K63: 07:58 | L63: 20:11 | M63: 733 | N63: 60 | O63: 0 | P63: 0 | Q63: All | T63: N | U63: N | X63: =$M63-$O63+$P63 -> 733 | Y63: =IF($M63=0,0,IF($J63="Working",IF($Q63="All",MAX(0,$M63-$I63),0),IF($Q63="None",0,$M63))) -> 13 | Z63: {=IF($J63<>"Working",IF($M63>0,$J63&" — worked",$J63),IF($U63="Y","Present",IF($X63<INDEX('08_Attendance_Rules'!$C$2:$C$5,MATCH($H63,'08_Attendance_Rules'!$A$2:$A$5,0)),"Absent",IF($X63<INDEX('08_Attendance_Rules'!$B$2:$B$5,MATCH($H63,'08_Attendance_Rules'!$A$2:$A$5,0)),"Half Day",IF($T63="Y","Half Day","Present")))))} -> Present | AA63: =IF($X63=0,"-",INT($X63/60)&":"&TEXT(MOD($X63,60),"00")) -> 12:13 | AB63: =IF($Y63=0,"-",INT($Y63/60)&":"&TEXT(MOD($Y63,60),"00")) -> 0:13
A64: AD-00063 | B64: E1023 | C64: Kavya Venkatesh | D64: 2026-09-03 | E64: Thu | F64: SH-A | G64: SH-A | H64: 12 | I64: 720 | J64: Working | K64: 07:53 | L64: 20:03 | M64: 730 | N64: 60 | O64: 0 | P64: 0 | Q64: All | T64: N | U64: N | X64: =$M64-$O64+$P64 -> 730 | Y64: =IF($M64=0,0,IF($J64="Working",IF($Q64="All",MAX(0,$M64-$I64),0),IF($Q64="None",0,$M64))) -> 10 | Z64: {=IF($J64<>"Working",IF($M64>0,$J64&" — worked",$J64),IF($U64="Y","Present",IF($X64<INDEX('08_Attendance_Rules'!$C$2:$C$5,MATCH($H64,'08_Attendance_Rules'!$A$2:$A$5,0)),"Absent",IF($X64<INDEX('08_Attendance_Rules'!$B$2:$B$5,MATCH($H64,'08_Attendance_Rules'!$A$2:$A$5,0)),"Half Day",IF($T64="Y","Half Day","Present")))))} -> Present | AA64: =IF($X64=0,"-",INT($X64/60)&":"&TEXT(MOD($X64,60),"00")) -> 12:10 | AB64: =IF($Y64=0,"-",INT($Y64/60)&":"&TEXT(MOD($Y64,60),"00")) -> 0:10
A65: AD-00064 | B65: E1023 | C65: Kavya Venkatesh | D65: 2026-09-04 | E65: Fri | F65: SH-A | G65: SH-A | H65: 12 | I65: 720 | J65: Working | K65: 08:02 | L65: 20:04 | M65: 722 | N65: 0 | O65: 120 | P65: 120 | Q65: All | R65: 2 | T65: N | U65: N | V65: Point 11 — 2h personal gate pass GP-2026-0141, credited to work hours | X65: =$M65-$O65+$P65 -> 722 | Y65: =IF($M65=0,0,IF($J65="Working",IF($Q65="All",MAX(0,$M65-$I65),0),IF($Q65="None",0,$M65))) -> 2 | Z65: {=IF($J65<>"Working",IF($M65>0,$J65&" — worked",$J65),IF($U65="Y","Present",IF($X65<INDEX('08_Attendance_Rules'!$C$2:$C$5,MATCH($H65,'08_Attendance_Rules'!$A$2:$A$5,0)),"Absent",IF($X65<INDEX('08_Attendance_Rules'!$B$2:$B$5,MATCH($H65,'08_Attendance_Rules'!$A$2:$A$5,0)),"Half Day",IF($T65="Y","Half Day","Present")))))} -> Present | AA65: =IF($X65=0,"-",INT($X65/60)&":"&TEXT(MOD($X65,60),"00")) -> 12:02 | AB65: =IF($Y65=0,"-",INT($Y65/60)&":"&TEXT(MOD($Y65,60),"00")) -> 0:02
A66: AD-00065 | B66: E1023 | C66: Kavya Venkatesh | D66: 2026-09-05 | E66: Sat | F66: SH-A | G66: SH-A | H66: 12 | I66: 720 | J66: Working | K66: 07:56 | L66: 20:08 | M66: 732 | N66: 60 | O66: 0 | P66: 0 | Q66: All | T66: N | U66: N | X66: =$M66-$O66+$P66 -> 732 | Y66: =IF($M66=0,0,IF($J66="Working",IF($Q66="All",MAX(0,$M66-$I66),0),IF($Q66="None",0,$M66))) -> 12 | Z66: {=IF($J66<>"Working",IF($M66>0,$J66&" — worked",$J66),IF($U66="Y","Present",IF($X66<INDEX('08_Attendance_Rules'!$C$2:$C$5,MATCH($H66,'08_Attendance_Rules'!$A$2:$A$5,0)),"Absent",IF($X66<INDEX('08_Attendance_Rules'!$B$2:$B$5,MATCH($H66,'08_Attendance_Rules'!$A$2:$A$5,0)),"Half Day",IF($T66="Y","Half Day","Present")))))} -> Present | AA66: =IF($X66=0,"-",INT($X66/60)&":"&TEXT(MOD($X66,60),"00")) -> 12:12 | AB66: =IF($Y66=0,"-",INT($Y66/60)&":"&TEXT(MOD($Y66,60),"00")) -> 0:12
A67: AD-00066 | B67: E1023 | C67: Kavya Venkatesh | D67: 2026-09-06 | E67: Sun | F67: SH-A | G67: SH-A | H67: 12 | I67: 720 | J67: Weekly Off | M67: 0 | N67: 0 | O67: 0 | P67: 0 | Q67: All | T67: N | U67: N | X67: =$M67-$O67+$P67 -> 0 | Y67: =IF($M67=0,0,IF($J67="Working",IF($Q67="All",MAX(0,$M67-$I67),0),IF($Q67="None",0,$M67))) -> 0 | Z67: {=IF($J67<>"Working",IF($M67>0,$J67&" — worked",$J67),IF($U67="Y","Present",IF($X67<INDEX('08_Attendance_Rules'!$C$2:$C$5,MATCH($H67,'08_Attendance_Rules'!$A$2:$A$5,0)),"Absent",IF($X67<INDEX('08_Attendance_Rules'!$B$2:$B$5,MATCH($H67,'08_Attendance_Rules'!$A$2:$A$5,0)),"Half Day",IF($T67="Y","Half Day","Present")))))} -> Weekly Off | AA67: =IF($X67=0,"-",INT($X67/60)&":"&TEXT(MOD($X67,60),"00")) -> - | AB67: =IF($Y67=0,"-",INT($Y67/60)&":"&TEXT(MOD($Y67,60),"00")) -> -
A68: AD-00067 | B68: E1023 | C68: Kavya Venkatesh | D68: 2026-09-07 | E68: Mon | F68: SH-A | G68: SH-A | H68: 12 | I68: 720 | J68: Working | K68: 07:54 | L68: 20:17 | M68: 743 | N68: 60 | O68: 0 | P68: 0 | Q68: All | T68: N | U68: N | X68: =$M68-$O68+$P68 -> 743 | Y68: =IF($M68=0,0,IF($J68="Working",IF($Q68="All",MAX(0,$M68-$I68),0),IF($Q68="None",0,$M68))) -> 23 | Z68: {=IF($J68<>"Working",IF($M68>0,$J68&" — worked",$J68),IF($U68="Y","Present",IF($X68<INDEX('08_Attendance_Rules'!$C$2:$C$5,MATCH($H68,'08_Attendance_Rules'!$A$2:$A$5,0)),"Absent",IF($X68<INDEX('08_Attendance_Rules'!$B$2:$B$5,MATCH($H68,'08_Attendance_Rules'!$A$2:$A$5,0)),"Half Day",IF($T68="Y","Half Day","Present")))))} -> Present | AA68: =IF($X68=0,"-",INT($X68/60)&":"&TEXT(MOD($X68,60),"00")) -> 12:23 | AB68: =IF($Y68=0,"-",INT($Y68/60)&":"&TEXT(MOD($Y68,60),"00")) -> 0:23
A69: AD-00068 | B69: E1023 | C69: Kavya Venkatesh | D69: 2026-09-08 | E69: Tue | F69: SH-A | G69: SH-A | H69: 12 | I69: 720 | J69: Working | K69: 07:59 | L69: 20:05 | M69: 726 | N69: 60 | O69: 0 | P69: 0 | Q69: All | T69: N | U69: N | X69: =$M69-$O69+$P69 -> 726 | Y69: =IF($M69=0,0,IF($J69="Working",IF($Q69="All",MAX(0,$M69-$I69),0),IF($Q69="None",0,$M69))) -> 6 | Z69: {=IF($J69<>"Working",IF($M69>0,$J69&" — worked",$J69),IF($U69="Y","Present",IF($X69<INDEX('08_Attendance_Rules'!$C$2:$C$5,MATCH($H69,'08_Attendance_Rules'!$A$2:$A$5,0)),"Absent",IF($X69<INDEX('08_Attendance_Rules'!$B$2:$B$5,MATCH($H69,'08_Attendance_Rules'!$A$2:$A$5,0)),"Half Day",IF($T69="Y","Half Day","Present")))))} -> Present | AA69: =IF($X69=0,"-",INT($X69/60)&":"&TEXT(MOD($X69,60),"00")) -> 12:06 | AB69: =IF($Y69=0,"-",INT($Y69/60)&":"&TEXT(MOD($Y69,60),"00")) -> 0:06
A70: AD-00069 | B70: E1023 | C70: Kavya Venkatesh | D70: 2026-09-09 | E70: Wed | F70: SH-A | G70: SH-A | H70: 12 | I70: 720 | J70: Working | K70: 07:57 | L70: 20:09 | M70: 732 | N70: 60 | O70: 0 | P70: 0 | Q70: All | T70: N | U70: N | X70: =$M70-$O70+$P70 -> 732 | Y70: =IF($M70=0,0,IF($J70="Working",IF($Q70="All",MAX(0,$M70-$I70),0),IF($Q70="None",0,$M70))) -> 12 | Z70: {=IF($J70<>"Working",IF($M70>0,$J70&" — worked",$J70),IF($U70="Y","Present",IF($X70<INDEX('08_Attendance_Rules'!$C$2:$C$5,MATCH($H70,'08_Attendance_Rules'!$A$2:$A$5,0)),"Absent",IF($X70<INDEX('08_Attendance_Rules'!$B$2:$B$5,MATCH($H70,'08_Attendance_Rules'!$A$2:$A$5,0)),"Half Day",IF($T70="Y","Half Day","Present")))))} -> Present | AA70: =IF($X70=0,"-",INT($X70/60)&":"&TEXT(MOD($X70,60),"00")) -> 12:12 | AB70: =IF($Y70=0,"-",INT($Y70/60)&":"&TEXT(MOD($Y70,60),"00")) -> 0:12
A71: AD-00070 | B71: E1023 | C71: Kavya Venkatesh | D71: 2026-09-10 | E71: Thu | F71: SH-A | G71: SH-A | H71: 12 | I71: 720 | J71: Working | K71: 08:01 | L71: 20:12 | M71: 731 | N71: 60 | O71: 0 | P71: 0 | Q71: All | R71: 1 | T71: N | U71: N | X71: =$M71-$O71+$P71 -> 731 | Y71: =IF($M71=0,0,IF($J71="Working",IF($Q71="All",MAX(0,$M71-$I71),0),IF($Q71="None",0,$M71))) -> 11 | Z71: {=IF($J71<>"Working",IF($M71>0,$J71&" — worked",$J71),IF($U71="Y","Present",IF($X71<INDEX('08_Attendance_Rules'!$C$2:$C$5,MATCH($H71,'08_Attendance_Rules'!$A$2:$A$5,0)),"Absent",IF($X71<INDEX('08_Attendance_Rules'!$B$2:$B$5,MATCH($H71,'08_Attendance_Rules'!$A$2:$A$5,0)),"Half Day",IF($T71="Y","Half Day","Present")))))} -> Present | AA71: =IF($X71=0,"-",INT($X71/60)&":"&TEXT(MOD($X71,60),"00")) -> 12:11 | AB71: =IF($Y71=0,"-",INT($Y71/60)&":"&TEXT(MOD($Y71,60),"00")) -> 0:11
A72: AD-00071 | B72: E1023 | C72: Kavya Venkatesh | D72: 2026-09-11 | E72: Fri | F72: SH-A | G72: SH-A | H72: 12 | I72: 720 | J72: Working | K72: 08:06 | L72: 20:08 | M72: 722 | N72: 0 | O72: 120 | P72: 120 | Q72: All | R72: 6 | T72: N | U72: N | V72: Point 11 — 2h gate pass GP-2026-0155, monthly ceiling of 4h now reached | X72: =$M72-$O72+$P72 -> 722 | Y72: =IF($M72=0,0,IF($J72="Working",IF($Q72="All",MAX(0,$M72-$I72),0),IF($Q72="None",0,$M72))) -> 2 | Z72: {=IF($J72<>"Working",IF($M72>0,$J72&" — worked",$J72),IF($U72="Y","Present",IF($X72<INDEX('08_Attendance_Rules'!$C$2:$C$5,MATCH($H72,'08_Attendance_Rules'!$A$2:$A$5,0)),"Absent",IF($X72<INDEX('08_Attendance_Rules'!$B$2:$B$5,MATCH($H72,'08_Attendance_Rules'!$A$2:$A$5,0)),"Half Day",IF($T72="Y","Half Day","Present")))))} -> Present | AA72: =IF($X72=0,"-",INT($X72/60)&":"&TEXT(MOD($X72,60),"00")) -> 12:02 | AB72: =IF($Y72=0,"-",INT($Y72/60)&":"&TEXT(MOD($Y72,60),"00")) -> 0:02
A73: AD-00072 | B73: E1023 | C73: Kavya Venkatesh | D73: 2026-09-12 | E73: Sat | F73: SH-A | G73: SH-A | H73: 12 | I73: 720 | J73: Working | K73: 08:02 | L73: 20:19 | M73: 737 | N73: 60 | O73: 0 | P73: 0 | Q73: All | R73: 2 | T73: N | U73: N | X73: =$M73-$O73+$P73 -> 737 | Y73: =IF($M73=0,0,IF($J73="Working",IF($Q73="All",MAX(0,$M73-$I73),0),IF($Q73="None",0,$M73))) -> 17 | Z73: {=IF($J73<>"Working",IF($M73>0,$J73&" — worked",$J73),IF($U73="Y","Present",IF($X73<INDEX('08_Attendance_Rules'!$C$2:$C$5,MATCH($H73,'08_Attendance_Rules'!$A$2:$A$5,0)),"Absent",IF($X73<INDEX('08_Attendance_Rules'!$B$2:$B$5,MATCH($H73,'08_Attendance_Rules'!$A$2:$A$5,0)),"Half Day",IF($T73="Y","Half Day","Present")))))} -> Present | AA73: =IF($X73=0,"-",INT($X73/60)&":"&TEXT(MOD($X73,60),"00")) -> 12:17 | AB73: =IF($Y73=0,"-",INT($Y73/60)&":"&TEXT(MOD($Y73,60),"00")) -> 0:17
A74: AD-00073 | B74: E1023 | C74: Kavya Venkatesh | D74: 2026-09-13 | E74: Sun | F74: SH-A | G74: SH-A | H74: 12 | I74: 720 | J74: Weekly Off | M74: 0 | N74: 0 | O74: 0 | P74: 0 | Q74: All | T74: N | U74: N | X74: =$M74-$O74+$P74 -> 0 | Y74: =IF($M74=0,0,IF($J74="Working",IF($Q74="All",MAX(0,$M74-$I74),0),IF($Q74="None",0,$M74))) -> 0 | Z74: {=IF($J74<>"Working",IF($M74>0,$J74&" — worked",$J74),IF($U74="Y","Present",IF($X74<INDEX('08_Attendance_Rules'!$C$2:$C$5,MATCH($H74,'08_Attendance_Rules'!$A$2:$A$5,0)),"Absent",IF($X74<INDEX('08_Attendance_Rules'!$B$2:$B$5,MATCH($H74,'08_Attendance_Rules'!$A$2:$A$5,0)),"Half Day",IF($T74="Y","Half Day","Present")))))} -> Weekly Off | AA74: =IF($X74=0,"-",INT($X74/60)&":"&TEXT(MOD($X74,60),"00")) -> - | AB74: =IF($Y74=0,"-",INT($Y74/60)&":"&TEXT(MOD($Y74,60),"00")) -> -
A75: AD-00074 | B75: E1023 | C75: Kavya Venkatesh | D75: 2026-09-14 | E75: Mon | F75: SH-A | G75: SH-A | H75: 12 | I75: 720 | J75: Working | K75: 08:00 | L75: 20:10 | M75: 730 | N75: 60 | O75: 0 | P75: 0 | Q75: All | T75: N | U75: N | X75: =$M75-$O75+$P75 -> 730 | Y75: =IF($M75=0,0,IF($J75="Working",IF($Q75="All",MAX(0,$M75-$I75),0),IF($Q75="None",0,$M75))) -> 10 | Z75: {=IF($J75<>"Working",IF($M75>0,$J75&" — worked",$J75),IF($U75="Y","Present",IF($X75<INDEX('08_Attendance_Rules'!$C$2:$C$5,MATCH($H75,'08_Attendance_Rules'!$A$2:$A$5,0)),"Absent",IF($X75<INDEX('08_Attendance_Rules'!$B$2:$B$5,MATCH($H75,'08_Attendance_Rules'!$A$2:$A$5,0)),"Half Day",IF($T75="Y","Half Day","Present")))))} -> Present | AA75: =IF($X75=0,"-",INT($X75/60)&":"&TEXT(MOD($X75,60),"00")) -> 12:10 | AB75: =IF($Y75=0,"-",INT($Y75/60)&":"&TEXT(MOD($Y75,60),"00")) -> 0:10
A76: AD-00075 | B76: E1023 | C76: Kavya Venkatesh | D76: 2026-09-15 | E76: Tue | F76: SH-A | G76: SH-A | H76: 12 | I76: 720 | J76: Working | K76: 07:57 | L76: 20:06 | M76: 729 | N76: 60 | O76: 0 | P76: 0 | Q76: All | T76: N | U76: N | X76: =$M76-$O76+$P76 -> 729 | Y76: =IF($M76=0,0,IF($J76="Working",IF($Q76="All",MAX(0,$M76-$I76),0),IF($Q76="None",0,$M76))) -> 9 | Z76: {=IF($J76<>"Working",IF($M76>0,$J76&" — worked",$J76),IF($U76="Y","Present",IF($X76<INDEX('08_Attendance_Rules'!$C$2:$C$5,MATCH($H76,'08_Attendance_Rules'!$A$2:$A$5,0)),"Absent",IF($X76<INDEX('08_Attendance_Rules'!$B$2:$B$5,MATCH($H76,'08_Attendance_Rules'!$A$2:$A$5,0)),"Half Day",IF($T76="Y","Half Day","Present")))))} -> Present | AA76: =IF($X76=0,"-",INT($X76/60)&":"&TEXT(MOD($X76,60),"00")) -> 12:09 | AB76: =IF($Y76=0,"-",INT($Y76/60)&":"&TEXT(MOD($Y76,60),"00")) -> 0:09
A77: AD-00076 | B77: E1026 | C77: Manjunath Poojary | D77: 2026-09-01 | E77: Tue | F77: SH-B | G77: SH-B | H77: 12 | I77: 720 | J77: Working | K77: 19:55 | L77: 08:06 | M77: 731 | N77: 60 | O77: 0 | P77: 0 | Q77: All | T77: N | U77: N | X77: =$M77-$O77+$P77 -> 731 | Y77: =IF($M77=0,0,IF($J77="Working",IF($Q77="All",MAX(0,$M77-$I77),0),IF($Q77="None",0,$M77))) -> 11 | Z77: {=IF($J77<>"Working",IF($M77>0,$J77&" — worked",$J77),IF($U77="Y","Present",IF($X77<INDEX('08_Attendance_Rules'!$C$2:$C$5,MATCH($H77,'08_Attendance_Rules'!$A$2:$A$5,0)),"Absent",IF($X77<INDEX('08_Attendance_Rules'!$B$2:$B$5,MATCH($H77,'08_Attendance_Rules'!$A$2:$A$5,0)),"Half Day",IF($T77="Y","Half Day","Present")))))} -> Present | AA77: =IF($X77=0,"-",INT($X77/60)&":"&TEXT(MOD($X77,60),"00")) -> 12:11 | AB77: =IF($Y77=0,"-",INT($Y77/60)&":"&TEXT(MOD($Y77,60),"00")) -> 0:11
A78: AD-00077 | B78: E1026 | C78: Manjunath Poojary | D78: 2026-09-02 | E78: Wed | F78: SH-B | G78: SH-B | H78: 12 | I78: 720 | J78: Working | K78: 19:58 | L78: 08:11 | M78: 733 | N78: 60 | O78: 0 | P78: 0 | Q78: All | T78: N | U78: N | X78: =$M78-$O78+$P78 -> 733 | Y78: =IF($M78=0,0,IF($J78="Working",IF($Q78="All",MAX(0,$M78-$I78),0),IF($Q78="None",0,$M78))) -> 13 | Z78: {=IF($J78<>"Working",IF($M78>0,$J78&" — worked",$J78),IF($U78="Y","Present",IF($X78<INDEX('08_Attendance_Rules'!$C$2:$C$5,MATCH($H78,'08_Attendance_Rules'!$A$2:$A$5,0)),"Absent",IF($X78<INDEX('08_Attendance_Rules'!$B$2:$B$5,MATCH($H78,'08_Attendance_Rules'!$A$2:$A$5,0)),"Half Day",IF($T78="Y","Half Day","Present")))))} -> Present | AA78: =IF($X78=0,"-",INT($X78/60)&":"&TEXT(MOD($X78,60),"00")) -> 12:13 | AB78: =IF($Y78=0,"-",INT($Y78/60)&":"&TEXT(MOD($Y78,60),"00")) -> 0:13
A79: AD-00078 | B79: E1026 | C79: Manjunath Poojary | D79: 2026-09-03 | E79: Thu | F79: SH-B | G79: SH-B | H79: 12 | I79: 720 | J79: Working | K79: 19:53 | L79: 08:03 | M79: 730 | N79: 60 | O79: 0 | P79: 0 | Q79: All | T79: N | U79: N | X79: =$M79-$O79+$P79 -> 730 | Y79: =IF($M79=0,0,IF($J79="Working",IF($Q79="All",MAX(0,$M79-$I79),0),IF($Q79="None",0,$M79))) -> 10 | Z79: {=IF($J79<>"Working",IF($M79>0,$J79&" — worked",$J79),IF($U79="Y","Present",IF($X79<INDEX('08_Attendance_Rules'!$C$2:$C$5,MATCH($H79,'08_Attendance_Rules'!$A$2:$A$5,0)),"Absent",IF($X79<INDEX('08_Attendance_Rules'!$B$2:$B$5,MATCH($H79,'08_Attendance_Rules'!$A$2:$A$5,0)),"Half Day",IF($T79="Y","Half Day","Present")))))} -> Present | AA79: =IF($X79=0,"-",INT($X79/60)&":"&TEXT(MOD($X79,60),"00")) -> 12:10 | AB79: =IF($Y79=0,"-",INT($Y79/60)&":"&TEXT(MOD($Y79,60),"00")) -> 0:10
A80: AD-00079 | B80: E1026 | C80: Manjunath Poojary | D80: 2026-09-04 | E80: Fri | F80: SH-B | G80: SH-B | H80: 12 | I80: 720 | J80: Working | K80: 20:00 | L80: 08:14 | M80: 734 | N80: 60 | O80: 0 | P80: 0 | Q80: All | T80: N | U80: N | X80: =$M80-$O80+$P80 -> 734 | Y80: =IF($M80=0,0,IF($J80="Working",IF($Q80="All",MAX(0,$M80-$I80),0),IF($Q80="None",0,$M80))) -> 14 | Z80: {=IF($J80<>"Working",IF($M80>0,$J80&" — worked",$J80),IF($U80="Y","Present",IF($X80<INDEX('08_Attendance_Rules'!$C$2:$C$5,MATCH($H80,'08_Attendance_Rules'!$A$2:$A$5,0)),"Absent",IF($X80<INDEX('08_Attendance_Rules'!$B$2:$B$5,MATCH($H80,'08_Attendance_Rules'!$A$2:$A$5,0)),"Half Day",IF($T80="Y","Half Day","Present")))))} -> Present | AA80: =IF($X80=0,"-",INT($X80/60)&":"&TEXT(MOD($X80,60),"00")) -> 12:14 | AB80: =IF($Y80=0,"-",INT($Y80/60)&":"&TEXT(MOD($Y80,60),"00")) -> 0:14
